Workbook

Sheet Sheet4
IU65534: English 4.1

Sheet Sheet3

Sheet Sheet2

Sheet Instructions
A1: 4.2
B2: AWWA Water Loss Control Committee (WLCC) Free Water Audit Software v4.2
C4: PURPOSE: This spreadsheet-based water audit tool is designed to help quantify and track water losses associated with water distribution systems and identify areas for improved efficiency and cost recovery. It provides a "top-down" summary water audit format, and is not meant to take the place of a full-scale, comprehensive water audit format.
C7: USE: The spreadsheet contains several separate worksheets. Sheets can be accessed using the tabs towards the bottom of the screen, or by clicking the buttons on the left below. Descriptions of each sheet are also given below.
C10: THE FOLLOWING KEY APPLIES THROUGHOUT: | G10: Value can be entered by user
G12: Value calculated based on input data
G14: These cells contain recommended default values
C16: Please begin by providing the following information, then proceed through each sheet in the workbook:
C18: NAME OF CITY OR UTILITY: | D18: Lehighton Water Authority | I18: COUNTRY: | J18: United Stetes
C20: REPORTING YEAR: | D20: 2013 | F20: START DATE(MM/YYYY): | G20: 41275 | I20: END DATE(MM/YYYY): | K20: 41609
C22: NAME OF CONTACT PERSON: | D22: Armen Galasso | F22: E-MAIL: | G22: waterlwa@ptd.net | K22: TELEPHONE: | M22: 6103771912
L23: Ext.
C24: PLEASE SELECT PREFERRED REPORTING UNITS FOR WATER VOLUME: | G24: Million gallons (US)
C26: Click to advance to sheet… | G26: Click here: for help about units and conversions
D27: The current sheet
D29: Enter the required data on this worksheet to calculate the water balance
D31: The values entered in the Reporting Worksheet are used to populate the water balance
D33: Depending on the confidence of audit inputs, a grading is assigned to the audit score
D35: Diagrams depicting possible customer service connection configurations
D37: Use this sheet to understand terms used in the audit process
D39: Use this sheet to interpret the results of the audit validity score and performance indicators
C41: Comments: | D41: D-89-93 CP
K45: If you have questions or comments regarding the software please contact us at: | L45: wlc@awwa.org

Sheet Reporting Worksheet
A1: 0
B2: AWWA WLCC Free Water Audit Software: Reporting Worksheet
C4: Water Audit Report for: | D4: =IF(ISBLANK(Instructions!D18),"",Instructions!D18) -> Lehighton Water Authority
C5: Reporting Year: | D5: =IF(ISBLANK(Instructions!D20),"",Instructions!D20) -> 2013 | G5: =IF(OR(ISBLANK(Instructions!G20),ISBLANK(Instructions!K20)),"",MONTH(Instructions!G20)&"/"&YEAR(Instructions!G20)&" - "&MONTH(Instructions!K20)&"/"&YEAR(Instructions!K20)) -> 1/2013 - 12/2013
G9: =IF(ISBLANK(Instructions!G24),"PLEASE CHOOSE REPORTING UNITS FROM THE INSTRUCTIONS SHEET BEFORE ENTERING DATA","All volumes to be entered as: "&UPPER(Instructions!$G$24)&" PER YEAR") -> All volumes to be entered as: MILLION GALLONS (US) PER YEAR
C12: WATER SUPPLIED | D12: << Enter grading in column 'E'
C14: Volume from own sources: | E14: 7 | G14: 285.656 | I14: =IF(Instructions!$G$24="Million gallons (US)","Million gallons (US)/yr (MG/Yr)",IF(Instructions!$G$24="Megalitres (thousand cubic metres)","Megalitres/yr (or ML/Yr)",IF(Instructions!$G$24="Acre-feet","acre-ft/yr",""))) -> Million gallons (US)/yr (MG/Yr)
C15: Master meter error adjustment (enter positive value): | E15: 1 | G15: 0 | K15: =IF(AND(NOT(ISBLANK(G15)),G15>0,ISBLANK(I15)),"<---Enter adjustment type",IF(Instructions!$G$24="million gallons (US)","MG/Yr",IF(Instructions!$G$24="Megalitres (thousand cubic metres)","ML/Yr",IF(Instructions!$G$24="acre-feet","acre-ft/yr","")))) -> MG/Yr
C16: Water imported: | E16: n/a | G16: 0 | I16: =IF(Instructions!$G$24="million gallons (US)","MG/Yr",IF(Instructions!$G$24="Megalitres (thousand cubic metres)","ML/Yr",IF(Instructions!$G$24="acre-feet","acre-ft/yr",""))) -> MG/Yr | J16: =IF(AND(G14=G16,G19<>0),"Volume identical to own sources","")
C17: Water exported: | E17: n/a | G17: 0 | I17: =IF(Instructions!$G$24="million gallons (US)","MG/Yr",IF(Instructions!$G$24="Megalitres (thousand cubic metres)","ML/Yr",IF(Instructions!$G$24="acre-feet","acre-ft/yr",""))) -> MG/Yr
C19: WATER SUPPLIED: | G19: =G14+IF(I15="under-registered",+G15,IF(I15="over-registered",-G15,))+G16-G17 -> 285.656 | I19: =IF(Instructions!$G$24="million gallons (US)","MG/Yr",IF(Instructions!$G$24="Megalitres (thousand cubic metres)","ML/Yr",IF(Instructions!$G$24="acre-feet","acre-ft/yr",""))) -> MG/Yr
E21: .
C22: AUTHORIZED CONSUMPTION
C23: Billed metered: | E23: 6 | G23: 161.2 | I23: =IF(Instructions!$G$24="million gallons (US)","MG/Yr",IF(Instructions!$G$24="Megalitres (thousand cubic metres)","ML/Yr",IF(Instructions!$G$24="acre-feet","acre-ft/yr",""))) -> MG/Yr
C24: Billed unmetered: | E24: n/a | G24: 0 | I24: =IF(Instructions!$G$24="million gallons (US)","MG/Yr",IF(Instructions!$G$24="Megalitres (thousand cubic metres)","ML/Yr",IF(Instructions!$G$24="acre-feet","acre-ft/yr",""))) -> MG/Yr
C25: Unbilled metered: | E25: 9 | G25: 1.467 | I25: =IF(Instructions!$G$24="million gallons (US)","MG/Yr",IF(Instructions!$G$24="Megalitres (thousand cubic metres)","ML/Yr",IF(Instructions!$G$24="acre-feet","acre-ft/yr",""))) -> MG/Yr | J25: Pcnt: | L25: Value:
C26: Unbilled unmetered: | G26: =IF(OR(P26=1,AND(P26=2,L26=0)),J26*$G$19,L26) -> 3.5707 | I26: =IF(Instructions!$G$24="million gallons (US)","MG/Yr",IF(Instructions!$G$24="Megalitres (thousand cubic metres)","ML/Yr",IF(Instructions!$G$24="acre-feet","acre-ft/yr",""))) -> MG/Yr | J26: 0.0125 | P26: 1
L27: 24061
C28: =IF(P26=1," Default option selected for Unbilled unmetered - a grading of 5 is applied but not displayed",IF(P26=2,IF(L26>0.125*G19," Unbilled Unmetered volume entered is greater than the recommended default value",IF(L26=0,"Enter a positive value, otherwise a default percentage of 1.25% and a grading of 5 is applied","")))) -> Default option selected for Unbilled unmetered - a grading of 5 is applied but not displayed
C30: AUTHORIZED CONSUMPTION: | G30: =SUM(G23:G26) -> 166.2377 | I30: =IF(Instructions!$G$24="million gallons (US)","MG/Yr",IF(Instructions!$G$24="Megalitres (thousand cubic metres)","ML/Yr",IF(Instructions!$G$24="acre-feet","acre-ft/yr",""))) -> MG/Yr
C32: =IF(AND(G30>=G19,(G30<>0))," Check input values; WATER SUPPLIED should be greater than AUTHORIZED CONSUMPTION","")
C35: WATER LOSSES (Water Supplied - Authorized Consumption) | G35: =G19-G30 -> 119.4183 | I35: =IF(Instructions!$G$24="million gallons (US)","MG/Yr",IF(Instructions!$G$24="Megalitres (thousand cubic metres)","ML/Yr",IF(Instructions!$G$24="acre-feet","acre-ft/yr",""))) -> MG/Yr
C37: Apparent Losses | J37: Pcnt: | L37: Value:
C38: Unauthorized consumption: | G38: =IF(P38=1,J38*$G$19,L38) -> 0.71414 | I38: =IF(Instructions!$G$24="million gallons (US)","MG/Yr",IF(Instructions!$G$24="Megalitres (thousand cubic metres)","ML/Yr",IF(Instructions!$G$24="acre-feet","acre-ft/yr",""))) -> MG/Yr | J38: 0.0025 | P38: 1
C40: =IF(P38=1," Default option selected for unauthorized consumption - a grading of 5 is applied but not displayed ",IF(P38=2,IF(L38>0.025*G19,"Unauthorized consumption volume entered is greater than the recommended default value",IF(L38=0,"Enter a positive value, otherwise a default percentage of 0.25% and a grading of 5 is applied","")))) -> Default option selected for unauthorized consumption - a grading of 5 is applied but not displayed
C42: Customer metering inaccuracies: | E42: 3 | G42: =IF(P42=1,((G23+G25)/(1-J42))-(G23+G25),L42) -> 8.5614211 | I42: =IF(Instructions!$G$24="million gallons (US)","MG/Yr",IF(Instructions!$G$24="Megalitres (thousand cubic metres)","ML/Yr",IF(Instructions!$G$24="acre-feet","acre-ft/yr",""))) -> MG/Yr | J42: 0.05 | P42: 1
C43: Systematic data handling errors: | E43: 4 | G43: 0 | I43: =IF(Instructions!$G$24="million gallons (US)","MG/Yr",IF(Instructions!$G$24="Megalitres (thousand cubic metres)","ML/Yr",IF(Instructions!$G$24="acre-feet","acre-ft/yr",""))) -> MG/Yr
L44: =IF(AND($P$42=1,ISBLANK($J$42)),"Enter a percentage less than 10% in the red cell (J42), or select 'Value' option","Choose this option to enter a percentage of billed metered consumption. This is NOT a default value") -> Choose this option to enter a percentage of billed metered consumption. This is NOT a default value
C45: =IF(OR(G19=0,E43="n/a"),"",IF(OR(ISBLANK(G43),G43=0),"Systematic data handling errors are likely, please enter a non-zero value; otherwise grade = 5","")) -> Systematic data handling errors are likely, please enter a non-zero value; otherwise grade = 5
C47: Apparent Losses: | G47: =G38+G42+G43 -> 9.2755611
C49: =IF(AND(G47>=G35,(G47<>0)),"Check input values; APPARENT LOSSES should be less than WATER LOSSES","")
C51: Real Losses (Current Annual Real Losses or CARL)
C52: Real Losses = Water Losses - Apparent Losses: | G52: =G19-(G30+G47) -> 110.14274 | I52: =IF(Instructions!$G$24="million gallons (US)","MG/Yr",IF(Instructions!$G$24="Megalitres (thousand cubic metres)","ML/Yr",IF(Instructions!$G$24="acre-feet","acre-ft/yr",""))) -> MG/Yr
C54: WATER LOSSES: | G54: =G47+G52 -> 119.4183 | I54: =IF(Instructions!$G$24="million gallons (US)","MG/Yr",IF(Instructions!$G$24="Megalitres (thousand cubic metres)","ML/Yr",IF(Instructions!$G$24="acre-feet","acre-ft/yr",""))) -> MG/Yr
C57: NON-REVENUE WATER
C58: NON-REVENUE WATER: | G58: =G47+G52+G25+G26 -> 124.456 | I58: =IF(Instructions!$G$24="million gallons (US)","MG/Yr",IF(Instructions!$G$24="Megalitres (thousand cubic metres)","ML/Yr",IF(Instructions!$G$24="acre-feet","acre-ft/yr",""))) -> MG/Yr
C59: = Total Water Loss + Unbilled Metered + Unbilled Unmetered
C60: SYSTEM DATA
C62: Length of mains: | E62: 3 | G62: 43 | I62: =IF(ISBLANK(Instructions!$G$24),"",IF(Instructions!$G$24="Megalitres (thousand cubic metres)","kilometers","miles")) -> miles
C63: Number of active AND inactive service connections: | E63: 3 | G63: 3700
C64: Connection density: | G64: =IF(ISERROR(G63/G62),"",G63/G62) -> 86.046512 | I64: =IF(ISBLANK(Instructions!$G$24),"",IF(Instructions!$G$24="Megalitres (thousand cubic metres)","conn./km","conn./mile")& " main") -> conn./mile main
C65: Average length of customer service line: | E65: 3 | G65: 100 | I65: =IF(ISBLANK(Instructions!$G$24),"",IF(Instructions!G24="Megalitres (thousand cubic metres)","metres","ft")) -> ft
C67: Average operating pressure: | E67: 2 | G67: 65 | I67: =IF(ISBLANK(Instructions!$G$24),"",IF(Instructions!G24="Megalitres (thousand cubic metres)","metres (head)","psi")) -> psi
C69: =IF(ISBLANK(G67),"",IF(OR(AND(P69=1,G67<=25),AND(P69<>1,G67<=40)),"Note: Average pressure this low will not allow for calculation of UARL","")) | P69: =IF(Instructions!G24="Megalitres (thousand cubic metres)",1,0) -> 0
C72: COST DATA
C74: Total annual cost of operating water system: | E74: 8 | G74: 1240000 | I74: $/Year
C75: Customer retail unit cost (applied to Apparent Losses): | E75: 8 | G75: 14.31 | I75: $/1000 gallons (US) | L75: =IF(AND(NOT(ISBLANK(G75)),ISBLANK(I75)),"<--Enter units","")
C76: Variable production cost (applied to Real Losses): | E76: 8 | G76: 334.02 | I76: ="$/"&IF(Instructions!$G$24="million gallons (US)","Million gallons",IF(Instructions!$G$24="Megalitres (thousand cubic metres)","Megalitre",IF(Instructions!$G$24="acre-feet","acre-ft",""))) -> $/Million gallons
C78: =IF(OR(ISBLANK(I75),ISBLANK(I76),ISBLANK(G76)),"",IF(G75*INDEX(Sheet1!B2:D4,MATCH(Instructions!G24,Sheet1!A2:A4,0),MATCH(I75,Sheet1!B1:D1,0))/G76>1,"","Retail costs are less than (or equal to) production costs; please review and correct if necessary")) | P78: =IF(OR(ISBLANK(I75),ISBLANK(I76),ISBLANK(G76)),"",IF(G75*INDEX(Sheet1!B2:D4,MATCH(Instructions!G24,Sheet1!A2:A4,0),MATCH(I75,Sheet1!B1:D1,0))/G76>1,0,1)) -> 0
C81: PERFORMANCE INDICATORS
C83: Financial Indicators
G84: Non-revenue water as percent by volume of Water Supplied: | I84: =IF(ISERROR(1/G19),"",(G25+G26+G47+G52)/G19) -> 0.43568488
G85: Non-revenue water as percent by cost of operating system: | I85: =IF(ISERROR(1/G74),"",(((G25+G26+G52)*G76)+(G47*G75*INDEX(Sheet1!B2:D4,MATCH(Instructions!G24,Sheet1!A2:A4,0),MATCH(I75,Sheet1!B1:D1,0))))/G74) -> 0.13806923
G86: Annual cost of Apparent Losses: | I86: =IF(ISBLANK(I75),"",(G47*G75)*INDEX(Sheet1!B2:D4,MATCH(Instructions!G24,Sheet1!A2:A4,0),MATCH('Reporting Worksheet'!I75:J75,Sheet1!B1:D1,0))) -> 132733.28
G87: Annual cost of Real Losses: | I87: =IF(ISBLANK(G76),"",G52*G76) -> 36789.878
C89: Operational Efficiency Indicators
G91: Apparent Losses per service connection per day: | I91: =IF(ISERROR(1/G63),"",IF(Instructions!$G$24="Acre-feet",G47*325851/1000000,G47)*1000000/365/G63) -> 6.8682422 | J91: =IF(ISBLANK(Instructions!$G$24),"",IF(Instructions!$G$24="Megalitres (thousand cubic metres)","litres","gallons")&"/connection/day") -> gallons/connection/day
G93: Real Losses per service connection per day*: | I93: =IF(ISERROR(1/G63),"",IF(Instructions!$G$24="Megalitres (thousand cubic metres)",IF(G64>20,G52*1000000/365/G63,"N/A"),IF(G64>32,IF(Instructions!$G$24="Million gallons (US)",G52*1000000,G52*325851)/365/G63,"N/A"))) -> 81.557008 | J93: =IF(ISBLANK(Instructions!$G$24),"",IF(Instructions!$G$24="Megalitres (thousand cubic metres)","litres","gallons")&"/connection/day") -> gallons/connection/day
G95: Real Losses per length of main per day*: | I95: =IF(ISERROR(1/G62),"",IF(I93="N/A",IF(Instructions!$G$24="Acre-feet",G52*325851/1000000,G52)*1000000/365/G62,"N/A")) -> N/A | J95: =IF(ISBLANK(Instructions!$G$24),"",IF(I95="N/A","",IF(Instructions!$G$24="Megalitres (thousand cubic metres)","litres/km","gallons/mile")&"/day"))
G97: ="Real Losses per service connection per day per "& IF(I67="psi","psi pressure","meter (head) pressure")&":" -> Real Losses per service connection per day per psi pressure: | I97: =IF(ISERROR(I93/G67),"",I93/G67) -> 1.2547232 | J97: =IF(ISBLANK(Instructions!$G$24),"",IF(Instructions!$G$24="Megalitres (thousand cubic metres)","litres/connection/day/m","gallons/connection/day/psi")) -> gallons/connection/day/psi
G99: Unavoidable Annual Real Losses (UARL): | I99: =IF(ISBLANK(Instructions!$G$24),"",IF(Instructions!$G$24="Megalitres (thousand cubic metres)",IF(AND(G67>=25,G62*20+G63>3000),(((18*G62)+(0.8*G63)+(25*(G63*G65/1000)))*G67/1000000)*365,"Not valid"),IF(AND(G67>=35,G62*32+G63>3000),(((5.41*G62)+(0.15*G63)+(7.5*(G63*G65/5280)))*G67)/IF(Instructions!$G$24="Million gallons (US)",1000000,325851.427242)*365,"Not Valid"))) -> 31.155627 | J99: =IF(OR(ISBLANK(Instructions!$G$24),I99="Not Valid"),"",IF(Instructions!$G$24="Megalitres (thousand cubic metres)","ML",IF(Instructions!$G$24="Acre-feet", "acre-feet","million gallons"))&"/year") -> million gallons/year
C101: =IF(I99="Not Valid","*** UARL cannot be calculated as either average pressure, number of connecions or length of mains is too small: SEE UARL DEFINITION ***","")
G103: From Above, Real Losses = Current Annual Real Losses (CARL): | I103: =IF(ISBLANK(Instructions!$G$24),"",G52) -> 110.14274 | J103: =IF(OR(ISBLANK(Instructions!$G$24),I99="Not Valid"),"",IF(Instructions!$G$24="Megalitres (thousand cubic metres)","ML",IF(Instructions!$G$24="Acre-feet", "acre-feet","million gallons"))&"/year") -> million gallons/year
C105: Infrastructure Leakage Index (ILI) [CARL/UARL]: | I105: =IF(ISERROR(1/I99),"",I103/I99) -> 3.5352439
C107: * only the most applicable of these two indicators will be calculated
C108: WATER AUDIT DATA VALIDITY SCORE:
C110: =IF(GradingAssessment!M22<=0,"*** YOUR SCORE IS: "&ROUND(GradingAssessment!G22,0)&" out of 100 ***",IF(GradingAssessment!M22>0,"Add a grading value for "&GradingAssessment!M22&" parameter(s) to enable an audit score to be calculated")) -> *** YOUR SCORE IS: 65 out of 100 *** | P110: =GradingAssessment!M22 -> 0
C112: =IF(GradingAssessment!M22<=0,"A weighted scale for the components of consumption and water loss is included in the calculation of the Water Audit Data Validity Score","") -> A weighted scale for the components of consumption and water loss is included in the calculation of the Water Audit Data Validity Score
C113: PRIORITY AREAS FOR ATTENTION:
C114: Based on the information provided, audit accuracy can be improved by addressing the following components:
C115: =" 1: "&VLOOKUP(1,GradingAssessment!$I$4:$J$21,2,FALSE) -> 1: Volume from own sources
C117: =" 2: "&VLOOKUP(2,GradingAssessment!$I$4:$J$21,2,FALSE) -> 2: Customer metering inaccuracies
C119: =" 3: "&VLOOKUP(3,GradingAssessment!$I$4:$J$21,2,FALSE) -> 3: Billed metered

Sheet Water Balance
B2: AWWA WLCC Free Water Audit Software: Water Balance | F2: Water Audit Report For: | G2: Report Yr:
F3: =IF(ISBLANK(Instructions!D18),"",Instructions!D18) -> Lehighton Water Authority | G3: =IF(ISBLANK(Instructions!D20),"",Instructions!D20) -> 2013
E4: =IF(ISBLANK(Instructions!H24),"","All Units in "&Instructions!H24)
C5: Water Exported | F5: Billed Water Exported
C6: ='Reporting Worksheet'!G17 -> 0
E7: Billed Authorized Consumption | F7: Billed Metered Consumption (inc. water exported) | G7: Revenue Water
F8: ='Reporting Worksheet'!G23 -> 161.2
B9: Own Sources | D9: Authorized Consumption | E9: ='Reporting Worksheet'!G23+'Reporting Worksheet'!G24 -> 161.2 | F9: Billed Unmetered Consumption | G9: =SUM(F8+F10) -> 161.2
B10: (Adjusted for known errors) | F10: ='Reporting Worksheet'!G24 -> 0
D11: ='Reporting Worksheet'!G30 -> 166.2377 | E11: Unbilled Authorized Consumption | F11: Unbilled Metered Consumption | G11: Non-Revenue Water (NRW)
F12: ='Reporting Worksheet'!G25 -> 1.467
B13: ='Reporting Worksheet'!G14+IF('Reporting Worksheet'!I15="under-registered",+'Reporting Worksheet'!G15,IF('Reporting Worksheet'!I15="over-registered",-'Reporting Worksheet'!G15,)) -> 285.656 | E13: ='Reporting Worksheet'!G25+'Reporting Worksheet'!G26 -> 5.0377 | F13: Unbilled Unmetered Consumption
F14: ='Reporting Worksheet'!G26 -> 3.5707
C15: Water Supplied | F15: Unauthorized Consumption | G15: ='Reporting Worksheet'!G25+'Reporting Worksheet'!G26+'Reporting Worksheet'!G47+'Reporting Worksheet'!G52 -> 124.456
E16: Apparent Losses | F16: ='Reporting Worksheet'!G38 -> 0.71414
C17: ='Reporting Worksheet'!G19 -> 285.656 | E17: ='Reporting Worksheet'!G47 -> 9.2755611 | F17: Customer Metering Inaccuracies
F18: ='Reporting Worksheet'!G42 -> 8.5614211
F19: Systematic Data Handling Errors
D20: Water Losses | F20: ='Reporting Worksheet'!G43 -> 0
B21: Water Imported | D21: ='Reporting Worksheet'!G54 -> 119.4183 | F21: Leakage on Transmission and/or Distribution Mains
E22: Real Losses | F22: Not broken down
B23: ='Reporting Worksheet'!G16 -> 0 | E23: ='Reporting Worksheet'!G52 -> 110.14274 | F23: Leakage and Overflows at Utility's Storage Tanks
F24: Not broken down
F25: Leakage on Service Connections
F26: Not broken down

Sheet GradingAssessment
G2: Score
C3: Grade | D3: Weight | E3: adjWeight | F3: adjFactor | G3: Grade*Weight | H3: droppedPts | I3: uniqueRank | K3: Needs grade | L3: Has grade | M3: Grade Problem
B4: Volume from own sources: | C4: =IF('Reporting Worksheet'!E14="n/a",0,'Reporting Worksheet'!E14) -> 7 | D4: =IF('Reporting Worksheet'!G14=0,0,IF('Reporting Worksheet'!G14>'Reporting Worksheet'!G16,20,8)) -> 20 | E4: =D4/$D$23 -> 28.169014 | F4: =IF(D4<>0,E4/10,0) -> 2.8169014 | G4: =C4*F4 -> 19.71831 | H4: =IF(F4=0,0,E4-G4) -> 8.4507042 | I4: {=SUM(1*(H4<$H$4:$H$21))+1+IF(ROW(H4)-ROW($H$4)=0,0,SUM(1*(H4=OFFSET($H$4,0,0,INDEX(ROW(H4)-ROW($H$4)+1,1)-1,1))))} -> 1 | J4: Volume from own sources | K4: =IF(D4<>0,1,0) -> 1 | L4: =IF(C4>0,1,0) -> 1 | M4: =IF(AND(K4=1,L4=0),1,0) -> 0
B5: Master meter error adjustment: | C5: =IF('Reporting Worksheet'!E15="n/a",0,'Reporting Worksheet'!E15) -> 1 | D5: =IF('Reporting Worksheet'!G15=0,0,8) -> 0 | E5: =D5/$D$23 -> 0 | F5: =IF(D5<>0,E5/10,0) -> 0 | G5: =C5*F5 -> 0 | H5: =IF(F5=0,0,E5-G5) -> 0 | I5: {=SUM(1*(H5<$H$4:$H$21))+1+IF(ROW(H5)-ROW($H$4)=0,0,SUM(1*(H5=OFFSET($H$4,0,0,INDEX(ROW(H5)-ROW($H$4)+1,1)-1,1))))} -> 15 | J5: Master meter error adjustment | K5: =IF(D5<>0,1,0) -> 0 | L5: =IF(C5>0,1,0) -> 1 | M5: =IF(AND(K5=1,L5=0),1,0) -> 0
B6: Water imported: | C6: =IF('Reporting Worksheet'!E16="n/a",0,'Reporting Worksheet'!E16) -> 0 | D6: =IF('Reporting Worksheet'!G16=0,0,IF('Reporting Worksheet'!G16>'Reporting Worksheet'!G14,20,8)) -> 0 | E6: =D6/$D$23 -> 0 | F6: =IF(D6<>0,E6/10,0) -> 0 | G6: =C6*F6 -> 0 | H6: =IF(F6=0,0,E6-G6) -> 0 | I6: {=SUM(1*(H6<$H$4:$H$21))+1+IF(ROW(H6)-ROW($H$4)=0,0,SUM(1*(H6=OFFSET($H$4,0,0,INDEX(ROW(H6)-ROW($H$4)+1,1)-1,1))))} -> 16 | J6: Water imported | K6: =IF(D6<>0,1,0) -> 0 | L6: =IF(C6>0,1,0) -> 0 | M6: =IF(AND(K6=1,L6=0),1,0) -> 0
B7: Water exported: | C7: =IF('Reporting Worksheet'!E17="n/a",0,'Reporting Worksheet'!E17) -> 0 | D7: =IF('Reporting Worksheet'!G17=0,0,8) -> 0 | E7: =D7/$D$23 -> 0 | F7: =IF(D7<>0,E7/10,0) -> 0 | G7: =C7*F7 -> 0 | H7: =IF(F7=0,0,E7-G7) -> 0 | I7: {=SUM(1*(H7<$H$4:$H$21))+1+IF(ROW(H7)-ROW($H$4)=0,0,SUM(1*(H7=OFFSET($H$4,0,0,INDEX(ROW(H7)-ROW($H$4)+1,1)-1,1))))} -> 17 | J7: Water exported | K7: =IF(D7<>0,1,0) -> 0 | L7: =IF(C7>0,1,0) -> 0 | M7: =IF(AND(K7=1,L7=0),1,0) -> 0
B8: Billed metered: | C8: =IF('Reporting Worksheet'!E23="n/a",0,'Reporting Worksheet'!E23) -> 6 | D8: =IF(AND('Reporting Worksheet'!E23="n/a",'Reporting Worksheet'!G23=0),0,8) -> 8 | E8: =D8/$D$23 -> 11.267606 | F8: =IF(D8<>0,E8/10,0) -> 1.1267606 | G8: =C8*F8 -> 6.7605634 | H8: =IF(F8=0,0,E8-G8) -> 4.5070423 | I8: {=SUM(1*(H8<$H$4:$H$21))+1+IF(ROW(H8)-ROW($H$4)=0,0,SUM(1*(H8=OFFSET($H$4,0,0,INDEX(ROW(H8)-ROW($H$4)+1,1)-1,1))))} -> 3 | J8: Billed metered | K8: =IF(D8<>0,1,0) -> 1 | L8: =IF(C8>0,1,0) -> 1 | M8: =IF(AND(K8=1,L8=0),1,0) -> 0
B9: Billed unmetered: | C9: =IF('Reporting Worksheet'!E24="n/a",0,'Reporting Worksheet'!E24) -> 0 | D9: =IF('Reporting Worksheet'!G24=0,0,6) -> 0 | E9: =D9/$D$23 -> 0 | F9: =IF(D9<>0,E9/10,0) -> 0 | G9: =C9*F9 -> 0 | H9: =IF(F9=0,0,E9-G9) -> 0 | I9: {=SUM(1*(H9<$H$4:$H$21))+1+IF(ROW(H9)-ROW($H$4)=0,0,SUM(1*(H9=OFFSET($H$4,0,0,INDEX(ROW(H9)-ROW($H$4)+1,1)-1,1))))} -> 18 | J9: Billed unmetered | K9: =IF(D9<>0,1,0) -> 0 | L9: =IF(C9>0,1,0) -> 0 | M9: =IF(AND(K9=1,L9=0),1,0) -> 0
B10: Unbilled metered: | C10: =IF('Reporting Worksheet'!E25="n/a",0,'Reporting Worksheet'!E25) -> 9 | D10: =IF('Reporting Worksheet'!G25=0,0,6) -> 6 | E10: =D10/$D$23 -> 8.4507042 | F10: =IF(D10<>0,E10/10,0) -> 0.84507042 | G10: =C10*F10 -> 7.6056338 | H10: =IF(F10=0,0,E10-G10) -> 0.84507042 | I10: {=SUM(1*(H10<$H$4:$H$21))+1+IF(ROW(H10)-ROW($H$4)=0,0,SUM(1*(H10=OFFSET($H$4,0,0,INDEX(ROW(H10)-ROW($H$4)+1,1)-1,1))))} -> 13 | J10: Unbilled metered | K10: =IF(D10<>0,1,0) -> 1 | L10: =IF(C10>0,1,0) -> 1 | M10: =IF(AND(K10=1,L10=0),1,0) -> 0
A11: D | B11: Unbilled unmetered: | C11: =IF(OR('Reporting Worksheet'!P26=1,AND('Reporting Worksheet'!P26=2,'Reporting Worksheet'!L26=0)),5,'Reporting Worksheet'!E26) -> 5 | D11: 1 | E11: =D11/$D$23 -> 1.4084507 | F11: =IF(D11<>0,E11/10,0) -> 0.14084507 | G11: =C11*F11 -> 0.70422535 | H11: =IF(F11=0,0,E11-G11) -> 0.70422535 | I11: {=SUM(1*(H11<$H$4:$H$21))+1+IF(ROW(H11)-ROW($H$4)=0,0,SUM(1*(H11=OFFSET($H$4,0,0,INDEX(ROW(H11)-ROW($H$4)+1,1)-1,1))))} -> 14 | J11: Unbilled unmetered | K11: =IF(D11<>0,1,0) -> 1 | L11: =IF(C11>0,1,0) -> 1 | M11: =IF(AND(K11=1,L11=0),1,0) -> 0
A12: D | B12: Unauthorized consumption: | C12: =IF(OR('Reporting Worksheet'!P38=1,AND('Reporting Worksheet'!P38=2,'Reporting Worksheet'!L38=0)),5,'Reporting Worksheet'!E38) -> 5 | D12: 4 | E12: =D12/$D$23 -> 5.6338028 | F12: =IF(D12<>0,E12/10,0) -> 0.56338028 | G12: =C12*F12 -> 2.8169014 | H12: =IF(F12=0,0,E12-G12) -> 2.8169014 | I12: {=SUM(1*(H12<$H$4:$H$21))+1+IF(ROW(H12)-ROW($H$4)=0,0,SUM(1*(H12=OFFSET($H$4,0,0,INDEX(ROW(H12)-ROW($H$4)+1,1)-1,1))))} -> 4 | J12: Unauthorized consumption | K12: =IF(D12<>0,1,0) -> 1 | L12: =IF(C12>0,1,0) -> 1 | M12: =IF(AND(K12=1,L12=0),1,0) -> 0
B13: Customer metering inaccuracies: | C13: =IF('Reporting Worksheet'!E42="n/a",0,'Reporting Worksheet'!E42) -> 3 | D13: =IF(AND('Reporting Worksheet'!E42="n/a",'Reporting Worksheet'!G42=0),0,6) -> 6 | E13: =D13/$D$23 -> 8.4507042 | F13: =IF(D13<>0,E13/10,0) -> 0.84507042 | G13: =C13*F13 -> 2.5352113 | H13: =IF(F13=0,0,E13-G13) -> 5.915493 | I13: {=SUM(1*(H13<$H$4:$H$21))+1+IF(ROW(H13)-ROW($H$4)=0,0,SUM(1*(H13=OFFSET($H$4,0,0,INDEX(ROW(H13)-ROW($H$4)+1,1)-1,1))))} -> 2 | J13: Customer metering inaccuracies | K13: =IF(D13<>0,1,0) -> 1 | L13: =IF(C13>0,1,0) -> 1 | M13: =IF(AND(K13=1,L13=0),1,0) -> 0
B14: Systematic data handling errors: | C14: =IF('Reporting Worksheet'!E43="n/a",0,IF('Reporting Worksheet'!G43=0,5,'Reporting Worksheet'!E43)) -> 5 | D14: 4 | E14: =D14/$D$23 -> 5.6338028 | F14: =IF(D14<>0,E14/10,0) -> 0.56338028 | G14: =C14*F14 -> 2.8169014 | H14: =IF(F14=0,0,E14-G14) -> 2.8169014 | I14: {=SUM(1*(H14<$H$4:$H$21))+1+IF(ROW(H14)-ROW($H$4)=0,0,SUM(1*(H14=OFFSET($H$4,0,0,INDEX(ROW(H14)-ROW($H$4)+1,1)-1,1))))} -> 5 | J14: Systematic data handling errors | K14: =IF(D14<>0,1,0) -> 1 | L14: =IF(C14>0,1,0) -> 1 | M14: =IF(AND(K14=1,L14=0),1,0) -> 0
B15: Length of mains: | C15: ='Reporting Worksheet'!E62 -> 3 | D15: 1 | E15: =D15/$D$23 -> 1.4084507 | F15: =IF(D15<>0,E15/10,0) -> 0.14084507 | G15: =C15*F15 -> 0.42253521 | H15: =IF(F15=0,0,E15-G15) -> 0.98591549 | I15: {=SUM(1*(H15<$H$4:$H$21))+1+IF(ROW(H15)-ROW($H$4)=0,0,SUM(1*(H15=OFFSET($H$4,0,0,INDEX(ROW(H15)-ROW($H$4)+1,1)-1,1))))} -> 10 | J15: Length of mains | K15: =IF(D15<>0,1,0) -> 1 | L15: =IF(C15>0,1,0) -> 1 | M15: =IF(AND(K15=1,L15=0),1,0) -> 0
B16: Number of active AND inactive service connections: | C16: ='Reporting Worksheet'!E63 -> 3 | D16: 1 | E16: =D16/$D$23 -> 1.4084507 | F16: =IF(D16<>0,E16/10,0) -> 0.14084507 | G16: =C16*F16 -> 0.42253521 | H16: =IF(F16=0,0,E16-G16) -> 0.98591549 | I16: {=SUM(1*(H16<$H$4:$H$21))+1+IF(ROW(H16)-ROW($H$4)=0,0,SUM(1*(H16=OFFSET($H$4,0,0,INDEX(ROW(H16)-ROW($H$4)+1,1)-1,1))))} -> 11 | J16: Number of active AND inactive service connections | K16: =IF(D16<>0,1,0) -> 1 | L16: =IF(C16>0,1,0) -> 1 | M16: =IF(AND(K16=1,L16=0),1,0) -> 0
B17: Average length of customer service line: | C17: =IF('Reporting Worksheet'!E65="n/a",0,'Reporting Worksheet'!E65) -> 3 | D17: 1 | E17: =D17/$D$23 -> 1.4084507 | F17: =IF(D17<>0,E17/10,0) -> 0.14084507 | G17: =C17*F17 -> 0.42253521 | H17: =IF(F17=0,0,E17-G17) -> 0.98591549 | I17: {=SUM(1*(H17<$H$4:$H$21))+1+IF(ROW(H17)-ROW($H$4)=0,0,SUM(1*(H17=OFFSET($H$4,0,0,INDEX(ROW(H17)-ROW($H$4)+1,1)-1,1))))} -> 12 | J17: Average length of customer service line | K17: =IF(D17<>0,1,0) -> 1 | L17: =IF(C17>0,1,0) -> 1 | M17: =IF(AND(K17=1,L17=0),1,0) -> 0
B18: Average operating pressure: | C18: ='Reporting Worksheet'!E67 -> 2 | D18: 1 | E18: =D18/$D$23 -> 1.4084507 | F18: =IF(D18<>0,E18/10,0) -> 0.14084507 | G18: =C18*F18 -> 0.28169014 | H18: =IF(F18=0,0,E18-G18) -> 1.1267606 | I18: {=SUM(1*(H18<$H$4:$H$21))+1+IF(ROW(H18)-ROW($H$4)=0,0,SUM(1*(H18=OFFSET($H$4,0,0,INDEX(ROW(H18)-ROW($H$4)+1,1)-1,1))))} -> 9 | J18: Average operating pressure | K18: =IF(D18<>0,1,0) -> 1 | L18: =IF(C18>0,1,0) -> 1 | M18: =IF(AND(K18=1,L18=0),1,0) -> 0
B19: Total annual cost of operating water system: | C19: ='Reporting Worksheet'!E74 -> 8 | D19: 6 | E19: =D19/$D$23 -> 8.4507042 | F19: =IF(D19<>0,E19/10,0) -> 0.84507042 | G19: =C19*F19 -> 6.7605634 | H19: =IF(F19=0,0,E19-G19) -> 1.6901408 | I19: {=SUM(1*(H19<$H$4:$H$21))+1+IF(ROW(H19)-ROW($H$4)=0,0,SUM(1*(H19=OFFSET($H$4,0,0,INDEX(ROW(H19)-ROW($H$4)+1,1)-1,1))))} -> 6 | J19: Total annual cost of operating water system | K19: =IF(D19<>0,1,0) -> 1 | L19: =IF(C19>0,1,0) -> 1 | M19: =IF(AND(K19=1,L19=0),1,0) -> 0
B20: Customer retail unit cost (applied to Apparent Losses): | C20: ='Reporting Worksheet'!E75 -> 8 | D20: 6 | E20: =D20/$D$23 -> 8.4507042 | F20: =IF(D20<>0,E20/10,0) -> 0.84507042 | G20: =C20*F20 -> 6.7605634 | H20: =IF(F20=0,0,E20-G20) -> 1.6901408 | I20: {=SUM(1*(H20<$H$4:$H$21))+1+IF(ROW(H20)-ROW($H$4)=0,0,SUM(1*(H20=OFFSET($H$4,0,0,INDEX(ROW(H20)-ROW($H$4)+1,1)-1,1))))} -> 7 | J20: Customer retail unit cost (applied to Apparent Losses) | K20: =IF(D20<>0,1,0) -> 1 | L20: =IF(C20>0,1,0) -> 1 | M20: =IF(AND(K20=1,L20=0),1,0) -> 0
B21: Variable production cost (applied to Real Losses): | C21: =IF('Reporting Worksheet'!E76="n/a",0,'Reporting Worksheet'!E76) -> 8 | D21: 6 | E21: =D21/$D$23 -> 8.4507042 | F21: =IF(D21<>0,E21/10,0) -> 0.84507042 | G21: =C21*F21 -> 6.7605634 | H21: =IF(F21=0,0,E21-G21) -> 1.6901408 | I21: {=SUM(1*(H21<$H$4:$H$21))+1+IF(ROW(H21)-ROW($H$4)=0,0,SUM(1*(H21=OFFSET($H$4,0,0,INDEX(ROW(H21)-ROW($H$4)+1,1)-1,1))))} -> 8 | J21: Variable production cost (applied to Real Losses) | K21: =IF(D21<>0,1,0) -> 1 | L21: =IF(C21>0,1,0) -> 1 | M21: =IF(AND(K21=1,L21=0),1,0) -> 0
D22: =SUM(D4:D21) -> 71 | E22: =SUM(E4:E21) -> 100 | F22: =SUM(F4:F21) -> 10 | G22: =SUM(G4:G21) -> 64.788732 | M22: =SUM(M4:M21) -> 0
D23: =D22/100 -> 0.71
B25: Enter criteria in these cells | L25: =IF(SUM('Reporting Worksheet'!P26,'Reporting Worksheet'!P38)=2,2,IF(SUM('Reporting Worksheet'!P26,'Reporting Worksheet'!P38)=3,1,0)) -> 2 | M25: default(s) being used

Sheet Grading Matrix
C2: AWWA WLCC Free Water Audit Software: Grading Matrix
R3: =VLOOKUP(1,GradingAssessment!$I$4:$J$21,2,FALSE)&":" -> Volume from own sources:
C4: In the Reporting Worksheet, grades were assigned to each component of the audit to describe the confidence and accuracy of the input data. The grading assigned to each audit component and the corresponding recommended improvements and actions are highlighted in yellow. Audit accuracy is likely to be improved by prioritizing those items shown in red | R4: =VLOOKUP(2,GradingAssessment!$I$4:$J$21,2,FALSE)&":" -> Customer metering inaccuracies:
R5: =VLOOKUP(3,GradingAssessment!$I$4:$J$21,2,FALSE)&":" -> Billed metered:
C6: Grading
D7: n/a | E7: 1 | F7: 2 | G7: 3 | H7: 4 | I7: 5 | J7: 6 | K7: 7 | L7: 8 | M7: 9 | N7: 10
C9: Volume from own sources: | D9: Select this grading only if the water utility purchases/imports all of its water resources (i.e. has no sources of its own) | E9: Less than 25% of water production sources are metered, remaining sources are estimated. No regular meter accuracy testing. | F9: 25% - 50% of treated water production sources are metered; other sources estimated. No regular meter accuracy testing. | G9: Conditions between 2 and 4 | H9: 50% - 75% of treated water production sources are metered, other sources estimated. Occasional meter accuracy testing | I9: Conditions between 4 and 6 | J9: At least 75% of treated water production sources are metered, or at least 90% of the source flow is derived from metered sources. Meter accuracy testing and/or electronic calibration conducted annually. Less than 25% of tested meters are found outside of +/- 6% accuracy. | K9: Conditions between 6 and 8 | L9: 100% of treated water production sources are metered, meter accuracy testing and electronic calibration conducted annually, less than 10% of meters are found outside of +/- 6% accuracy | M9: Conditions between 8 and 10 | N9: 100% of treated water production sources are metered, meter accuracy testing and electronic calibration conducted semi-annually, with less than 10% found outside of +/- 3% accuracy. | Q9: ='Reporting Worksheet'!E14 -> 7 | R9: =IF(OR(C9=$R$3,C9=$R$4,C9=$R$5),1,0) -> 1
C10: Improvements to attain higher data grading for "Volume from own Sources" component: | E10: to qualify for 2: Organize efforts to begin to collect data for determining volume from own sources | F10: to qualify for 4: Locate all water production sources on maps and in field, launch meter accuracy testing for existing meters, begin to install meters on unmetered water production sources and replace any obsolete/defective meters | H10: to qualify for 6: Formalize annual meter accuracy testing for all source meters. Complete installation of meters on unmetered water production sources and complete replacement of all obsolete/defective meters. | J10: to qualify for 8: Conduct annual meter accuracy testing on all meters. Complete project to install new, or replace defective existing, meters so that entire production meter population is metered. Repair or replace meters outside of +/- 6% accuracy. | L10: to qualify for 10: Maintain annual meter accuracy testing for all meters. Repair or replace meters outside of +/- 6% accuracy. Investigate new meter technology; pilot one or more replacements with innovative meters in attempt to improve meter accuracy. | N10: to maintain 10: Standardize meter accuracy test frequency to semi-annual, or more frequent, for all meters. Repair or replace meters outside of +/- 3% accuracy. Continually investigate/pilot improving metering technology. | Q10: =Q9 -> 7
C11: Master meter error adjustment: | D11: Select n/a only if the water utility fails to have meters on its sources of supply, either its own source, and/or imported (purchased) water sources | E11: Inventory information on meters and paper records of measured volumes in crude condition; data error cannot be determined | F11: No automatic datalogging of production volumes; daily readings are scribed on paper records. Tank/storage elevation changes are not employed in calculating "Volume from own sources" component. Data is adjusted only when grossly evident data error occurs. | G11: Conditions between 2 and 4 | H11: Production meter data is logged automatically in electronic format and reviewed at least on a monthly basis. "Volume from own sources" tabulations include estimate of daily changes in tanks/storage facilities. Meter data is adjusted when gross data errors occur, or occasional meter testing deems this necessary. | I11: Conditions between 4 and 6 | J11: Hourly production meter data logged automatically & reviewed on at least a weekly basis. Data adjusted to correct gross error from equipment malfunction and error confirmed by meter accuracy testing. Tank/storage facility elevation changes are automatically used in calculating a balanced "Volume from own sources" component. | K11: Conditions between 6 and 8 | L11: Continuous production meter data logged automatically & reviewed daily. Data adjusted to correct gross error from equipment malfunction & results of meter accuracy testing. Tank/storage facility elevation changes are automatically used in "Volume from own sources" tabulations. | M11: Conditions between 8 and 10 | N11: Computerized system (SCADA or similar) automatically balances flows from all sources and storages; results reviewed daily. Mass balance technique compares production meter data to raw (untreated) water and treatment volumes to detect anomalies. Regular calibrations between SCADA and sources meters ensures minimal data transfer error. | Q11: ='Reporting Worksheet'!E15 -> 1 | R11: =IF(OR(C11=$R$3,C11=$R$4,C11=$R$5),1,0) -> 0
C12: Improvements to attain higher data grading for "Master meter error adjustment" component: | E12: to qualify for 2: Develop plan to restructure recordkeeping system to capture all flow data; set procedure to review data daily to detect input errors | F12: to qualify for 4: Install automatic datalogging equipment on production meters. Identify tanks/storage facilities and include estimated daily volume of water added to, or subtracted from, "Water Supplied" volume based upon changes in storage | H12: to qualify for 6: Review hourly production meter data for gross error on, at least, a weekly basis. Begin to install instrumentation on tanks/storage facilities to record elevation changes. Use daily net storage change to balance flows in calculating "Water Supplied" volume. | J12: to qualify for 8: Complete installation of elevation instrumentation on all tanks/storage facilities. Continue to use daily net storage change in calculating balanced "Volume from own sources" component. Adjust production meter data for gross error and inaccuracy confirmed by testing. | L12: to qualify for 10: Link all production and tank/storage facility elevation change data to a Supervisory Control & Data Acquisition (SCADA) System, or similar computerized monitoring/control system, and establish automatic flow balancing algorithm and regularly calibrate between SCADA and source meters. | N12: to maintain 10: Monitor meter innovations for development of more accurate and less expensive flowmeters. Continue to replace or repair meters as they perform outside of desired accuracy limits. | Q12: =Q11 -> 1
C13: Water Imported: | D13: Select n/a if the water utility's supply is exclusively from its own water resources (no bulk purchased/ imported water) | E13: Less than 25% of imported water sources are metered, remaining sources are estimated. No regular meter accuracy testing. | F13: 25% - 50% of imported water sources are metered; other sources estimated. No regular meter accuracy testing. | G13: Conditions between 2 and 4 | H13: 50% - 75% of imported water sources are metered, other sources estimated. Occasional meter accuracy testing | I13: Conditions between 4 and 6 | J13: At least 75% of imported water sources are metered, meter accuracy testing and/or electronic calibration conducted annually. Less than 25% of tested meters are found outside of +/- 6% accuracy. | K13: Conditions between 6 and 8 | L13: 100% of imported water sources are metered, meter accuracy testing and/or electronic calibration conducted annually, less than 10% of meters are found outside of +/- 6% accuracy | M13: Conditions between 8 and 10 | N13: 100% of imported water sources are metered, meter accuracy testing and/or electronic calibration conducted semi-annually, with less than 10% found outside of +/- 3% accuracy. | Q13: ='Reporting Worksheet'!E16 -> n/a | R13: =IF(OR(C13=$R$3,C13=$R$4,C13=$R$5),1,0) -> 0
C14: Improvements to attain higher data grading for "Water Imported Volume" component: | E14: to qualify for 2: Review bulk water purchase agreements with partner suppliers; confirm requirements for use and maintenance of accurate metering. Identify needs for new or replacement meters with goal to meter all imported water sources. | F14: To qualify for 4: Locate all imported water sources on maps and in field, launch meter accuracy testing for existing meters, begin to install meters on unmetered imported water interconnections and replace obsolete/defective meters | H14: to qualify for 6: Formalize annual meter accuracy testing for all imported water meters. Continue installation of meters on unmetered exported water interconnections and replacement of obsolete/defective meters. | J14: to qualify for 8: Complete project to install new, or replace defective, meters on all imported water interconnections. Maintain annual meter accuracy testing for all imported water meters. Repair or replace meters outside of +/- 6% accuracy. | L14: to qualify for 10: Maintain annual meter accuracy testing for all meters. Repair or replace meters outside of +/- 6% accuracy. Investigate new meter technology; pilot one or more replacements with innovative meters in attempt to improve meter accuracy. | N14: to maintain 10: Standardize meter accuracy test frequency to semi-annual, or more frequent, for all meters. Repair or replace meters outside of +/- 3% accuracy. Continually investigate/pilot improving metering technology. | Q14: =Q13 -> n/a
C15: Water Exported: | D15: Select n/a if the water utility sells no bulk water to neighboring water utilities (no exported water sales) | E15: Less than 25% of exported water sources are metered, remaining sources are estimated. No regular meter accuracy testing. | F15: 25% - 50% of exported water sources are metered; other sources estimated. No regular meter accuracy testing. | G15: Conditions between 2 and 4 | H15: 50% - 75% of exported water sources are metered, other sources estimated. Occasional meter accuracy testing | I15: Conditions between 4 and 6 | J15: At least 75% of exported water sources are metered, meter accuracy testing and/or electronic calibration conducted annually. Less than 25% of tested meters are found outside of +/- 6% accuracy. | K15: Conditions between 6 and 8 | L15: 100% of exported water sources are metered, meter accuracy testing and/or electronic calibration conducted annually, less than 10% of meters are found outside of +/- 6% accuracy | M15: Conditions between 8 and 10 | N15: 100% of exported water sources are metered, meter accuracy testing and/or electronic calibration conducted semi-annually, with less than 10% found outside of +/- 3% accuracy. | Q15: ='Reporting Worksheet'!E17 -> n/a | R15: =IF(OR(C15=$R$3,C15=$R$4,C15=$R$5),1,0) -> 0
C16: Improvements to attain higher data grading for "Water Exported Volume" component: | E16: to qualify for 2: Review bulk water sales agreements with partner suppliers; confirm requirements for use & upkeep of accurate metering. Identify needs to install new, or replace defective meters as needed. | F16: To qualify for 4: Locate all exported water sources on maps and in field, launch meter accuracy testing for existing meters, begin to install meters on unmetered exported water interconnections and replace obsolete/defective meters | H16: to qualify for 6: Formalize annual meter accuracy testing for all exported water meters. Continue installation of meters on unmetered exported water interconnections and replacement of obsolete/defective meters. | J16: to qualify for 8: Complete project to install new, or replace defective, meters on all exported water interconnections. Maintain annual meter accuracy testing for all imported water meters. Repair or replace meters outside of +/- 6% accuracy. | L16: to qualify for 10: Maintain annual meter accuracy testing for all meters. Repair or replace meters outside of +/- 6% accuracy. Investigate new meter technology; pilot one or more replacements with innovative meters in attempt to improve meter accuracy. | N16: to maintain 10: Standardize meter accuracy test frequency to semi-annual, or more frequent, for all meters. Repair or replace meters outside of +/- 3% accuracy. Continually investigate/pilot improving metering technology. | Q16: =Q15 -> n/a
C17: AUTHORIZED CONSUMPTION
C18: Billed metered: | D18: n/a (not applicable). Select n/a only if the entire customer population is not metered and is billed for water service on a flat or fixed rate basis. In such a case the volume entered must be zero. | E18: Less than 50% of customers with volume-based billings from meter readings; flat or fixed rate billed for the majority of the customer population | F18: At least 50% of customers with volume-based billing from meter reads; flat rate billed for others. Manual meter reading, under 50% read success rate, remainder estimated. Limited meter records, no regular meter testing or replacement. Billing data maintained on paper records, with no auditing. | G18: Conditions between 2 and 4 | H18: At least 75% of customers with volume-based billing from meter reads; flat or fixed rate billed for remainder. Manual meter reading used, at least 50% meter read success rate, failed reads are estimated. Purchase records verify age of customer meters; only very limited meter accuracy testing is conducted. Customer meters replaced only upon complete failure. Computerized billing records, but only periodic internal auditing conducted. | I18: Conditions between 4 and 6 | J18: At least 90% of customers with volume-based billing from meter reads; remaining accounts are estimated. Manual customer meter reading gives at least 80% customer meter reading success rate, failed reads are estimated. Good customer meter records, limited meter accuracy testing, regular replacement of oldest meters. Computerized billing records with routine auditing of global statistics. | K18: Conditions between 6 and 8 | L18: At least 97% of customers with volume-based billing from meter reads. At least 90% customer meter read success rate; or minimum 80% read success rate with planning and budgeting for trials of Automatic Metering Reading (AMR) in one or more pilot areas. Good customer meter records. Regular meter accuracy testing guides replacement of statistically significant number of meters each year. Routine auditing of computerized billing records for global and detailed statistics; verified periodically by third party. | M18: Conditions between 8 and 10 | N18: At least 99% of customers with volume-based billing from meter reads. At least 95% customer meter reading success rate; or minimum 80% meter reading success rate, with Automatic Meter Reading (AMR) trials underway. Statistically significant customer meter testing and replacement program in place. Computerized billing with routine, detailed auditing, including field investigation of representative sample of accounts. Annual audit verification by third party. | Q18: ='Reporting Worksheet'!E23 -> 6 | R18: =IF(OR(C18=$R$3,C18=$R$4,C18=$R$5),1,0) -> 1
C19: Improvements to attain higher data grading for "Billed Metered Consumption" component: | D19: If n/a is selected because the customer meter population is unmetered, consider establishing a new policy to meter the customer population and employ water rates based upon metered volumes. | E19: to qualify for 2: Conduct investigations or trials of customer meters to select appropriate meter models. Budget funding for meter installations. Investigate volume based water rate structures. | F19: to qualify for 4: Purchase and install meters on unmetered accounts. Implement policies to improve meter reading success. Catalog meter information during meter read visits to identify age/model of existing meters. Test a minimal number of meters for accuracy. Install computerized billing system. | H19: to qualify for 6: Purchase and install meters on unmetered accounts. Eliminate flat fee billing and establish appropriate water rate structure based upon measured consumption. Continue to achieve verifiable success in removing manual meter reading barriers. Expand meter accuracy testing. Launch regular meter replacement program. Conduct routine audit of global statistics. | J19: to qualify for 8: Purchase and install meters on unmetered accounts. Assess cost-effectiveness of Automatic Meter Reading (AMR) system for portion or entire system; or achieve ongoing improvements in manual meter reading success rate. Refine meter accuracy testing program. Set meter replacement goals based upon accuracy test results. Refine routine auditing procedures based upon third party guidance. | L19: to qualify for 10: Purchase and install meters on unmetered accounts. Launch Automatic Meter Reading (AMR) system trials if manual meter reading success rate of at least 95% is not achieved within a five-year program. Continue meter accuracy testing program. Conduct planning and budgeting for large scale meter replacement based upon meter life cycle analysis using cumulative flow target. Continue routine auditing and require annual third party review. | N19: to maintain 10: Regular internal and third party auditing, and meter accuracy testing ensures that accurate customer meter readings are obtained and entered as the basis for volume based billing. Stay abreast of improvements in Advanced Metering Infrastructure (AMI) and information management. Plan and budget for justified upgrades in metering, meter reading and billing data management. | Q19: =Q18 -> 6
C20: Billed unmetered: | D20: Select n/a if it is the policy of the water utility to meter all customer connections and it has been confirmed by detailed auditing that all customers do indeed have a water meter; i.e. no unmetered accounts exist | E20: Water utility policy does not require customer metering; flat or fixed fee billed. No data collected on customer consumption. Only estimates available are derived from data estimation methods using average fixture count multiplied by number of connections, or similar approach. | F20: Water utility policy does not require customer metering; flat or fixed fee billed. Some metered accounts exist in parts of the system (pilot areas or District Metered Areas) with consumption recorded on portable dataloggers. Data from these sample meters are used to infer consumption for the total customer population. Site specific estimation methods are used for unusual buildings/water uses. | G20: Conditions between 2 and 4 | H20: Water utility policy does require metering and volume based billing but lacks written procedures and employs casual oversight, resulting in up to 20% of billed accounts believed to be unmetered. A rough estimate of the annual consumption for all unmetered accounts is included in the annual water audit, with no inspection of individual unmetered accounts. | I20: Conditions between 4 and 6 | J20: Water utility policy does require metering and volume based billing but exemption exist for a portion of accounts such as municipal buildings. As many as 15% of billed accounts are unmetered due to this exemption or meter installation difficulties. Only a group estimate of annual consumption for all unmetered accounts is included in the annual water audit, with no inspection of individual unmetered accounts. | K20: Conditions between 6 and 8 | L20: Water utility policy requires metering and volume based billing for all customer accounts. However, less than 5% of billed accounts remain unmetered because because installation is hindered by unusual circumstances. The goal is to minimize the number of unmetered accounts. Reliable estimates of consumption are obtained for unmetered accounts via site specific estimation methods. | M20: Conditions between 8 and 10 | N20: Water utility policy requires metering and volume based billing for all customer accounts. Less than 2% of billed accounts are unmetered and exist because meter installation is hindered by unusual circumstances. The goal exists to minimize the number of unmetered accounts to the extent that is economical. Reliable estimates of consumption are obtained at these accounts via site specific estimation methods. | Q20: ='Reporting Worksheet'!E24 -> n/a | R20: =IF(OR(C20=$R$3,C20=$R$4,C20=$R$5),1,0) -> 0
C21: Improvements to attain higher data grading for "Billed Unmetered Consumption" component: | E21: to qualify for 2: Investigate a new water utility policy to require metering of the customer population, and a reduction of unmetered accounts. Conduct pilot metering project by installing water meters in small sample of customer accounts and datalogging the water consumption. | F21: to qualify for 4: Implement a new water utility policy requiring customer metering. Expand pilot metering study to include several different meter types, which will provide data for economic assessment of full scale metering options. Assess sites with access difficulties to devise means to obtain water consumption volumes. | H21: to qualify for 6: Budget for staff resources to review billing records to identify unmetered properties. Specify metering needs and funding requirements to install sufficient meters to significant reduce the number of unmetered accounts | J21: to qualify for 8: Install customer meters on a full scale basis. Refine metering policy and procedures to ensure that all accounts, including municipal properties, are designated for meters. Implement procedures to obtain reliable consumption estimate for unmetered accounts awaiting meter installation. | L21: to qualify for 10: Continue customer meter installation throughout the service area, with a goal to minimize unmetered accounts. Sustain the effort to investigate accounts with access difficulties to devise means to install water meters or otherwise measure water consumption. | N21: to maintain 10: Continue to refine estimation methods for unmetered consumption and explore means to establish metering, for as many billed unmetered accounts as is economically feasible. | Q21: =Q20 -> n/a
C22: Unbilled metered: | D22: select n/a if all billing-exempt consumption is unmetered. | E22: Billing practices exempt certain accounts, such as municipal buildings, but written policies do not exist; and a reliable count of unbilled metered accounts is unavailable. Meter upkeep and meter reading on these accounts is rare and not considered a priority. Due to poor recordkeeping and lack of auditing, water consumption for all such accounts is purely guesstimated. | F22: Billing practices exempt certain accounts, such as municipal buildings, but only scattered, dated written directives exist to justify this practice. A reliable count of unbilled metered accounts is unavailable. Sporadic meter replacement and meter reading occurs on an as-needed basis. The total annual water consumption for all unbilled, metered accounts is estimated based upon approximating the number of accounts and assigning consumption from actively billed accounts of same meter size. | G22: Conditions between 2 and 4 | H22: Dated written procedures permit billing exemption for specific accounts, such as municipal properties, but are unclear regarding certain other types of accounts. Meter reading is given low priority and is sporadic. Consumption is quantified from meter readings where available. The total number of unbilled, unmetered accounts must be estimated along with consumption volumes. | I22: Conditions between 4 and 6 | J22: Written policies regarding billing exemptions exist but adherence in practice is questionable. Metering and meter reading for municipal buildings is reliable but sporadic for other unbilled metered accounts. Periodic auditing of such accounts is conducted. Water consumption is quantified directly from meter readings where available, but the majority of the consumption is estimated. | K22: Conditions between 6 and 8 | L22: Written policy identifies the types of accounts granted a billing exemption. Customer meter management and meter reading are considered secondary priorities, but meter reading is conducted at least annually to obtain consumption volumes for the annual water audit. High level auditing of billing records ensures that a reliable census of such accounts exists. | M22: Conditions between 8 and 10 | N22: Clearly written policy identifies the types of accounts given a billing exemption, with emphasis on keeping such accounts to a minimum. Customer meter management and meter reading for these accounts is given proper priority and is reliably conducted. Regular auditing confirms this. Total water consumption for these accounts is taken from reliable readings from accurate meters. | Q22: ='Reporting Worksheet'!E25 -> 9 | R22: =IF(OR(C22=$R$3,C22=$R$4,C22=$R$5),1,0) -> 0
C23: Improvements to attain higher data grading for "Unbilled metered Consumption" component: | E23: to qualify for 2: Reassess the water utility's policy allowing certain accounts to be granted a billing exemption. Draft an outline of a new written policy for billing exemptions, with clear justification as to why any accounts should be exempt from billing, and with the intention to keep the number of such accounts to a minimum. | F23: to qualify for 4: Review historic written directives and policy documents allowing certain accounts to be billing-exempt. Draft an outline of a written policy for billing exemptions, identify criteria that grants an exemption, with a goal of keeping this number of accounts to a minimum. | H23: to qualify for 6: Draft a new written policy regarding billing exemptions based upon consensus criteria allowing this occurrence. Assign resources to audit meter records and billing records to obtain census of unbilled metered accounts. | J23: to qualify for 8: Communicate billing exemption policy throughout the organization and implement procedures that ensure proper account management. Conduct inspections of accounts confirmed in unbilled metered status and verify that accurate meters exist and are scheduled for routine meter readings. | L23: to qualify for 10: Ensure that meter management (meter accuracy testing, meter replacement) and meter reading activities are accorded the same priority as billed accounts. Establish ongoing annual auditing process to ensure that water consumption is reliably collected and provided to the annual water audit process. | N23: to maintain 10: Reassess philosophy in allowing any water uses to go "unbilled". It is possible to meter and bill all accounts, even if the fee charged for water consumption is discounted or waived. Metering and billing all accounts ensures that water consumption is tracked and water waste from plumbing leaks is detected and minimized. | Q23: =Q22 -> 9
C24: Unbilled unmetered: | E24: Extent of unbilled, unmetered consumption is unknown due to unclear policies and poor recordkeeping. Total consumption is quantified based upon a purely subjective estimate. | F24: Clear extent of unbilled, unmetered consumption is unknown, but a number of events are randomly documented each year, confirming existence of such consumption, but without sufficient documentation to quantify an accurate estimate of the annual volume consumed. | G24: Conditions between 2 and 4 | H24: Extent of unbilled, unmetered consumption is partially known, and procedures exist to document certain events such as miscellaneous fire hydrant uses. Formulae is used to quantify the consumption from such events (time running x typical flowrate x number of events). | I24: Default value of 1.25% of system input volume is employed | J24: Coherent policies exist for some forms of unbilled, unmetered consumption but others await closer evaluation. Reasonable recordkeeping for the managed uses exists and allows for annual volumes to be quantified by inference, but unsupervised uses are guesstimated. | K24: Conditions between 6 and 8 | L24: Clear policies and good recordkeeping exist for some uses (ex: unmetered fire connections registering consumption), but other uses (ex: miscellaneous uses of fire hydrants) have limited oversight. Total consumption is a mix of well quantified use such as from formulae (time x typical flow) or temporary meters, and relatively subjective estimates of less regulated use. | M24: Conditions between 8 and 10 | N24: Clear policies exist to identify permitted use of water in unbilled, unmetered fashion, with the intention of minimizing this type of consumption. Good records document each occurrence and consumption is quantified via formulae (time x typical flow) or use of temporary meters. | Q24: ='Reporting Worksheet'!E26 -> 0 | R24: =IF(OR(C24=$R$3,C24=$R$4,C24=$R$5),1,0) -> 0
C25: Improvements to attain higher data grading for "Unbilled Unmetered Consumption" component: | E25: to qualify for 5: Utilize accepted default value of 1.25% of system input volume as an expedient means to gain a reasonable quantification of this use. to qualify for 2: Establish a policy regarding what water uses should be allowed as unbilled and unmetered. Consider tracking a small sample of one such use (ex: fire hydrant flushings). | F25: to qualify for 5: Utilize accepted default value of 1.25% of system input volume as an expedient means to gain a reasonable quantification of this use. to qualify for 4: Evaluate the documentation of events that have been observed. Meet with user groups (ex: for fire hydrants - fire departments, contractors to ascertain their need for water from fire hydrants). | H25: to qualify for 5: Utilize accepted default value of 1.25% of system input volume as expedient means to gain a reasonable quantification of all such use. This is particularly appropriate for water utilities who are in the early stages of the water auditing process. | I25: to qualify for 6 or greater: Finalize policy and do field checks. Proceed if top-down audit exists and/or a great volume of such use is suspected. | J25: to qualify for 8: Assess water utility policy and procedures to ensure that fire hydrant permits are issued for use by persons outside of the utility. Create written procedures for use and documentation of fire hydrants by water utility personnel. | L25: to qualify for 10: Refine written procedures to ensure that all uses of unbilled, unmetered water are overseen by a structured permitting process managed by water utility personnel. Reassess policy to determine if some of these uses have value in being converted to billed and/or metered status. | N25: to maintain 10: Continue to refine policy and procedures with intention of reducing the number of allowable uses of water in unbilled and unmetered fashion. Any uses that can feasibly become billed and metered should be converted eventually. | Q25: =Q24 -> 0
C26: APPARENT LOSSES
C27: Unauthorized consumption: | E27: Extent of unauthorized consumption is unknown due to unclear policies and poor recordkeeping. Total unauthorized consumption is guesstimated. | F27: Unauthorized consumption is a known occurrence, but its extent is a mystery. There are no requirements to document observed events, but periodic field reports capture some of these occurrences. Total unauthorized consumption is approximated from this limited data. | G27: conditions between 2 and 4 | H27: Procedures exist to document some unauthorized consumption such as observed unauthorized fire hydrant openings. Use formulae to quantify this consumption (time running x typical flowrate x number of events). | I27: Default value of 0.25% of system input volume is employed | J27: Coherent policies exist for some forms of unauthorized consumption but others await closer evaluation. Reasonable surveillance and recordkeeping exist for occurrences that fall under the policy. Volumes quantified by inference from these records. Unsupervised uses are guesstimated. | K27: Conditions between 6 and 8 | L27: Clear policies and good recordkeeping exist for certain events (ex: tampering with water meters); other occurrences have limited oversight. Total consumption is a combination of volumes from formulae (time x typical flow) and subjective estimates of unconfirmed consumption. | M27: Conditions between 8 and 10 | N27: Clear policies exist to identify all known unauthorized uses of water. Staff and procedures exist to provide enforcement of policies and detect violations. Each occurrence is quantified via formulae (time x typical flow) or similar methods. | Q27: ='Reporting Worksheet'!E38 -> 0 | R27: =IF(OR(C27=$R$3,C27=$R$4,C27=$R$5),1,0) -> 0
C28: Improvements to attain higher data grading for "Unauthorized Consumption" component: | E28: to qualify for 5: Use accepted default of 0.25% of system input volume. to qualify for 2: Review utility policy regarding what water uses are considered unauthorized, and consider tracking a small sample of one such occurrence (ex: unauthorized fire hydrant openings) | F28: to qualify for 5: Use accepted default of 0.25% of system input volume to qualify for 4: Review utility policy regarding what water uses are considered unauthorized, and consider tracking a small sample of one such occurrence (ex: unauthorized fire hydrant openings) | H28: to qualify for 5: Utilize accepted default value of 0.25% of system input volume as expedient means to gain a reasonable quantification of all such use. This is particularly appropriate for water utilities who are in the early stages of the water auditing process. | I28: to qualify for 6 or greater: Finalize policy and do field checks. Proceed if top-down audit exists and/or a great volume of such use is suspected. | J28: to quality for 8: Assess water utility policies to ensure that all known occurrences of unauthorized consumption are outlawed, and that appropriate penalties are prescribed. Create written procedures for use and documentation of various occurrences of unauthorized consumption as they are uncovered. | L28: to qualify for 10: Refine written procedures and assign staff to seek out likely occurrences of unauthorized consumption. Explore new locking devices, monitors and other technologies designed to detect and thwart unauthorized consumption. | N28: to maintain 10: Continue to refine policy and procedures to eliminate any loopholes that allow or tacitly encourage unauthorized consumption. Continue to be vigilant in documentation and enforcement efforts. | Q28: =Q27 -> 0
C29: Customer metering inaccuracies: | D29: select n/a only if the entire customer population is unmetered. In such a case the volume entered must be zero. | E29: Customer meters exist, but with unorganized paper records on meters; no meter accuracy testing or meter replacement program. Workflow is driven chaotically by customer complaints with no proactive management. Loss volume due to aggregate meter inaccuracy is guesstimated. | F29: Poor recordkeeping and meter oversight is recognized by water utility management who has allotted staff and funding resources to organize improved recordkeeping and start meter accuracy testing. Existing paper records gathered and organized to provide cursory disposition of meter population. | G29: Conditions between 2 and 4 | H29: Reliable recordkeeping exists; meter information is improving as meters are replaced. Meter accuracy testing is conducted annually for a small number of meters. Limited number of oldest meters replaced each year. Inaccuracy volume is largely an estimate, but refined based upon limited testing data. | I29: Conditions between 4 and 6 | J29: A reliable electronic recordkeeping system for meters exists. Population includes a mix of new high performing meters and dated meters with suspect accuracy. Routine, but limited, meter accuracy testing and meter replacement occur. Inaccuracy volume is quantified using a mix of reliable and less certain data. | K29: Conditions between 6 and 8 | L29: Ongoing meter replacement and accuracy testing result in highly accurate customer meter population. Testing is conducted on samples of meters at varying lifespans to determine optimum replacement time for various types of meters. | M29: Conditions between 8 and 10 | N29: Good records of number, type and size of customer meters; ongoing meter replacement occurs. Regular meter accuracy testing gives reliable measure of composite inaccuracy volume for the system. New metering technology is embraced to keep overall accuracy improving. | Q29: ='Reporting Worksheet'!E42 -> 3 | R29: =IF(OR(C29=$R$3,C29=$R$4,C29=$R$5),1,0) -> 1
C30: Improvements to attain higher data grading for "Customer meter inaccuracy volume" component: | D30: If n/a is selected because the customer meter population is unmetered, consider establishing a new policy to meter the customer population and employ water rates based upon metered volumes. | E30: to qualify for 2: Gather available meter purchase records. Conduct testing on a small number of meters believed to be the most inaccurate. Review staffing needs of metering group and budget for necessary resources to better organize meter management. | F30: to qualify for 4: Implement a reliable record keeping system for customer meter histories, preferably using electronic methods typically linked to, or part of, the Customer Billing System or Customer Information System. Expand meter accuracy testing to a larger group of meters. | H30: to qualify for 6: Standardize procedures for meter recordkeeping with the electronic information system. Accelerate meter accuracy testing and meter replacements guided by testing results. | J30: to qualify for 8: Expand annual meter accuracy testing to evaluate a statistically significant number of meter makes/models. Expand meter replacement program to replace statistically significant number of poor performing meters each year. | L30: to qualify for 10: Continue efforts to manage meter population with reliable recordkeeping, meter testing and replacement. Evaluate new meter types and install one or more types in 5-10 customer accounts each year in order to pilot improving metering technology. | N30: to maintain 10: Increase the number of meters tested and replaced as justified by meter accuracy test data. Continually monitor development of new technology in Advanced Metering Infrastructure (AMI) to grasp opportunities for greater accuracy in metering and customer consumption data. | Q30: =Q29 -> 3
C31: Systematic Data Handling Error: | D31: Note: all water utilities incur some amount of this error. Even in water utilities with unmetered customer populations and fixed rate billing, errors occur in annual billing tabulations. Enter a positive value for the volume and select a grading. | E31: Vague policy for permitting (creating new customer accounts) and billing. Billing data maintained on paper records which are in disarray. No audits conducted to confirm billing data handling efficiency. Unknown number of customers escape routine billing due to lack of billing process oversight. | F31: Policy for permitting and billing exists but needs refinement. Billing data maintained on paper records or insufficiently capable electronic database. Only periodic unstructured auditing work conducted to confirm billing data handling efficiency. Volume of unbilled water due to billing lapses is a guess. | G31: Conditions between 2 and 4 | H31: Policy and procedures for permitting and billing exist but needs refinement. Computerized billing system exists, but is dated or lacks needed functionality. Periodic, limited internal audits conducted and confirm with approximate accuracy the consumption volumes lost to billing lapses. | I31: Conditions between 4 and 6 | J31: Policy for permitting and billing is adequate and reviewed periodically. Computerized billing system in use with basic reporting available. Any effect of billing adjustments on measured consumption volumes is well understood. Internal checks of billing data error conducted annually. Reasonably accurate quantification of consumption volume lost to billing lapses is obtained. | K31: Conditions between 6 and 8 | L31: Permitting and billing policy reviewed at least biannually. Computerized billing system includes an array of reports to confirm billing data and system functionality. Annual internal checks conducted with periodic third party audit. Accountability checks flag billing lapses. Consumption lost to billing lapses is well quantified and reducing year-by-year. | M31: Conditions between 8 and 10 | N31: Sound policy exists for permitting of all customer billing accounts. Robust computerized billing system gives high functionality and reporting capabilities. Assessment of policy and data handling errors conducted internally and audited by third party annually, ensuring consumption lost to billing lapses is minimized and detected as it occurs. | Q31: ='Reporting Worksheet'!E43 -> 4 | R31: =IF(OR(C31=$R$3,C31=$R$4,C31=$R$5),1,0) -> 0
C32: Improvements to attain higher data grading for "Systematic Data Handling Error volume" component: | E32: to qualify for 2: Draft written policy for permitting and billing. Investigate and budget for computerized customer billing system. Conduct initial audit of billing records by flow-charting the basic business processes of the customer account/billing function. | F32: to qualify for 4: Finalize written policy for permitting and billing. Implement a computerized customer billing system. Conduct initial audit of billing records as part of this process. | H32: to qualify for 6: Refine permitting and billing procedures and ensure consistency with the utility policy regarding billing, and minimize opportunity for missed billings. Upgrade or replace customer billing system for needed functionality - ensure that billing adjustments don't corrupt the value of consumption volumes. Procedurize internal annual audit process. | J32: to qualify for 8: Formalize regular review of permitting and billing practices. Enhance reporting capability of computerized billing system. Formalize regular auditing process to reveal scope of data handling error. | L32: to qualify for 10: Close policy/procedure loopholes that allow some customer accounts to go unbilled, or data handling errors to exist. Ensure that internal and third party audits are conducted annually. | N32: to maintain 10: Stay abreast of customer information management developments and innovations. Monitor developments of Advanced Metering Infrastructure (AMI) and integrate technology to ensure that customer endpoint information is well-monitored and errors/lapses are at an economic minimum. | Q32: =Q31 -> 4
C33: SYSTEM DATA
C34: Length of mains: | E34: Poorly assembled and maintained paper as-built records of existing water main installations makes accurate determination of system pipe length impossible. Length of mains is guesstimated. | F34: Paper records in poor condition (no annual tracking of installations & abandonments). Poor procedures to ensure that new water mains installed by developers are accurately documented. | G34: Conditions between 2 and 4 | H34: Sound policy and procedures for permitting and documenting new water main installations, but gaps in management result in a uncertain degree of error in tabulation of mains length. | I34: Conditions between 4 and 6 | J34: Sound policy and procedures exist for permitting and commissioning new water mains. Highly accurate paper records with regular field validation; or electronic records and asset management system in good condition. Includes system backup. | K34: Conditions between 6 and 8 | L34: Sound policy and procedures exist for permitting and commissioning new water mains. Electronic recordkeeping and asset management system are used to store and manage data. | M34: Conditions between 8 and 10 | N34: Sound policy exists for managing water mains extensions and replacements. Geographic Information System (GIS) data and asset management database agree and random field validation proves truth of databases. | Q34: ='Reporting Worksheet'!E62 -> 3 | R34: =IF(OR(C34=$R$3,C34=$R$4,C34=$R$5),1,0) -> 0
C35: Improvements to attain higher data grading for "Length of Water Mains" component: | E35: to qualify for 2: Assign personnel to inventory current as-built records and compare with customer billing system records and highway plans. Assemble policy documents regarding permitting and documentation of water main installations by the utility and building developers; identify gaps in procedure that result in poor documentation. | F35: to qualify for 4: Complete inventory of paper records of water main installations & abandonments for a number of years prior to audit year. Review policy and procedures for commissioning and documenting new water main installation and abandonments. | H35: to qualify for 6: Finalize updates/improvements to policy and procedures for permitting/commissioning new main installations. Confirm inventory of records for five years prior to audit year; correct any errors or omissions. | J35: to qualify for 8: Launch random field checks of limited number of locations. Convert to electronic databases with backup as justified. | L35: to qualify for 10: Link Geographic Information System (GIS) and asset management databases, conduct field verification of data. | N35: to maintain 10: Continue with standardization and random field validation to improve knowledge of system. | Q35: =Q34 -> 3
C36: Number of active AND inactive service connections: | E36: Vague permitting (of new service connections) policy and poor paper recordkeeping of customer connections/billings result in suspect determination of the number of service connections, which may be 10-15% in error from actual count. | F36: General permitting policy exists but paper records, procedural gaps, and weak oversight result in questionable total for number of connections, which may vary 5-10% of actual count. | G36: Conditions between 2 and 4 | H36: Permitting policy and procedures exist, but with some gaps in performance and oversight. Computerized information management system is being brought online to replace dated paper recordkeeping system. Reasonably accurate tracking of service connection installations & abandonments; but count can be up to 5% in error from actual total. | I36: Conditions between 4 and 6 | J36: Permitting policy and procedures are adequate and reviewed periodically. Computerized information management system is in use with annual installations & abandonments totaled. Very limited field verifications and audits. Error in count of number of service connections is believed to be no more that 3%. | K36: Conditions between 6 and 8 | L36: Permitting policy and procedures reviewed at least biannually. Well-managed computerized information management system and routine, periodic field checks and internal system audits allows counts of connections that is no more than 2% in error. | M36: Conditions between 8 and 10 | N36: Sound permitting policy and well managed and audited procedures ensure reliable management of service connection population. Computerized information management system and Geographic Information System (GIS) information agree; field validation proves truth of databases. Count of connections believed to be in error by less than 1%. | Q36: ='Reporting Worksheet'!E63 -> 3 | R36: =IF(OR(C36=$R$3,C36=$R$4,C36=$R$5),1,0) -> 0
C37: Improvements to attain higher data grading for "Number of Active and Inactive customer service connections" component: | E37: to qualify for 2: Draft new policy and procedures for permitting and billing. Research and collect paper records of installations & abandonments for several years prior to audit year. | F37: to qualify for 4: Refine policy and procedures for permitting and billing. Research computerized recordkeeping system (Customer Information System or Customer Billing System) to improve documentation format for service connections. | H37: to qualify for 6: Refine procedures to ensure consistency with permitting policy to establish new service connections or decommission existing connections. Improve process to include all totals for at least five years prior to audit year. | J37: to qualify for 8: Formalize regular review of permitting policy and procedures. Launch random field checks of limited number of locations. Develop reports and auditing mechanisms for computerized information management system. | L37: to qualify for 10: Close any procedural loopholes that allow installations to go undocumented. Link computerized information management system with Geographic Information System (GIS) and formalize field inspection and information system auditing processes. Documentation of new or decommissioned service connections encounters several levels of checks and balances. | N37: to maintain 10: Continue with standardization and random field validation to improve knowledge of system. | Q37: =Q36 -> 3
C38: Average length of customer service line: | D38: Note: if customer water meters are located outside of the customer building next to the curbstop or boundary separating utility/customer responsibility, follow the grading description for 10(a). Also see the Service Connection Diagram worksheet. | E38: Gradings 1-9 apply if customer properties are unmetered, if customer meters exist and are located inside the customer building premises, or if the water utility owns and is responsible for the entire service connection piping from the water main to the customer building. In any of these cases the average distance between the curbstop or boundary separating utility/customer responsibility for service connection piping, and the typical first point of use (ex: faucet) or the customer meter must be quantified. Gradings of 1-9 are used to grade the validity of the means to quantify this value. (See the "Service Connection Diagram" worksheet) | N38: Either of two conditions can be met to obtain a grading of 10: a) The customer water meter is located outside of the customer building adjacent to the curbstop or boundary separating utility/customer responsibility for the service connection piping. In this case enter a value of zero in the Reporting Worksheet with a grading of 10. b). Customer water meters are located inside customer buildings, or the properties are unmetered. In either case the distance is highly reliable since data is drawn from a Geographic Information System (GIS) and confirmed by routine field checks. | Q38: =Q39 -> 3 | R38: =IF(OR(C38=$R$3,C38=$R$4,C38=$R$5),1,0) -> 0
E39: Vague policy exists to define the delineation of water utility ownership and customer ownership of the service connection piping. Curbstops are perceived as the breakpoint but these have not been well-maintained or documented. Most are buried or obscured. Their location varies widely from site-to-site, and estimating this distance is arbitrary due to the unknown location of many curbstops. | F39: Policy requires that the curbstop serves as the delineation point between water utility ownership and customer ownership of the service connection piping. The piping from the water main to the curbstop is the property of the water utility; and the piping from the curbstop to the customer building is owned by the customer. Curbstop locations are not well documented and the average distance is based upon a limited number of locations measured in the field. | G39: Conditions between 2 and 4 | H39: Good policy requires that the curbstop serves as the delineation point between water utility ownership and customer ownership of the service connection piping. Curbstops are generally installed as needed and are reasonably documented. Their location varies widely from site-to-site, and an estimate of this distance is hindered by the availability of paper records. | I39: Conditions between 4 and 6 | J39: Clear policy exists to define utility/customer responsibility for service connection piping. Accurate, well-maintained paper or basic electronic recordkeeping system exists. Periodic field checks confirm piping lengths for a sample of customer properties. | K39: Conditions between 6 and 8 | L39: Clearly worded policy standardizes the location of curbstops and meters, which are inspected upon installation. Accurate and well maintained electronic records exist with periodic field checks to confirm locations of service lines, curbstops and customer meter pits. An accurate number of customer properties from the customer billing system allows for reliable averaging of this length. | M39: Conditions between 8 and 10 | Q39: ='Reporting Worksheet'!E65 -> 3 | R39: =IF(OR(C39=$R$3,C39=$R$4,C39=$R$5),1,0) -> 0
C40: Improvements to attain higher data grading for "Average Length of Customer Service Line" component: | E40: to qualify for 2: Research and collect paper records of service line installations. Inspect several sites in the field using pipe locators to locate curbstops. Obtain the length of this small sample of connections in this manner. | F40: to qualify for 4: Formalize and communicate policy delineating utility/customer responsibilities for service connection piping. Assess accuracy of paper records by field inspection of a small sample of service connections using pipe locators as needed. Research the potential migration to a computerized information management system to store service connection data. | H40: to qualify for 6: Establish coherent procedures to ensure that policy for curbstop, meter installation and documentation is followed. Gain consensus within the water utility for the establishment of a computerized information management system. | J40: to qualify for 8: Implement an electronic means of recordkeeping, typically via a customer information system or customer billing system. Standardize the process to conduct field checks of limited number of locations. | L40: to qualify for 10: Link customer information management system and Geographic Information System (GIS), standardize process for field verification of data. | N40: to maintain 10: Continue with standardization and random field validation to improve knowledge of system. | Q40: =Q39 -> 3
C41: Average operating pressure: | E41: Available records are poorly assembled and maintained paper records of supply pump characteristics and water distribution system operating conditions. Average pressure is guesstimated based upon this information and ground elevations from crude topographical maps. Widely varying distribution system pressures due to undulating terrain, high system head loss and weak/erratic pressure controls further compromise the validity of the average pressure calculation. | F41: Limited telemetry monitoring of scattered sites provides some static pressure data, which is recorded in handwritten logbooks. Pressure data is gathered at individual sites only when low pressure complaints arise. Average pressure is determined by averaging relatively crude data, and is affected by significant variation in ground elevations, system head loss and gaps in pressure controls in the distribution system. | G41: Conditions between 2 and 4 | H41: Effective pressure controls separate different pressure zones; moderate pressure variation across the system, occasional open boundary valves are discovered that breech pressure zones. Basic telemetry monitoring of the distribution system logs pressure data electronically. Pressure data gathered by gauges or dataloggers at fire hydrants or buildings when low pressure complaints arise, and during fire flow tests and system flushing. Reliable topographical data exists. Average pressure is calculated using this mix of data. | I41: Conditions between 4 and 6 | J41: Reliable pressure controls separate distinct pressure zones; only very occasional open boundary valves are encountered that breech pressure zones. Well-covered telemetry monitoring of the distribution system logs extensive pressure data electronically. Pressure gathered by gauges/dataloggers at fire hydrants and buildings when low pressure complaints arise, and during fire flow tests and system flushing. Average pressure is determined by using this mix of reliable data. | K41: Conditions between 6 and 8 | L41: Well-managed, discrete pressure zones exist with generally predictable pressure fluctuations. A current full-scale SCADA System exists to monitor the water distribution system and collect data, including real time pressure readings at representative sites across the system. The average system pressure is determined from reliable SCADA System data. | M41: Conditions between 8 and 10 | N41: Well-managed pressure districts/zones, SCADA System and hydraulic model exist to give very precise pressure data across the water distribution system. Average system pressure is reliably calculated from extensive, reliable, and cross-checked data. | Q41: ='Reporting Worksheet'!E67 -> 2 | R41: =IF(OR(C41=$R$3,C41=$R$4,C41=$R$5),1,0) -> 0
C42: Improvements to attain higher data grading for "Average Operating Pressure" component: | E42: to qualify for 2: Employ pressure gauging and/or datalogging equipment to obtain pressure measurements from fire hydrants. Locate accurate topographical maps of service area in order to confirm ground elevations. Research pump data sheets to find pump pressure/flow characteristics | F42: to qualify for 4: Formalize a procedure to use pressure gauging/datalogging equipment to gather pressure data during various system events such as low pressure complaints, or operational testing. Gather pump pressure and flow data at different flow regimes. Identify faulty pressure controls (pressure reducing valves, altitude valves, partially open boundary valves) and plan to properly configure pressure zones. Make all pressure data from these efforts available to generate system-wide average pressure. | H42: to qualify for 6: Expand the use of pressure gauging/datalogging equipment to gather scattered pressure data at a representative set of sites, based upon pressure zones or areas. Utilize pump pressure and flow data to determine supply head entering each pressure zone or district. Correct any faulty pressure controls (pressure reducing valves, altitude valves, partially open boundary valves) to ensure properly configured pressure zones. Use expanded pressure dataset from these activities to generate system-wide average pressure. | J42: to qualify for 8: Install a Supervisory Control and Data Acquisition (SCADA) System to monitor system parameters and control operations. Set regular calibration schedule for instrumentation to insure data accuracy. Obtain accurate topographical data and utilize pressure data gathered from field surveys to provide extensive, reliable data for pressure averaging. | L42: to qualify for 10: Obtain average pressure data from hydraulic model of the distribution system that has been calibrated via field measurements in the water distribution system and confirmed in comparisons with SCADA System data. | N42: to maintain 10: Continue to refine the hydraulic model of the distribution system and consider linking it with SCADA System for real-time pressure data calibration, and averaging. | Q42: =Q41 -> 2
C43: COST DATA
C44: Total annual cost of operating water system: | E44: Incomplete paper records and lack of documentation on many operating functions making calculation of water system operating costs a pure guesstimate | F44: Reasonably maintained, but incomplete, paper or electronic accounting provides data to estimate the major portion of water system operating costs. | G44: Conditions between 2 and 4 | H44: Electronic, industry-standard cost accounting system in place. Gaps in data known to exist, periodic internal reviews conducted but not a structured audit. | I44: Conditions between 4 and 6 | J44: Reliable electronic, industry-standard cost accounting system in place, with all pertinent water system operating costs tracked. Data audited periodically by utility personnel, not a Certified Public Accountant (CPA). | K44: Conditions between 6 and 8 | L44: Reliable electronic, industry-standard cost accounting system in place, with all pertinent water system operating costs tracked. Data audited at least annually by utility personnel, and periodically by third-party CPA. | M44: Conditions between 8 and 10 | N44: Reliable electronic, industry-standard cost accounting system in place, with all pertinent water system operating costs tracked. Data audited annually by utility personnel and by third-party CPA. | Q44: ='Reporting Worksheet'!E74 -> 8 | R44: =IF(OR(C44=$R$3,C44=$R$4,C44=$R$5),1,0) -> 0
C45: Improvements to attain higher data grading for "Total Annual Cost of Operating the Water System" component: | E45: to qualify for 2: Gather available records, institute new procedures to regularly collect and audit basic cost data of most important operations functions. | F45: to qualify for 4: Implement an electronic cost accounting system, structured according to accounting standards for water utilities | H45: to qualify for 6: Establish process for periodic internal audit of water system operating costs; identify cost data gaps and institute procedures for tracking these outstanding costs. | J45: to qualify for 8: Standardize the process to conduct routine financial audit on an annual basis. | L45: to qualify for 10: Standardize the process to conduct a third-party financial audit by a CPA on an annual basis. | N45: to maintain 10: Maintain program, stay abreast of expenses subject to erratic cost changes and budget/track costs proactively | Q45: =Q44 -> 8
C46: Customer retail unit cost (applied to Apparent Losses): | E46: Antiquated, cumbersome water rate structure is use, with periodic historic amendments that were poorly documented and implemented; resulting in classes of customers being billed inconsistent charges. The actual composite billing rate likely differs significantly from the published water rate structure, but a lack of auditing leaves the degree of error indeterminate. | F46: Dated, cumbersome water rate structure, not always employed consistently in actual billing operations. The actual composite billing rate is known to differ from the published water rate structure, and a reasonably accurate estimate of the degree of error is determined, allowing a composite billing rate to be quantified. | G46: Conditions between 2 and 4 | H46: Straight-forward water rate structure in use, but not updated in several years. Billing operations reliably employ the rate structure. The composite billing rate is derived from a single customer class such as residential customer accounts, neglecting the effect of different rates from varying customer classes. | I46: Customer population unmetered. Fixed fee charged; single composite number derived from multiple customer classes. | J46: Clearly written, up-to-date water rate structure is in force and is applied reliably in billing operations. Composite customer rate is determined using a weighted average residential rate using volumes of water in each rate block. | K46: Conditions between 6 and 8 | L46: Effective water rate structure is in force and is applied reliably in billing operations. Composite customer rate is determined using a weighted average composite consumption rate, including residential, commercial, industrial and any other customer classes within the water rate structure. | M46: Conditions between 8 and 10 | N46: Third party reviewed weighted average composite consumption rate (includes residential, commercial, industrial, etc.) | Q46: ='Reporting Worksheet'!E75 -> 8 | R46: =IF(OR(C46=$R$3,C46=$R$4,C46=$R$5),1,0) -> 0
C47: Improvements to attain higher data grading for "Customer Retail Unit Cost" component: | E47: to qualify for 2: Formalize the process to implement water rates, including a secure documentation procedure. Create a current, formal water rate document and gain approval from all stakeholders. | F47: to qualify for 4: Review the water rate structure and update/formalize as needed. Assess billing operations to ensure that actual billing operations incorporate the established water rate structure. | H47: to qualify for 6: Evaluate volume of water used in each usage block by residential users. Multiply volumes by full rate structure. | I47: Meter customers and charge rates based upon water volumes | J47: to qualify for 8: Evaluate volume of water used in each usage block by all classifications of users. Multiply volumes by full rate structure. | L47: to qualify for 10: Conduct a periodic third-party audit of water used in each usage block by all classifications of users. Multiply volumes by full rate structure. | N47: to maintain 10: Keep water rate structure current in addressing the water utility's revenue needs. Update the calculation of the customer unit rate as new rate components, customer classes, or other components are modified. | Q47: =Q46 -> 8
C48: Variable production cost (applied to Real Losses): | D48: Note: if the water utility purchases/imports its entire water supply, then enter the unit purchase cost of the bulk water supply in the Reporting Worksheet with a grading of 10 | E48: Incomplete paper records and lack of documentation on primary operating functions (electric power and treatment costs most importantly) makes calculation of variable production costs a pure guesstimate | F48: Reasonably maintained, but incomplete, paper or electronic accounting provides data to roughly estimate the basic operations costs (pumping power costs and treatment costs) and calculate a unit variable production cost. | G48: Conditions between 2 and 4 | H48: Electronic, industry-standard cost accounting system in place. Electric power and treatment costs are reliably tracked and allow accurate calculation of unit variable production costs based on these two inputs only. All costs are audited internally on a periodic basis. | I48: Conditions between 4 and 6 | J48: Reliable electronic, industry-standard cost accounting system in place, with all pertinent water system operating costs tracked. Pertinent additional costs beyond power and treatment (ex: liability, residuals management, etc.) are included in the unit variable production cost. Data audited at least annually by utility personnel. | K48: Conditions between 6 and 8 | L48: Reliable electronic, industry-standard cost accounting system in place, with all pertinent variable production costs tracked. Data audited at least annually by utility personnel, and periodically by third-party. | M48: Conditions between 8 and 10 | N48: Either of two conditions can be met to obtain a grading of 10: 1) Third party CPA audit of all primary and secondary cost components on an annual basis. or: 2) Water supply is entirely purchased as bulk imported water, and unit purchase cost serves as the variable production cost. | Q48: ='Reporting Worksheet'!E76 -> 8 | R48: =IF(OR(C48=$R$3,C48=$R$4,C48=$R$5),1,0) -> 0
C49: Improvements to attain higher data grading for "Variable Production Cost" component: | E49: to qualify for 2: Gather available records, institute new procedures to regularly collect and audit basic cost data and most important operations functions. | F49: to qualify for 4: Implement an electronic cost accounting system, structured according to accounting standards for water utilities | H49: to qualify for 6: Formalize process for regular internal audits of production costs. Assess whether additional costs (liability, residuals management, etc.) should be included to calculate a more accurate variable production cost. | J49: to qualify for 8: Formalize the accounting process to include primary cost components (power, treatment) as well as secondary components (liability, residuals management, etc.) Conduct periodic third-party audits. | L49: to qualify for 10: Standardize the process to conduct a third-party financial audit by a CPA on an annual basis. | N49: to maintain 10: Maintain program, stay abreast of expenses subject to erratic cost changes and budget/track costs proactively | Q49: =Q48 -> 8

Sheet Service Connection Diagram
B2: AWWA WLCC Free Water Audit Software: Customer Service Line Diagrams
E4: =IF(ISBLANK(Instructions!H24),"","All Units in "&Instructions!H24)

Sheet Definitions
C2: AWWA WLCC Free Water Audit Software: Definitions
C4: Item Name | E4: Description
C6: Apparent Losses | E6: = unauthorized consumption + meter under-registration + data handling errors Includes all types of inaccuracies associated with customer metering as well as data handling errors (meter reading and billing), plus unauthorized consumption (theft or illegal use). NOTE: Over-registration of customer meters, leads to under-estimation of Real Losses. Under-registration of customer meters, leads to over-estimation of Real Losses.
C8: AUTHORIZED CONSUMPTION | E8: = billed metered + billed unmetered + unbilled metered + unbilled unmetered The volume of metered and/or unmetered water taken by registered customers, the water supplier and others who are implicitly or explicitly authorized to do so by the water supplier, for residential, commercial and industrial purposes. This does NOT include water sold to neighboring utilities (water exported). Authorized consumption may include items such as fire fighting and training, flushing of mains and sewers, street cleaning, watering of municipal gardens, public fountains, frost protection, building water, etc. These may be billed or unbilled, metered or unmetered.
C10: Average length of customer service line
C12: Average operating pressure | E12: The average pressure may be approximated when compiling the preliminary water audit. Once routine water auditing has been established, a more accurate assessment of average pressure should be pursued. If the water utility infrastructure is recorded in a Geographical Information System (GIS) the average pressure at many locations in the distribution system can be readily obtained. If a GIS does not exist, a weighted average of pressure data can be calculated from water pressure measured at various fire hydrants scattered across the water distribution system.
C14: Billed Authorized Consumption | E14: All consumption that is billed and authorized by the utility. This may include both metered and unmetered consumption. See "Authorized Consumption" for more information.
C16: Billed metered consumption | E16: All metered consumption which is billed. This includes all groups of customers such as domestic, commercial, industrial or institutional. It does NOT include water sold to neighboring utilities (water exported) which is metered and billed. The metered consumption data can be taken directly from billing records for the water audit period. The accuracy of yearly metered consumption data can be refined by including an adjustment to account for customer meter reading lagtime, however additional analysis is necessary to determine the adjustment value, which may or may not be significant.
C18: Billed unmetered consumption | E18: All billed consumption which is calculated based on estimates or norms but is not metered. This might be a very small component in fully metered systems (for example billing based on estimates for the period a customer meter is out of order) but can be the key consumption component in systems without universal metering. It does NOT include water sold to neighboring utilities (water exported) which is unmetered but billed.
C20: Connection density | E20: =number of connections / length of mains
C22: Customer metering inaccuracies | E22: Apparent water losses caused by the collective under-registration of customer water meters. Many customer water meters will wear as large cumulative volumes of water are passed through them over time. This causes the meters to under-register. The auditor has two options for entering data for this component of the audit. The auditor can enter a percentage under-registration (typically an estimated value), this will apply the selected percentage to the two categories of metered consumption to determine the volume of water not recorded due to customer meter inaccuracy. Alternatively, if the auditor has substantial data from meter testing to arrive at their own volumes of such losses, this volume may be entered directly. Note that a value of zero will be accepted but an alert will appear asking if the customer population is unmetered. Since all metered systems have some degree of inaccuracy, then a positive value should be entered. A value of zero in this component is valid only if the water utility does not meter its customer population.
C24: Customer retail unit cost | E24: The Customer Retail Unit Cost represents the charge that customers pay for water service. This unit cost is applied to the components of apparent loss, since these losses represent water reaching customers but not (fully) paid for. It is important to compile these costs per the same unit cost basis as the volume measure included in the water audit. For example, if all water volumes are measured in million gallons, then the unit cost should be dollars per million gallon ($/mil gal). The software allows the user to select the units that are charged to customers (either $/1,000 gallons, $/hundred cubic feet or $/1,000 litres) and automatically converts these units to the units that appear in the "WATER SUPPLIED" box. Since most water utilities have a rate structure that includes a variety of different costs based upon class of customer, a weighted average of individual costs and number of customer accounts in each class can be calculated to determine a single composite cost that should be entered into this cell. Finally, the weighted average cost should also include additional charges for sewer, stormwater or biosolids processing, if these charges are based upon the volume of potable water consumed.
C26: Infrastructure Leakage Index (ILI) | E26: The ratio of the Current Annual Real Losses (Real Losses) to the Unavoidable Annual Real Losses (UARL). The ILI is a highly effective performance indicator for comparing (benchmarking) the performance of utilities in operational management of real losses.
C28: Length of mains | E28: Length of all pipelines (except service connections) in the system starting from the point of system input metering (for example at the outlet of the treatment plant). It is also recommended to include in this measure the total length of fire hydrant lead pipe. Hydrant lead pipe is the pipe branching from the water main to the fire hydrant. Fire hydrant leads are typically of a sufficiently large size that is more representative of a pipeline than a service connection. The average length of hydrant leads across the entire system can be assumed if not known, and multiplied by the number of fire hydrants in the system, which can also be assumed if not known. This value can then be added to the total pipeline length. Total length of mains can therefore be calculated as: Length of Mains, miles = (total pipeline length, miles) + [ {(average fire hydrant lead length, ft) x (number of fire hydrants)} / 5,280 ft/mile ] or Length of Mains, kilometres = (total pipeline length, kilometres) + [ {(average fire hydrant lead length, metres) x (number of fire hydrants)} / 1,000 metres/kilometre ]
C30: Master meter error adjustment | E30: An estimate or measure of the degree of any inaccuracy that exists in the master meters measuring the Volume from own sources. Please also indicate if this adjustment is because the master meters under-registered (did not capture all the flow) or over-registered (overstated the actual flow). All systems encounter some degree of error in their Master Meter data. Please enter a positive value.
C32: NON-REVENUE WATER | E32: = Apparent Losses + Real Losses + Unbilled Metered + Unbilled Unmetered Water which does not provide any revenue to the utility
C34: Number of active AND inactive service connections | E34: Number of service connections, main to curb stop. Please note that this includes the actual number of distinct piping connections including fire connections whether active or inactive. This may differ substantially from the number of Customers (or number of accounts)
... C46: Unavoidable Annual Real Losses (UARL) | E46: UARL (gallons/day)=(5.41Lm + 0.15Nc + 7.5Lc) xP, or UARL (litres/day)=(18.0Lm + 0.8Nc + 25.0Lc) xP where: Lm = length of mains (miles or kilometres) Nc = number of service connections Lc = total length of customer service lines (miles or km) = Nc multiplied by the average distance of customer service line, Lp (miles or km) P = Pressure (psi or metres)
E47: The UARL is a theoretical reference value representing the technical low limit of leakage that could be achieved if all of today's best technology could be successfully applied. It is a key variable in the calculation of the Infrastructure Leakage Index (ILI). It is not necessary that water utilities set this level as the target level of leakage, unless water is unusually expensive, scarce or both. NOTE: The UARL calculation has not yet been fully proven as effective for very small, or low pressure water distribution systems. If, in gallons per day: (Lm x 32) + Nc < 3000 or P <35psi in litres per day: (Lm x 20) + Nc < 3000 or P < 25m then the calculated UARL value may not be valid. The software does not display a value of UARL or ILI if either of these conditions is true.
C49: Unbilled Authorized Consumption | E49: All consumption that is unbilled, but still authorized by the utility. See "Authorized Consumption" for more information.
C51: Unbilled metered consumption | E51: Metered Consumption which is for any reason unbilled. This might for example include metered consumption of the utility itself or water provided to institutions free of charge. It does NOT include water sold to neighboring utilities (water exported) which is metered but unbilled.
C53: Unbilled unmetered consumption | E53: Any kind of Authorized Consumption which is neither billed nor metered. This component typically includes items such as fire fighting, flushing of mains and sewers, street cleaning, frost protection, etc. In most water utilities it is a small component which is very often substantially overestimated. It does NOT include water sold to neighboring utilities (water exported) which is unmetered and unbilled – an unlikely case. This component has many sub-components of water use which are often tedious to identify and quantify. Because of this, and the fact that it is usually a small portion of the water supplied, it is recommended that the auditor apply the default value of 1.25% of the volume from own sources. Select the default percentage to enter this value. If the water utility already has well validated data that gives a value substantially higher or lower than the default volume, then the auditor should enter their own volume. However the default approach is recommended for most water utilities. Note that a value of zero is not permitted, since all water utilities have some volume of water in this component occurring in their system.
C55: Units and Conversions | E55: The user may develop an audit based on one of three unit selections: 1) Million Gallons (US) 2) Megalitres (Thousand Cubic Metres) 3) Acre-feet Once this selection has been made in the instructions sheet, all calculations are made on the basis of the chosen units. Should the user wish to make additional conversions, a unit converter is provided below (use drop down menus to select units from the yellow unit boxes):
E56: Enter Units: | G56: Convert From… | I56: Converts to…..
E57: 1 | G57: Million Gallons (US) | H57: = | I57: =E57*INDEX(Sheet1!N2:P4,MATCH(G57,Sheet1!M2:M4,0),MATCH(J57,Sheet1!N1:P1,0)) -> 3.0688833 | J57: Acre-feet
G58: ="(conversion factor = "&INDEX(Sheet1!N2:P4,MATCH(G57,Sheet1!M2:M4,0),MATCH(J57,Sheet1!N1:P1,0))&")" -> (conversion factor = 3.06888328973723)
C61: Use of Option Buttons
C63: Variable production cost (applied to Real Losses) | E63: The cost to produce and supply the next unit of water. (E.g., $/million gallons) This cost is determined by calculating the summed unit costs for ground and surface water treatment and all power used for pumping from the source to the customer. It should also include the unit cost of bulk water purchased as an import if applicable.
C65: Volume from own sources | E65: The volume of treated water input to system from own production facilities
C67: Water exported | E67: Bulk water sold and conveyed out of the water distribution system. Typically this is water sold to a neighboring water utility. Be sure to account for any export meter inaccuracy in reporting this volume
C69: Water imported | E69: Bulk water purchased to become part of the water supplied. Typically this is water purchased from a neighboring water utility or regional water authority. Be sure to account for any import meter inaccuracy in reporting this volume
C71: WATER LOSSES | E71: = apparent losses + real losses The difference between System Input and Authorized Consumption. Water losses can be considered as a total volume for the whole system, or for partial systems such as transmission or distribution systems, or individual zones. Water Losses consist of Real Losses and Apparent Losses.

Sheet Loss Control Planning
C2: AWWA WLCC Free Water Audit Software: Determining Water Loss Standing
C4: Water Loss Control Planning Guide
D5: Water Audit Data Validity Level / Score
C6: Functional Focus Area | D6: Level I (0-25) | G6: Level II (26-50) | J6: Level III (51-70) | M6: Level IV (71-90) | P6: Level V (91-100)
C7: Audit Data Collection | D7: Launch auditing and loss control team; address production metering deficiencies | G7: Analyze business process for customer metering and billing functions and water supply operations. Identify data gaps. | J7: Establish/revise policies and procedures for data collection | M7: Refine data collection practices and establish as routine business process | P7: Annual water audit is a reliable gauge of year-to-year water efficiency standing
C8: Short-term loss control | D8: Research information on leak detection programs. Begin flowcharting analysis of customer billing system | G8: Conduct loss assessment investigations on a sample portion of the system: customer meter testing, leak survey, unauthorized consumption, etc. | J8: Establish ongoing mechanisms for customer meter accuracy testing, active leakage control and infrastructure monitoring | M8: Refine, enhance or expand ongoing programs based upon economic justification | P8: Stay abreast of improvements in metering, meter reading, billing, leakage management and infrastructure rehabilitation
C9: Long-term loss control | G9: Begin to assess long-term needs requiring large expenditure: customer meter replacement, water main replacement program, new customer billing system or Automatic Meter Reading (AMR) system. | J9: Begin to assemble economic business case for long-term needs based upon improved data becoming available through the water audit process. | M9: Conduct detailed planning, budgeting and launch of comprehensive improvements for metering, billing or infrastructure management | P9: Continue incremental improvements in short-term and long-term loss control interventions
C10: Target-setting | J10: Establish long-term apparent and real loss reduction goals (+10 year horizon) | M10: Establish mid-range (5 year horizon) apparent and real loss reduction goals | P10: Evaluate and refine loss control goals on a yearly basis
C11: Benchmarking | J11: Preliminary Comparisons - can begin to rely upon the Infrastructure Leakage Index (ILI) for performance comparisons for real losses (see below table) | M11: Performance Benchmarking - ILI is meaningful in comparing real loss standing | P11: Identify Best Practices/ Best in class - the ILI is very reliable as a real loss performance indicator for best in class service
C12: For validity scores of 50 or below, the shaded blocks should not be focus areas until better data validity is achieved.
E14: 0 | H14: 26 | K14: 51 | N14: 71 | Q14: 91
E15: 25 | H15: 50 | K15: 70 | N15: 90 | Q15: 100
E16: =IF(AND(GradingAssessment!$G$22>=E14,GradingAssessment!$G$22<='Loss Control Planning'!E15),1,0) -> 0 | H16: =IF(AND(GradingAssessment!$G$22>=H14,GradingAssessment!$G$22<='Loss Control Planning'!H15),1,0) -> 0 | K16: =IF(AND(GradingAssessment!$G$22>=K14,GradingAssessment!$G$22<='Loss Control Planning'!K15),1,0) -> 1 | N16: =IF(AND(GradingAssessment!$G$22>=N14,GradingAssessment!$G$22<='Loss Control Planning'!N15),1,0) -> 0 | Q16: =IF(AND(GradingAssessment!$G$22>=Q14,GradingAssessment!$G$22<='Loss Control Planning'!Q15),1,0) -> 0
C17: Once data has been entered into the Reporting Worksheet, the performance indicators are automatically calculated. How does a water utility operator know how well his or her system is performing? The AWWA Water Loss Control Committee provided the following table to assist water utilities is gauging an approximate Infrastructure Leakage Index (ILI) that is appropriate for their water system and local conditions. The lower the amount of leakage and real losses that exist in the system, then the lower the ILI value will be. Note: this table offers an approximate guideline for leakage reduction target-setting. The best means of setting such targets include performing an economic assessment of various loss control methods. However, this table is useful if such an assessment is not possible.
C19: General Guidelines for Setting a Target ILI (without doing a full economic analysis of leakage control options)
C20: Target ILI Range | D20: Financial Considerations | I20: Operational Considerations | N20: Water Resources Considerations
B21: 1 | C21: 1.0 - 3.0 | D21: Water resources are costly to develop or purchase; ability to increase revenues via water rates is greatly limited because of regulation or low ratepayer affordability. | I21: Operating with system leakage above this level would require expansion of existing infrastructure and/or additional water resources to meet the demand. | N21: Available resources are greatly limited and are very difficult and/or environmentally unsound to develop. | S21: =IF(AND('Reporting Worksheet'!$I$105>='Loss Control Planning'!U21,'Reporting Worksheet'!$I$105<='Loss Control Planning'!V21),1,0) -> 0 | U21: 1 | V21: 3
B22: 2 | C22: >3.0 -5.0 | D22: Water resources can be developed or purchased at reasonable expense; periodic water rate increases can be feasibly imposed and are tolerated by the customer population. | I22: Existing water supply infrastructure capability is sufficient to meet long-term demand as long as reasonable leakage management controls are in place. | N22: Water resources are believed to be sufficient to meet long-term needs, but demand management interventions (leakage management, water conservation) are included in the long-term planning. | S22: =IF(AND('Reporting Worksheet'!$I$105>='Loss Control Planning'!U22,'Reporting Worksheet'!$I$105<='Loss Control Planning'!V22),1,0) -> 1 | U22: 3 | V22: 5
B23: 3 | C23: >5.0 - 8.0 | D23: Cost to purchase or obtain/treat water is low, as are rates charged to customers. | I23: Superior reliability, capacity and integrity of the water supply infrastructure make it relatively immune to supply shortages. | N23: Water resources are plentiful, reliable, and easily extracted. | S23: =IF(AND('Reporting Worksheet'!$I$105>='Loss Control Planning'!U23,'Reporting Worksheet'!$I$105<='Loss Control Planning'!V23),1,0) -> 0 | U23: 5 | V23: 8
C24: Greater than 8.0 | D24: Although operational and financial considerations may allow a long-term ILI greater than 8.0, such a level of leakage is not an effective utilization of water as a resource. Setting a target level greater than 8.0 - other than as an incremental goal to a smaller long-term target - is discouraged. | S24: =IF('Reporting Worksheet'!$I$105>'Loss Control Planning'!U24,1,0) -> 0 | U24: 8
B25: 4 | C25: Less than 1.0 | D25: If the calculated Infrastructure Leakage Index (ILI) value for your system is 1.0 or less, two possibilities exist. a) you are maintaining your leakage at low levels in a class with the top worldwide performers in leakage control. b) A portion of your data may be flawed, causing your losses to be greatly understated. This is likely if you calculate a low ILI value but do not employ extensive leakage control practices in your operations. In such cases it is beneficial to validate the data by performing field measurements to confirm the accuracy of production and customer meters, or to identify any other potential sources of error in the data. | S25: =IF('Reporting Worksheet'!$I$105<1,1,0) -> 0 | U25: 1

Sheet Ex. Audit 1 (Million Gallons)
A1: 0
B2: AWWA WLCC Free Water Audit Software: Reporting Worksheet
C4: Water Audit Report for: | D4: Philadelphia Water Department
C5: Reporting Year: | D5: 2008 | G5: 7/2007 - 6/2008
G9: All volumes to be entered as: MILLION GALLONS (US) PER YEAR
C12: WATER SUPPLIED | D12: << Enter grading in column 'E'
C14: Volume from own sources: | E14: 7 | G14: 94536.9 | I14: Million gallons (US)/yr (MG/Yr)
C15: Master meter error adjustment (enter positive value): | E15: 10 | G15: 2779.3 | I15: over-registered | K15: MG/Yr
C16: Water imported: | E16: n/a | I16: MG/Yr
C17: Water exported: | E17: 10 | G17: 7100.4 | I17: MG/Yr
C19: WATER SUPPLIED: | G19: 84657.2 | I19: MG/Yr
E21: .
C22: AUTHORIZED CONSUMPTION
C23: Billed metered: | E23: 7 | G23: 57242.4 | I23: MG/Yr
C24: Billed unmetered: | E24: n/a | I24: MG/Yr
C25: Unbilled metered: | E25: n/a | I25: MG/Yr | J25: Pcnt: | L25: Value:
C26: Unbilled unmetered: | E26: 8 | G26: 764.2 | I26: MG/Yr | J26: 0.0125 | L26: 764.2 | P26: 2
C30: AUTHORIZED CONSUMPTION: | G30: 58006.6 | I30: MG/Yr
C35: WATER LOSSES (Water Supplied - Authorized Consumption) | G35: 26650.6 | I35: MG/Yr
C37: Apparent Losses | J37: Pcnt: | L37: Value:
C38: Unauthorized consumption: | E38: 8 | G38: 2086.3 | I38: MG/Yr | J38: 0.0025 | L38: 2086.3 | P38: 2
C42: Customer metering inaccuracies: | E42: 8 | G42: 190.3 | I42: MG/Yr | L42: 190.3 | P42: 2
C43: Systematic data handling errors: | E43: 5 | G43: 4676.4 | I43: MG/Yr
L44: Choose this option to enter a percentage of billed metered consumption. This is NOT a default value
C47: Apparent Losses: | G47: 6953
C51: Real Losses (Current Annual Real Losses or CARL)
C52: Real Losses = Water Losses - Apparent Losses: | G52: 19697.6 | I52: MG/Yr
C54: WATER LOSSES: | G54: 26650.6 | I54: MG/Yr
C57: NON-REVENUE WATER
C58: NON-REVENUE WATER: | G58: 27414.8 | I58: MG/Yr
C59: = Total Water Loss + Unbilled Metered + Unbilled Unmetered
C60: SYSTEM DATA
C62: Length of mains: | E62: 9 | G62: 3137 | I62: miles
C63: Number of active AND inactive service connections: | E63: 7 | G63: 547932
C64: Connection density: | G64: 174.66752 | I64: conn./mile main
C65: Average length of customer service line: | E65: 7 | G65: 12 | I65: ft
C67: Average operating pressure: | E67: 10 | G67: 55 | I67: psi
P69: 0
C72: COST DATA
C74: Total annual cost of operating water system: | E74: 10 | G74: 219182339 | I74: $/Year
C75: Customer retail unit cost (applied to Apparent Losses): | E75: 9 | G75: 4.97 | I75: $/1000 gallons (US)
C76: Variable production cost (applied to Real Losses): | E76: 9 | G76: 215.5 | I76: $/Million gallons
P78: 0
C81: PERFORMANCE INDICATORS
C83: Financial Indicators
G84: Non-revenue water as percent by volume of Water Supplied: | I84: 0.32383306
G85: Non-revenue water as percent by cost of operating system: | I85: 0.17777859
G86: Annual cost of Apparent Losses: | I86: 34556410
G87: Annual cost of Real Losses: | I87: 4244832.8
C89: Operational Efficiency Indicators
G91: Apparent Losses per service connection per day: | I91: 34.765838 | J91: gallons/connection/day
G93: Real Losses per service connection per day*: | I93: 98.490374 | J93: gallons/connection/day
G95: Real Losses per length of main per day*: | I95: N/A
G97: Real Losses per service connection per day per psi pressure: | I97: 1.7907341 | J97: gallons/connection/day/psi
G99: Unavoidable Annual Real Losses (UARL): | I99: 2178.152 | J99: million gallons/year
G103: From Above, Real Losses = Current Annual Real Losses (CARL): | I103: 19697.6 | J103: million gallons/year
C105: Infrastructure Leakage Index (ILI) [CARL/UARL]: | I105: 9.0432626
C107: * only the most applicable of these two indicators will be calculated
C108: WATER AUDIT DATA VALIDITY SCORE:
C110: *** YOUR SCORE IS: 82 out of 100 *** | P110: 0
C112: A weighted scale for the components of consumption and water loss is included in the calculation of the Water Audit Data Validity Score
C113: PRIORITY AREAS FOR ATTENTION:
C114: Based on the information provided, audit accuracy can be improved by addressing the following components:
C115: 1: Volume from own sources
C117: 2: Billed metered
C119: 3: Systematic data handling errors

Sheet Ex. Audit 2 (Megalitres)
A1: 0
B2: AWWA WLCC Free Water Audit Software: Reporting Worksheet
C4: Water Audit Report for: | D4: Regional Municipality of Peel
C5: Reporting Year: | D5: 2008 | G5: 1/2008 - 12/2008
G9: All volumes to be entered as: MEGALITRES (THOUSAND CUBIC METRES) PER YEAR
C12: WATER SUPPLIED | D12: << Enter grading in column 'E'
C14: Volume from own sources: | E14: 7 | G14: 213977 | I14: Megalitres/yr (or ML/Yr)
C15: Master meter error adjustment (enter positive value): | E15: 4 | G15: 0 | K15: ML/Yr
C16: Water imported: | E16: n/a | G16: 0 | I16: ML/Yr
C17: Water exported: | E17: 7 | G17: 26457.5 | I17: ML/Yr
C19: WATER SUPPLIED: | G19: 187519.5 | I19: ML/Yr
E21: .
C22: AUTHORIZED CONSUMPTION
C23: Billed metered: | E23: 7 | G23: 163665 | I23: ML/Yr
C24: Billed unmetered: | E24: 2 | G24: 433.9 | I24: ML/Yr
C25: Unbilled metered: | E25: 8 | G25: 1768.4 | I25: ML/Yr | J25: Pcnt: | L25: Value:
C26: Unbilled unmetered: | E26: 5 | G26: 230.1 | I26: ML/Yr | J26: 0.0125 | L26: 230.1 | P26: 2
C30: AUTHORIZED CONSUMPTION: | G30: 166097.4 | I30: ML/Yr
C35: WATER LOSSES (Water Supplied - Authorized Consumption) | G35: 21422.1 | I35: ML/Yr
C37: Apparent Losses | J37: Pcnt: | L37: Value:
C38: Unauthorized consumption: | E38: 5 | G38: 886.8 | I38: ML/Yr | J38: 0.0025 | L38: 886.8 | P38: 2
C42: Customer metering inaccuracies: | E42: 7 | G42: 2851 | I42: ML/Yr | L42: 2851 | P42: 2
C43: Systematic data handling errors: | E43: 5 | G43: 0 | I43: ML/Yr
L44: Choose this option to enter a percentage of billed metered consumption. This is NOT a default value
C45: Systematic data handling errors are likely, please enter a non-zero value; otherwise grade = 5
C47: Apparent Losses: | G47: 3737.8
C51: Real Losses (Current Annual Real Losses or CARL)
C52: Real Losses = Water Losses - Apparent Losses: | G52: 17684.3 | I52: ML/Yr
C54: WATER LOSSES: | G54: 21422.1 | I54: ML/Yr
C57: NON-REVENUE WATER
C58: NON-REVENUE WATER: | G58: 23420.6 | I58: ML/Yr
C59: = Total Water Loss + Unbilled Metered + Unbilled Unmetered
C60: SYSTEM DATA
C62: Length of mains: | E62: 8 | G62: 4161 | I62: kilometers
C63: Number of active AND inactive service connections: | E63: 9 | G63: 287905
C64: Connection density: | G64: 69.1913 | I64: conn./km main
C65: Average length of customer service line: | E65: 5 | G65: 16 | I65: metres
C67: Average operating pressure: | E67: 6 | G67: 58.4 | I67: metres (head)
P69: 1
C72: COST DATA
C74: Total annual cost of operating water system: | E74: 3 | G74: 100000000 | I74: $/Year
C75: Customer retail unit cost (applied to Apparent Losses): | E75: 10 | G75: 0.642 | I75: $/1000 litres
C76: Variable production cost (applied to Real Losses): | E76: 10 | G76: 642 | I76: $/Megalitre
C78: Retail costs are less than (or equal to) production costs; please review and correct if necessary | P78: 1
C81: PERFORMANCE INDICATORS
C83: Financial Indicators
G84: Non-revenue water as percent by volume of Water Supplied: | I84: 0.12489688
G85: Non-revenue water as percent by cost of operating system: | I85: 0.15036025
G86: Annual cost of Apparent Losses: | I86: 2399667.6
G87: Annual cost of Real Losses: | I87: 11353321
C89: Operational Efficiency Indicators
G91: Apparent Losses per service connection per day: | I91: 35.569191 | J91: litres/connection/day
G93: Real Losses per service connection per day*: | I93: 168.28515 | J93: litres/connection/day
G95: Real Losses per length of main per day*: | I95: N/A
G97: Real Losses per service connection per day per meter (head) pressure: | I97: 2.8815951 | J97: litres/connection/day/m
G99: Unavoidable Annual Real Losses (UARL): | I99: 8960.9053 | J99: ML/yr
G103: From Above, Real Losses = Current Annual Real Losses (CARL): | I103: 17684.3 | J103: ML/yr
C105: Infrastructure Leakage Index (ILI) [CARL/UARL]: | I105: 1.9734948
C107: * only the most applicable of these two indicators will be calculated
C108: WATER AUDIT DATA VALIDITY SCORE:
C110: *** YOUR SCORE IS: 66 out of 100 *** | P110: 0
C112: A weighted scale for the components of consumption and water loss is included in the calculation of the Water Audit Data Validity Score
C113: PRIORITY AREAS FOR ATTENTION:
C114: Based on the information provided, audit accuracy can be improved by addressing the following components:
C115: 1: Volume from own sources
C117: 2: Billed unmetered
C119: 3: Total annual cost of operating water system

Sheet Acknowledgements
C2: AWWA WLCC Free Water Audit Software: Acknowledgements
C4: AWWA Water Audit Software Version 4.2 Developed by the Water Loss Control Committee of the American Water Works Association May 2010
C6: This software is intended to serve as a basic tool to compile a preliminary, or “top-down”, water audit. It is recommended that users also refer to the 3rd Edition AWWA M36 Publication, Water Audits and Loss Control Programs, for detailed guidance on compiling a comprehensive, or “bottom-up”, water audit using the same water audit methodology.
C8: DEVELOPED BY: | D8: ANDREW CHASTAIN-HOWLEY, Miya Water
D9: DAVID GOFF, P.E. Goff Water Audits & Engineering
D10: GEORGE KUNKEL, P.E. Philadelphia Water Department
D11: ALAIN LALONDE, Veritec Consulting
D12: DAVID SAYERS, Delaware River Basin Commission
C14: REFERENCES: | D14: - Alegre, H., Hirner, W., Baptista, J. and Parena, R. Performance Indicators for Water Supply Services. IWA Publishing ‘Manual of Best Practice’ Series, 2000. ISBN 1 900222 272
D15: - Kunkel, G. et al, 2003. Water Loss Control Committee Report: Applying Worldwide Best Management Practices in Water Loss Control. Journal AWWA, 95:8:65 - AWWA Water Audits and Loss Control Programs, M36 Publication, 3rd Edition, 2009 - Service Connection Diagrams courtesy of Ronnie McKenzie, WRP Pty Ltd.

Sheet Sheet1
B1: $/100 cubic feet (ccf) | C1: $/1000 gallons (US) | D1: $/1000 litres | F1: Conversion table | M1: FROM: TO: | N1: Million gallons (US) | O1: Megalitres (thousand cubic metres) | P1: Acre-feet
A2: Million gallons (US) | B2: =1000000/(F2*100) -> 1336.8056 | C2: 1000 | D2: =1000/F5 -> 3785.4118 | F2: 7.4805195 | G2: gallons / cubic foot | H2: converting FROM volume unit TO pricing UNITS | M2: Million gallons (US) | N2: 1 | O2: =F4 -> 3.7854118 | P2: 3.0688833
A3: Megalitres (thousand cubic metres) | B3: =1000000/F4/(F2*100) -> 353.14667 | C3: =1000/F4 -> 264.17205 | D3: 1000 | F3: 43560 | G3: sq feet / acre | M3: Megalitres (thousand cubic metres) | N3: =1/O2 -> 0.26417205 | O3: 1 | P3: 0.81071319
A4: Acre-feet | B4: =F3/100 -> 435.6 | C4: =F3*F2/1000 -> 325.85143 | D4: =F3*F2*F4/1000 -> 1233.4818 | F4: 3.7854118 | G4: litres / gallon | M4: Acre-feet | N4: =325851.427242/1000000 -> 0.32585143 | O4: 1.2334818 | P4: 1
F5: =1/F4 -> 0.26417205 | G5: gallons / litre
A7: losses | B7: 1 | C7: million gallons (US) | D7: =MATCH(C7,A2:A4,0) -> 1
E8: =INDEX($B$2:$D$4,MATCH(C7,A2:A4,0),MATCH(C9,B1:D1,0)) -> 1336.8056
A9: cost | B9: 10 | C9: $/100 cubic feet (ccf) | D9: =MATCH(C9,B1:D1,0) -> 1
B11: cost = | C11: =B7*B9*E8 -> 13368.056 | I11: Multiply By…
G12: million | I12: From | L12: To
G13: m3 | H13: 1 | I13: Acre-feet | J13: = | K13: =H13*INDEX(N2:P4,MATCH(I13,M2:M4,0),MATCH(L13,N1:P1,0)) -> 1.2334818 | L13: Megalitres (thousand cubic metres)
B15: customer cost
B16: $/100 cubic feet (ccf) | C16: $/1000 gallons (US) | D16: $/1000 litres
A17: million gallons (US) | B17: =1000000/(7.48*100) -> 1336.8984 | C17: 1000 | D17: =1000000/CONVERT(1000,"l","gal") -> 3785.4118
A18: thousand cubic metres | B18: =1000000/CONVERT((7.48*100),"gal","l") -> 353.17119 | C18: =1000000/CONVERT(1000,"gal","l") -> 264.17205 | D18: 1000
A19: acre-feet | B19: =43560/100 -> 435.6 | C19: =43560/(1000/7.48) -> 325.8288 | D19: =F3/(CONVERT(1000,"l","gal")/F2) -> 1233.4818
A22: customer cost | B22: 5 | C22: $/1000 gallons (US) | D22: =MATCH(C22,B16:D16,0) -> 2
E23: =INDEX($B$2:$D$4,MATCH(C24,A2:A4,0),MATCH(C22,B1:D1,0)) -> 1000
A24: marginal production | B24: 5000 | C24: million gallons (US) | D24: =MATCH(C24,A17:A19,0) -> 1
B26: cost = | C26: =(B22*E23)/B24 -> 1
C27: >1 = higher customer cost
C28: <1 = lower customer cost
A31: =IF(ISERROR(1/G60),"",(((G24+G25+G40)*G62)+(G37*G61)*INDEX(Sheet1!B2:D4,MATCH(Instructions!G24,Sheet1!A2:A4,0),MATCH('Reporting Worksheet'!I61:J61,Sheet1!B1:D1,0)))/G60)
B33: (reallosses * real loss cost per unit) + (apparent losses * apparent loss cost per unit * unit conversion factor)
A37: =IF(ISBLANK(Instructions!$G$26),"",IF(Instructions!$G$26="Megalitres (thousand cubic metres)",IF(AND(G55>25,G50*20+G51>3000),(((18*G50)+(0.8*G51)+(25*(G51*G53/1000)))*G55/1000000)*365,"Not valid"),IF(AND(G55>40,G50*32+G51>3000),(((5.41*G50)+(0.15*G51)+(7.5*(G51*G53/5280)))*G55)/1000000*365,"Not Valid")))
A38: IF(AND(G55>40,G50*32+G51>3000),(((5.41*G50)+(0.15*G51)+(7.5*(G51*G53/5280)))*G55)/1000000,"Not Valid")))
A39: Logic:
A40: If volume unit is blank show nothing
A42: If instructions is tcm Then
A43: If pressure > 25 AND length of mains * 20 + # connections > 3000 Then
A44: (((18 * length of mains) + (0.8 * # connections) + (25 * (# service connections * avg len of pipe / 1000))) * pressure) /1000
A45: Otherwise not valid
A47: If instructions is gallons Then
A48: If pressure > 40 AND length of mains * 32 + # connections > 3000 Then
A49: (((5.41 * length of mains) + (0.15 * # connections) + (7.5 * (# service connections * avg len of pipe / 5280))) * pressure) /1000000
A50: Otherwise not valid
... A55: Otherwise not valid
