Workbook

Sheet Instructions
A1: 4.2
B2: AWWA Free Water Audit Software v5.0
U3: Select a state / province from the list
C4: This spreadsheet-based water audit tool is designed to help quantify and track water losses associated with water distribution systems and identify areas for improved efficiency and cost recovery. It provides a "top-down" summary water audit format, and is not meant to take the place of a full-scale, comprehensive water audit format. | U4: Alaska (AK)
U5: Alabama (AL)
C6: Auditors are strongly encouraged to refer to the most current edition of AWWA M36 Manual for Water Audits for detailed guidance on the water auditing process and targetting loss reduction levels | U6: Arkansas (AR)
C7: The spreadsheet contains several separate worksheets. Sheets can be accessed using the tabs towards the bottom of the screen, or by clicking the buttons below. | U7: Arizona (AZ)
U8: California (CA)
U9: Colorado (CO)
C10: Please begin by providing the following information | J10: The following guidance will help you complete the Audit | U10: Connecticut (CT)
U11: Dist. Columbia (DC)
C12: Name of Contact Person: | D12: Eric Storms | J12: All audit data are entered on the | M12: Reporting Worksheet | U12: Delaware (DE)
U13: Florida (FL)
C14: Email Address: | D14: eric.storms@suez.com | L14: Value can be entered by user | U14: Georgia (GA)
U15: Hawaii (HI)
C16: Telephone | Ext.: | D16: 302-252-3032 | L16: Value calculated based on input data | U16: Iowa (IA)
U17: Idaho (ID)
C18: Name of City / Utility: | D18: Suez Water DE | L18: These cells contain recommended default values | U18: Illinois (IL)
U19: Indiana (IN)
C20: City/Town/Municipality: | D20: Wilmington | U20: Kansas (KS)
U21: Kentucky (KY)
C22: State / Province: | D22: Delaware (DE) | J22: Use of Option (Radio) Buttons: | L22: Pcnt: | N22: Value: | U22: Louisiana (LA)
U23: Massachusetts (MA)
C24: Country: | D24: New Castle | L24: 0.0025 | U24: Maryland (MD)
U25: Maine (ME)
C26: Year: | D26: 2020 | E26: Calendar Year | U26: Michigan (MI)
U27: Minnesota (MN)
C28: Start Date: | E28: Enter MM/YYYY numeric format | U28: Missouri (MO)
U29: Mississippi (MS)
C30: End Date: | E30: Enter MM/YYYY numeric format | U30: Montana (MT)
U31: Nebraska (NE)
C32: Audit Preparation Date: | D32: 44202 | U32: Nevada (NV)
U33: New Hampshire (NH)
C34: Volume Reporting Units: | D34: Million gallons (US) | U34: New Jersey (NJ)
U35: New Mexico (NM)
C36: PWSID / Other ID: | U36: New York (NY)
D37: The following worksheets are available by clicking the buttons below or selecting the tabs along the bottom of the page | U37: North Carolina (NC)
U38: North Dakota (ND)
U39: Ohio (OH)
U40: Oklahoma (OK)
U41: Oregon (OR)
U42: Pennsylvania (PA)
U43: Rhode Island (RI)
U44: South Carolina (SC)
U45: South Dakota (SD)
U46: Tennessee (TN)
U47: Texas (TX)
U48: Utah (UT)
U49: Virginia (VA)
U50: Vermont (VT)
L51: If you have questions or comments regarding the software please contact us via email at: | M51: wlc@awwa.org | U51: Washington (WA)
U52: Wisconsin (WI)
U53: West Virginia (WV)
U54: Wyoming (WY)
U55: Alberta (AB)
U56: British Columbia (BC)
U57: Labrador (LB)
U58: Manitoba (MB)
U59: New Brunswick (NB)
U60: Newfoundland (NF)
U61: Nova Scotia (NS)
U62: Nunavut (NU)
U63: North West Terr. (NW)
... U69: International (XX)

Sheet Reporting Worksheet
B2: AWWA Free Water Audit Software: Reporting Worksheet
C4: Water Audit Report for: | D4: =IF(ISBLANK(Instructions!D18),"<< Please enter system details and contact information on the Instructions tab >>",Instructions!D18&IF(ISBLANK(Instructions!D36),""," ("&Instructions!D36&")")) -> Suez Water DE
C5: Reporting Year: | D5: =IF(ISBLANK(Instructions!D26),"",Instructions!D26) -> 2020 | G5: =IF(ISBLANK(Instructions!D26),"",IF(Instructions!E26="Calendar Year","1/"&Instructions!D26&" - "&"12/"&Instructions!D26,IF(OR(ISBLANK(Instructions!D28),ISBLANK(Instructions!D30)),"",MONTH(Instructions!D28)&"/"&YEAR(Instructions!D28)&" - "&MONTH(Instructions!D30)&"/"&YEAR(Instructions!D30)))) -> 1/2020 - 12/2020
G9: =IF(ISBLANK(Instructions!D34),"PLEASE CHOOSE REPORTING UNITS FROM THE INSTRUCTIONS SHEET BEFORE ENTERING DATA","All volumes to be entered as: "&UPPER(Instructions!$D$34)&" PER YEAR") -> All volumes to be entered as: MILLION GALLONS (US) PER YEAR
J12: Master Meter and Supply Error Adjustments
C13: WATER SUPPLIED | D13: <----------- Enter grading in column 'E' and 'J' ----------> | L13: Pcnt: | N13: Value: | R13: Pcnt(1) or Val(2) | T13: Raw Vol | U13: MME | W13: Grading weighting points in red
C15: Volume from own sources: | E15: 7 | G15: 5243.759 | I15: =IF(Instructions!$D$34="million gallons (US)","MG/Yr",IF(Instructions!$D$34="Megalitres (thousand cubic metres)","ML/Yr",IF(Instructions!$D$34="acre-feet","acre-ft/yr",""))) -> MG/Yr | P15: =IF(Instructions!$D$34="million gallons (US)","MG/Yr",IF(Instructions!$D$34="Megalitres (thousand cubic metres)","ML/Yr",IF(Instructions!$D$34="acre-feet","acre-ft/yr",""))) -> MG/Yr | R15: 1 | S15: =IF(G15>0,IF(R15=1,L15*G15,N15),0) -> 0 | T15: =$T$19/$T$18*G15 -> 33.177901 | U15: =$T$19/$T$18*ABS(S15) -> 0
C16: Water imported: | E16: 9 | G16: 233.6473 | I16: =IF(Instructions!$D$34="million gallons (US)","MG/Yr",IF(Instructions!$D$34="Megalitres (thousand cubic metres)","ML/Yr",IF(Instructions!$D$34="acre-feet","acre-ft/yr",""))) -> MG/Yr | P16: =IF(Instructions!$D$34="million gallons (US)","MG/Yr",IF(Instructions!$D$34="Megalitres (thousand cubic metres)","ML/Yr",IF(Instructions!$D$34="acre-feet","acre-ft/yr",""))) -> MG/Yr | R16: 1 | S16: =IF(G16>0,IF(R16=1,L16*G16,N16),0) -> 0 | T16: =$T$19/$T$18*G16 -> 1.4783149 | U16: =$T$19/$T$18*ABS(S16) -> 0
C17: Water exported: | E17: 2 | G17: 54.335 | I17: =IF(Instructions!$D$34="million gallons (US)","MG/Yr",IF(Instructions!$D$34="Megalitres (thousand cubic metres)","ML/Yr",IF(Instructions!$D$34="acre-feet","acre-ft/yr",""))) -> MG/Yr | P17: =IF(Instructions!$D$34="million gallons (US)","MG/Yr",IF(Instructions!$D$34="Megalitres (thousand cubic metres)","ML/Yr",IF(Instructions!$D$34="acre-feet","acre-ft/yr",""))) -> MG/Yr | R17: 1 | S17: =IF(G17>0,IF(R17=1,L17*G17,N17),0) -> 0 | T17: =$T$19/$T$18*G17 -> 0.34378415 | U17: =$T$19/$T$18*ABS(S17) -> 0
J18: Enter negative % or value for under-registration | T18: =G15+G16+G17+IF(G15>0,ABS(S15),0)+IF(G16>0,ABS(S16),0)+IF(G17>0,(ABS(S17)),) -> 5531.7413
C19: WATER SUPPLIED: | G19: =IF(G15>0,IF(R15=1,G15/(1+L15),G15-N15),0)+IF(G16>0,IF(R16=1,G16/(1+L16),G16-N16),0)-IF(G17>0,IF(R17=1,G17/(1+L17),G17-N17),0) -> 5423.0713 | I19: =IF(Instructions!$D$34="million gallons (US)","MG/Yr",IF(Instructions!$D$34="Megalitres (thousand cubic metres)","ML/Yr",IF(Instructions!$D$34="acre-feet","acre-ft/yr",""))) -> MG/Yr | J19: Enter positive % or value for over-registration | T19: =GradingAssessment!D27 -> 35 | U19: total weighting pts
E21: .
C22: AUTHORIZED CONSUMPTION
C23: Billed metered: | E23: 9 | G23: 4440.547 | I23: =IF(Instructions!$D$34="million gallons (US)","MG/Yr",IF(Instructions!$D$34="Megalitres (thousand cubic metres)","ML/Yr",IF(Instructions!$D$34="acre-feet","acre-ft/yr",""))) -> MG/Yr
C24: Billed unmetered: | E24: n/a | I24: =IF(Instructions!$D$34="million gallons (US)","MG/Yr",IF(Instructions!$D$34="Megalitres (thousand cubic metres)","ML/Yr",IF(Instructions!$D$34="acre-feet","acre-ft/yr",""))) -> MG/Yr
C25: Unbilled metered: | E25: 8 | G25: 53.98333 | I25: =IF(Instructions!$D$34="million gallons (US)","MG/Yr",IF(Instructions!$D$34="Megalitres (thousand cubic metres)","ML/Yr",IF(Instructions!$D$34="acre-feet","acre-ft/yr",""))) -> MG/Yr | L25: Pcnt: | N25: Value: | AA25: Testing... different object positioning settings to try to prevent radio buttons from moving - seeing this on many completed audits. Evaluate performance during beta testing
C26: Unbilled unmetered: | G26: =IF(OR(R26=1,AND(R26=2,N26=0)),L26*$G$19,N26) -> 67.788391 | I26: =IF(Instructions!$D$34="million gallons (US)","MG/Yr",IF(Instructions!$D$34="Megalitres (thousand cubic metres)","ML/Yr",IF(Instructions!$D$34="acre-feet","acre-ft/yr",""))) -> MG/Yr | L26: 0.0125 | P26: =IF(Instructions!$D$34="million gallons (US)","MG/Yr",IF(Instructions!$D$34="Megalitres (thousand cubic metres)","ML/Yr",IF(Instructions!$D$34="acre-feet","acre-ft/yr",""))) -> MG/Yr | R26: 1 | T26: Format Shape > Properties - Object positioning: Move and Size with cells
N27: 24061
C28: =IF(R26=1," Default option selected for Unbilled unmetered - a grading of 5 is applied but not displayed",IF(R26=2,IF(N26>0.0125*G19," Unbilled Unmetered volume entered is greater than the recommended default value",IF(N26=0,"Enter a positive value, otherwise a default percentage of 1.25% (of billed metered) is applied and a grading of 5 is applied but not displayed","")))) -> Default option selected for Unbilled unmetered - a grading of 5 is applied but not displayed
C30: AUTHORIZED CONSUMPTION: | G30: =SUM(G23:G26) -> 4562.3187 | I30: =IF(Instructions!$D$34="million gallons (US)","MG/Yr",IF(Instructions!$D$34="Megalitres (thousand cubic metres)","ML/Yr",IF(Instructions!$D$34="acre-feet","acre-ft/yr",""))) -> MG/Yr
C32: =IF(AND(G30>=G19,(G30<>0))," Check input values; WATER SUPPLIED should be greater than AUTHORIZED CONSUMPTION","") | T32: look into locking radio buttons in place - they often seem to move
C35: WATER LOSSES (Water Supplied - Authorized Consumption) | G35: =G19-G30 -> 860.75258 | I35: =IF(Instructions!$D$34="million gallons (US)","MG/Yr",IF(Instructions!$D$34="Megalitres (thousand cubic metres)","ML/Yr",IF(Instructions!$D$34="acre-feet","acre-ft/yr",""))) -> MG/Yr
C37: Apparent Losses | L37: Pcnt: | N37: Value:
C38: Unauthorized consumption: | G38: =IF(OR(R38=1,AND(R38=2,N38=0)),L38*$G$19,N38) -> 13.557678 | I38: =IF(Instructions!$D$34="million gallons (US)","MG/Yr",IF(Instructions!$D$34="Megalitres (thousand cubic metres)","ML/Yr",IF(Instructions!$D$34="acre-feet","acre-ft/yr",""))) -> MG/Yr | L38: 0.0025 | P38: =IF(Instructions!$D$34="million gallons (US)","MG/Yr",IF(Instructions!$D$34="Megalitres (thousand cubic metres)","ML/Yr",IF(Instructions!$D$34="acre-feet","acre-ft/yr",""))) -> MG/Yr | R38: 1 | T38: Format Shape > Properties - Object positioning: Move but don't size with cells
C40: =IF(R38=1," Default option selected for unauthorized consumption - a grading of 5 is applied but not displayed ",IF(R38=2,IF(N38>0.0025*G19,"Unauthorized consumption volume entered is greater than the recommended default value",IF(N38=0,"Enter a positive value, otherwise a default percentage of 0.25% is applied and a grading of 5 is applied but not displayed","")))) -> Default option selected for unauthorized consumption - a grading of 5 is applied but not displayed
C42: Customer metering inaccuracies: | E42: 6 | G42: =IF(R42=1,((G23+G25)/(1-L42))-(G23+G25),N42) -> 0 | I42: =IF(Instructions!$D$34="million gallons (US)","MG/Yr",IF(Instructions!$D$34="Megalitres (thousand cubic metres)","ML/Yr",IF(Instructions!$D$34="acre-feet","acre-ft/yr",""))) -> MG/Yr | L42: 0 | P42: =IF(Instructions!$D$34="million gallons (US)","MG/Yr",IF(Instructions!$D$34="Megalitres (thousand cubic metres)","ML/Yr",IF(Instructions!$D$34="acre-feet","acre-ft/yr",""))) -> MG/Yr | R42: 1 | T42: Format Shape > Properties - Was forced to change this to: size with cells because of "Can't shift objects off sheet error"
C43: Systematic data handling errors: | G43: =IF(R43=1,L43*$G$23,N43) -> 11.101367 | I43: =IF(Instructions!$D$34="million gallons (US)","MG/Yr",IF(Instructions!$D$34="Megalitres (thousand cubic metres)","ML/Yr",IF(Instructions!$D$34="acre-feet","acre-ft/yr",""))) -> MG/Yr | L43: 0.0025 | P43: =IF(Instructions!$D$34="million gallons (US)","MG/Yr",IF(Instructions!$D$34="Megalitres (thousand cubic metres)","ML/Yr",IF(Instructions!$D$34="acre-feet","acre-ft/yr",""))) -> MG/Yr | R43: 1
C45: =IF(OR(G19=0,E43="n/a"),"",IF(OR(ISBLANK(G43),G43=0),"Systematic data handling errors are likely, please enter a positive, non-zero value; otherwise grade = 1 (not displayed)",IF(R43=1," Default option selected for Systematic data handling errors - a grading of 5 is applied but not displayed",""))) -> Default option selected for Systematic data handling errors - a grading of 5 is applied but not displayed
C47: Apparent Losses: | G47: =G38+G42+G43 -> 24.659046 | I47: =IF(Instructions!$D$34="million gallons (US)","MG/Yr",IF(Instructions!$D$34="Megalitres (thousand cubic metres)","ML/Yr",IF(Instructions!$D$34="acre-feet","acre-ft/yr",""))) -> MG/Yr
C49: =IF(AND(G47>=G35,(G47<>0)),"Check input values; APPARENT LOSSES should be less than WATER LOSSES","")
C51: Real Losses (Current Annual Real Losses or CARL)
C52: Real Losses = Water Losses - Apparent Losses: | G52: =G35-G47 -> 836.09353 | I52: =IF(Instructions!$D$34="million gallons (US)","MG/Yr",IF(Instructions!$D$34="Megalitres (thousand cubic metres)","ML/Yr",IF(Instructions!$D$34="acre-feet","acre-ft/yr",""))) -> MG/Yr
C54: WATER LOSSES: | G54: =G47+G52 -> 860.75258 | I54: =IF(Instructions!$D$34="million gallons (US)","MG/Yr",IF(Instructions!$D$34="Megalitres (thousand cubic metres)","ML/Yr",IF(Instructions!$D$34="acre-feet","acre-ft/yr",""))) -> MG/Yr
C57: NON-REVENUE WATER
C58: NON-REVENUE WATER: | G58: =G35+G25+G26 -> 982.5243 | I58: =IF(Instructions!$D$34="million gallons (US)","MG/Yr",IF(Instructions!$D$34="Megalitres (thousand cubic metres)","ML/Yr",IF(Instructions!$D$34="acre-feet","acre-ft/yr",""))) -> MG/Yr
C59: = Water Losses + Unbilled Metered + Unbilled Unmetered
C60: SYSTEM DATA
C62: Length of mains: | E62: 9 | G62: 551 | I62: =IF(ISBLANK(Instructions!$D$34),"",IF(Instructions!$D$34="Megalitres (thousand cubic metres)","kilometers","miles")) -> miles
C63: Number of active AND inactive service connections: | E63: 6 | G63: 40933
C64: Service connection density: | G64: =IF(ISERROR(G63/G62),"",G63/G62) -> 74.288566 | I64: =IF(ISBLANK(Instructions!$D$34),"",IF(Instructions!$D$34="Megalitres (thousand cubic metres)","conn./km","conn./mile")& " main") -> conn./mile main
C65: Are customer meters typically located at the curbstop or property line?
G66: No | R66: =IF(G66="Yes",1,0) -> 0 | S66: If Yes,
C67: Average length of customer service line: | E67: 4 | G67: 35 | I67: =IF(ISBLANK(Instructions!$D$34),"",IF(Instructions!D34="Megalitres (thousand cubic metres)","metres","ft")) -> ft | R67: =IF(G66="Yes",10,E67) -> 4 | S67: If Yes, force grade to 10
C68: =IF(G66="Yes","Average length of customer service line has been set to zero and a data grading score of 10 has been applied","") | R68: =IF(G66="Yes",0,G67) -> 35 | S68: If Yes, force length to 0
C69: Average operating pressure: | E69: 4 | G69: 66 | I69: =IF(ISBLANK(Instructions!$D$34),"",IF(Instructions!D34="Megalitres (thousand cubic metres)","metres (head)","psi")) -> psi
C71: =IF(ISBLANK(G69),"",IF(OR(AND(R71=1,G69<=25),AND(R71<>1,G69<=40)),"Note: Average pressure this low will not allow for calculation of UARL","")) | R71: =IF(Instructions!D34="Megalitres (thousand cubic metres)",1,0) -> 0
C74: COST DATA
C76: Total annual cost of operating water system: | E76: 10 | G76: 20745961 | I76: $/Year
C77: Customer retail unit cost (applied to Apparent Losses): | E77: 8 | G77: 5.55 | I77: $/1000 gallons (US) | N77: =IF(AND(NOT(ISBLANK(G77)),ISBLANK(I77)),"<--Enter units","")
C78: Variable production cost (applied to Real Losses): | E78: 4 | G78: 346.7 | I78: ="$/"&IF(Instructions!$D$34="million gallons (US)","Million gallons",IF(Instructions!$D$34="Megalitres (thousand cubic metres)","Megalitre",IF(Instructions!$D$34="acre-feet","acre-ft",""))) -> $/Million gallons
C80: =IF(OR(ISBLANK(I77),ISBLANK(I78),ISBLANK(G78),ISBLANK(Instructions!D34)),"",IF(G77*INDEX(Sheet1!B2:D4,MATCH(Instructions!D34,Sheet1!A2:A4,0),MATCH(I77,Sheet1!B1:D1,0))/G78>1,"","Retail costs are less than (or equal to) production costs; please review and correct if necessary")) | R80: =IF(OR(ISBLANK(I77),ISBLANK(I78),ISBLANK(G78)),"",IF(G77*INDEX(Sheet1!B2:D4,MATCH(Instructions!D34,Sheet1!A2:A4,0),MATCH(I77,Sheet1!B1:D1,0))/G78>1,0,1)) -> 0
C83: WATER AUDIT DATA VALIDITY SCORE:
C85: =IF(ISERROR(GradingAssessment!M24),"",IF(GradingAssessment!M24<=0,"*** YOUR SCORE IS: "&ROUND(GradingAssessment!G24,0)&" out of 100 ***",IF(GradingAssessment!M24>0,"Add a grading value for "&GradingAssessment!M24&" parameter(s) to enable an audit score to be calculated"))) -> *** YOUR SCORE IS: 70 out of 100 *** | R85: =GradingAssessment!M24 -> 0
C87: =IF(ISERROR(GradingAssessment!M24),"",IF(GradingAssessment!M24<=0,"A weighted scale for the components of consumption and water loss is included in the calculation of the Water Audit Data Validity Score","")) -> A weighted scale for the components of consumption and water loss is included in the calculation of the Water Audit Data Validity Score
C88: PRIORITY AREAS FOR ATTENTION:
C89: Based on the information provided, audit accuracy can be improved by addressing the following components:
C90: =IF(ISERROR(GradingAssessment!M24),""," 1: "&VLOOKUP(1,GradingAssessment!$I$4:$J$23,2,FALSE)) -> 1: Volume from own sources
C92: =IF(ISERROR(GradingAssessment!M24),""," 2: "&VLOOKUP(2,GradingAssessment!$I$4:$J$23,2,FALSE)) -> 2: Variable production cost (applied to Real Losses)
C94: =IF(ISERROR(GradingAssessment!M24),""," 3: "&VLOOKUP(3,GradingAssessment!$I$4:$J$23,2,FALSE)) -> 3: Customer metering inaccuracies

Sheet Performance Indicators
A1: 0
B2: AWWA Free Water Audit Software: System Attributes and Performance Indicators
C4: Water Audit Report for: | D4: =IF(ISBLANK(Instructions!D18),"<< Please enter system details and contact information on the Instructions tab >>",Instructions!D18&IF(ISBLANK(Instructions!D36),""," ("&Instructions!D36&")")) -> Suez Water DE
C5: Reporting Year: | D5: =IF(ISBLANK(Instructions!D26),"",Instructions!D26) -> 2020 | G5: =IF(ISBLANK(Instructions!D26),"",IF(Instructions!E26="Calendar Year","1/"&Instructions!D26&" - "&"12/"&Instructions!D26,IF(OR(ISBLANK(Instructions!D28),ISBLANK(Instructions!D30)),"",MONTH(Instructions!D28)&"/"&YEAR(Instructions!D28)&" - "&MONTH(Instructions!D30)&"/"&YEAR(Instructions!D30)))) -> 1/2020 - 12/2020
C9: =IF(ISBLANK(Instructions!$D$34),"********** REPORTING UNITS MUST BE SELECTED ON THE INSTRUCTIONS WORKSHEET BEFORE PERFORMANCE INDICATORS CAN BE DISPLAYED **********",IF(GradingAssessment!M24>0," ********** DATA GRADING MUST BE COMPLTED ON THE REPORTING WORKSHEET BEFORE PERFORMANCE INDICATORS CAN BE DISPLAYED **********","*** YOUR WATER AUDIT DATA VALIDITY SCORE IS: "&ROUND(GradingAssessment!G24,0)&" out of 100 ***")) -> *** YOUR WATER AUDIT DATA VALIDITY SCORE IS: 70 out of 100 ***
C10: System Attributes:
G11: Apparent Losses: | I11: =IF(ISBLANK(Instructions!$D$34),"",'Reporting Worksheet'!G47) -> 24.659046 | J11: =IF(Instructions!$D$34="million gallons (US)","MG/Yr",IF(Instructions!$D$34="Megalitres (thousand cubic metres)","ML/Yr",IF(Instructions!$D$34="acre-feet","acre-ft/yr",""))) -> MG/Yr | R11: =GradingAssessment!M24 -> 0 | S11: >0 if a grading has been missed
G13: + Real Losses: | I13: =IF(ISBLANK(Instructions!$D$34),"",'Reporting Worksheet'!G52) -> 836.09353 | J13: =IF(Instructions!$D$34="million gallons (US)","MG/Yr",IF(Instructions!$D$34="Megalitres (thousand cubic metres)","ML/Yr",IF(Instructions!$D$34="acre-feet","acre-ft/yr",""))) -> MG/Yr | R13: =IF(ISBLANK(Instructions!$D$34),0,1) -> 1 | S13: =0 if no reporting units selected
G15: = Water Losses: | I15: =IF(ISBLANK(Instructions!$D$34),"",'Reporting Worksheet'!G54) -> 860.75258 | J15: =IF(Instructions!$D$34="million gallons (US)","MG/Yr",IF(Instructions!$D$34="Megalitres (thousand cubic metres)","ML/Yr",IF(Instructions!$D$34="acre-feet","acre-ft/yr",""))) -> MG/Yr
G17: Unavoidable Annual Real Losses (UARL): | I17: =IF(ISBLANK(Instructions!$D$34),"",IF(Instructions!$D$34="Megalitres (thousand cubic metres)",IF(AND('Reporting Worksheet'!G69>=25,'Reporting Worksheet'!G62*20+'Reporting Worksheet'!G63>3000),(((18*'Reporting Worksheet'!G62)+(0.8*'Reporting Worksheet'!G63)+(25*('Reporting Worksheet'!G63*'Reporting Worksheet'!R68/1000)))*'Reporting Worksheet'!G69/1000000)*365,"Not Valid"),IF(AND('Reporting Worksheet'!G69>=35,'Reporting Worksheet'!G62*32+'Reporting Worksheet'!G63>3000),(((5.41*'Reporting Worksheet'!G62)+(0.15*'Reporting Worksheet'!G63)+(7.5*('Reporting Worksheet'!G63*'Reporting Worksheet'!R68/5280)))*'Reporting Worksheet'!G69)/IF(Instructions!$D$34="Million gallons (US)",1000000,325851.427242)*365,"See limits in definition"))) -> 268.74518 | J17: =IF(Instructions!$D$34="million gallons (US)","MG/Yr",IF(Instructions!$D$34="Megalitres (thousand cubic metres)","ML/Yr",IF(Instructions!$D$34="acre-feet","acre-ft/yr",""))) -> MG/Yr
G19: Annual cost of Apparent Losses: | I19: =IF(OR(ISBLANK(Instructions!$D$34),ISBLANK('Reporting Worksheet'!I77)),"",('Reporting Worksheet'!G47*'Reporting Worksheet'!G77)*INDEX(Sheet1!B2:D4,MATCH(Instructions!D34,Sheet1!A2:A4,0),MATCH('Reporting Worksheet'!I77,Sheet1!B1:D1,0))) -> 136857.7
G21: Annual cost of Real Losses: | I21: =IF(ISBLANK(Instructions!D34),"",IF(ISBLANK('Reporting Worksheet'!G78),"",'Reporting Worksheet'!G52*(IF(R21=FALSE,'Reporting Worksheet'!G78,IF(R21=TRUE,'Reporting Worksheet'!G77*INDEX(Sheet1!B2:D4,MATCH(Instructions!D34,Sheet1!A2:A4,0),MATCH('Reporting Worksheet'!I77,Sheet1!B1:D1,0)),""))))) -> 4640319.1 | L21: Valued at | M21: =IF(R21=FALSE,"Variable Production Cost","Customer Retail Unit Cost") -> Customer Retail Unit Cost | R21: TRUE | S21: FALSE=VPC;TRUE=CRUC
J22: Return to Reporting Worksheet to change this assumption | S22: We could add a 3rd option - another box for $ input (at user defined rate)
C24: Performance Indicators:
G26: Non-revenue water as percent by volume of Water Supplied: | I26: =IF(ISERROR(1/'Reporting Worksheet'!G19),"",('Reporting Worksheet'!G25+'Reporting Worksheet'!G26+'Reporting Worksheet'!G47+'Reporting Worksheet'!G52)/'Reporting Worksheet'!G19) -> 0.18117488
G28: Non-revenue water as percent by cost of operating system: | I28: =IF(ISERROR(1/'Reporting Worksheet'!G76),"",((('Reporting Worksheet'!G25+'Reporting Worksheet'!G26+'Reporting Worksheet'!G52)*IF(R21=FALSE,'Reporting Worksheet'!G78,'Reporting Worksheet'!G77*INDEX(Sheet1!B2:D4,MATCH(Instructions!D34,Sheet1!A2:A4,0),MATCH('Reporting Worksheet'!I77,Sheet1!B1:D1,0))))+('Reporting Worksheet'!G47*'Reporting Worksheet'!G77*INDEX(Sheet1!B2:D4,MATCH(Instructions!D34,Sheet1!A2:A4,0),MATCH('Reporting Worksheet'!I77,Sheet1!B1:D1,0))))/'Reporting Worksheet'!G76) -> 0.26284682 | J28: =" Real Losses valued at "&IF(R21=FALSE,"Variable Production Cost","Customer Retail Unit Cost") -> Real Losses valued at Customer Retail Unit Cost
G32: Apparent Losses per service connection per day: | I32: =IF(ISERROR(1/'Reporting Worksheet'!G63),"",IF(Instructions!$D$34="Acre-feet",'Reporting Worksheet'!G47*325851/1000000,'Reporting Worksheet'!G47)*1000000/365/'Reporting Worksheet'!G63) -> 1.6504783 | J32: =IF(ISBLANK(Instructions!$D$34),"",IF(Instructions!$D$34="Megalitres (thousand cubic metres)","litres","gallons")&"/connection/day") -> gallons/connection/day
G34: Real Losses per service connection per day: | I34: =IF(ISERROR(1/'Reporting Worksheet'!G63),"",IF(Instructions!$D$34="Megalitres (thousand cubic metres)",IF('Reporting Worksheet'!G64>20,'Reporting Worksheet'!G52*1000000/365/'Reporting Worksheet'!G63,"N/A"),IF('Reporting Worksheet'!G64>32,IF(Instructions!$D$34="Million gallons (US)",'Reporting Worksheet'!G52*1000000,'Reporting Worksheet'!G52*325851)/365/'Reporting Worksheet'!G63,"N/A"))) -> 55.961381 | J34: =IF(ISBLANK(Instructions!$D$34),"",IF(Instructions!$D$34="Megalitres (thousand cubic metres)","litres","gallons")&"/connection/day") -> gallons/connection/day
G36: Real Losses per length of main per day*: | I36: =IF(ISERROR(1/'Reporting Worksheet'!G62),"",IF(I34="N/A",IF(Instructions!$D$34="Acre-feet",'Reporting Worksheet'!G52*325851/1000000,'Reporting Worksheet'!G52)*1000000/365/'Reporting Worksheet'!G62,"N/A")) -> N/A | J36: =IF(ISBLANK(Instructions!$D$34),"",IF(I36="N/A","",IF(Instructions!$D$34="Megalitres (thousand cubic metres)","litres/km","gallons/mile")&"/day"))
G38: ="Real Losses per service connection per day per "& IF('Reporting Worksheet'!I69="psi","psi pressure","meter (head) pressure")&":" -> Real Losses per service connection per day per psi pressure: | I38: =IF(I34="N/A","N/A",IF(ISERROR(I34/'Reporting Worksheet'!G69),"",I34/'Reporting Worksheet'!G69)) -> 0.84789971 | J38: =IF(ISBLANK(Instructions!$D$34),"",IF(Instructions!$D$34="Megalitres (thousand cubic metres)","litres/connection/day/m","gallons/connection/day/psi")) -> gallons/connection/day/psi
C41: =IF(I17="Not Valid","*** UARL cannot be calculated as either average pressure, number of connections or length of mains is too small: SEE UARL DEFINITION ***","")
G43: From Above, Real Losses = Current Annual Real Losses (CARL): | I43: =IF(ISBLANK(Instructions!$D$34),"",'Reporting Worksheet'!G52) -> 836.09353 | J43: =IF(OR(ISBLANK(Instructions!$D$34),I17="Not Valid"),"",IF(Instructions!$D$34="Megalitres (thousand cubic metres)","ML",IF(Instructions!$D$34="Acre-feet", "acre-feet","million gallons"))&"/year") -> million gallons/year
C45: Infrastructure Leakage Index (ILI) [CARL/UARL]: | I45: =IF(ISERROR(1/I17),"",I43/I17) -> 3.1111015
C46: ="* This performance indicator applies for systems with a low service connection density of less than "&IF(Instructions!D34="Megalitres (thousand cubic metres)",20,32)&" service connections/"&IF(Instructions!D34="Megalitres (thousand cubic metres)","kilometre","mile")&" of pipeline" -> * This performance indicator applies for systems with a low service connection density of less than 32 service connections/mile of pipeline

Sheet Comments
B2: AWWA Free Water Audit Software: User Comments
B3: Use this worksheet to add comments or notes to explain how an input value was calculated, or to document the sources of the information used.
B5: General Comment:
B7: Audit Item | C7: Comment
B8: Volume from own sources:
B9: Vol. from own sources: Master meter error adjustment:
B10: Water imported:
B11: Water imported: master meter error adjustment:
B12: Water exported:
B13: Water exported: master meter error adjustment:
B14: Billed metered:
B15: Billed unmetered:
B16: Unbilled metered:
B17: Unbilled unmetered:
B18: Unauthorized consumption:
B19: Customer metering inaccuracies:
... B27: Variable production cost (applied to Real Losses):

Sheet Water Balance
B2: AWWA Free Water Audit Software: Water Balance
E5: Water Audit Report for: | F5: =IF(ISBLANK(Instructions!D18),"<< Please enter system details and contact information on the Instructions tab >>",Instructions!D18&IF(ISBLANK(Instructions!D36),""," ("&Instructions!D36&")")) -> Suez Water DE
E6: Reporting Year: | F6: =IF(ISBLANK(Instructions!D26),"",Instructions!D26) -> 2020 | G6: =IF(ISBLANK(Instructions!D26),"",IF(Instructions!E26="Calendar Year","1/"&Instructions!D26&" - "&"12/"&Instructions!D26,IF(OR(ISBLANK(Instructions!D28),ISBLANK(Instructions!D30)),"",MONTH(Instructions!D28)&"/"&YEAR(Instructions!D28)&" - "&MONTH(Instructions!D30)&"/"&YEAR(Instructions!D30)))) -> 1/2020 - 12/2020
E7: Data Validity Score: | F7: =IF(ISBLANK(Instructions!$D$34),"N/A*",IF(GradingAssessment!M24>0,"N/A*",ROUND(GradingAssessment!G24,0))) -> 70 | G7: =IF(F7="N/A*","* Confirm Units and Data Grading are Complete","")
D9: Water Exported | G9: Billed Water Exported | H9: Revenue Water
D10: =IF('Reporting Worksheet'!G17>0,IF('Reporting Worksheet'!R17=1,'Reporting Worksheet'!G17/(1+'Reporting Worksheet'!L17),'Reporting Worksheet'!G17-'Reporting Worksheet'!N17),0) -> 54.335 | H10: =D10 -> 54.335
F11: Billed Authorized Consumption | G11: Billed Metered Consumption (water exported is removed) | H11: Revenue Water | K11: Data for plotting the Water Balance with volume-proportional bars on the Dashboard
G12: ='Reporting Worksheet'!G23 -> 4440.547
B13: Own Sources | E13: Authorized Consumption | F13: ='Reporting Worksheet'!G23+'Reporting Worksheet'!G24 -> 4440.547 | G13: Billed Unmetered Consumption | H13: =SUM(G12+G14) -> 4440.547 | K13: Volume From Own Sources | L13: ='Water Balance'!B17 -> 5243.759
B14: (Adjusted for known errors) | G14: ='Reporting Worksheet'!G24 -> 0 | K14: Water Imported | L14: ='Water Balance'!B27 -> 233.6473
E15: ='Reporting Worksheet'!G30 -> 4562.3187 | F15: Unbilled Authorized Consumption | G15: Unbilled Metered Consumption | H15: Non-Revenue Water (NRW) | K15: Water Exported | L15: ='Water Balance'!D10 -> 54.335 | M15: ='Water Balance'!D10 -> 54.335 | N15: ='Water Balance'!D10 -> 54.335 | O15: ='Water Balance'!D10 -> 54.335 | P15: ='Water Balance'!D10 -> 54.335
G16: ='Reporting Worksheet'!G25 -> 53.98333 | K16: Water Supplied | M16: ='Water Balance'!D21 -> 5423.0713
B17: =IF('Reporting Worksheet'!R15>0,IF('Reporting Worksheet'!R15=1,'Reporting Worksheet'!G15/(1+'Reporting Worksheet'!L15),'Reporting Worksheet'!G15-'Reporting Worksheet'!N15),0) -> 5243.759 | F17: ='Reporting Worksheet'!G25+'Reporting Worksheet'!G26 -> 121.77172 | G17: Unbilled Unmetered Consumption | K17: Authorized Consumption | N17: ='Water Balance'!E15 -> 4562.3187
G18: ='Reporting Worksheet'!G26 -> 67.788391 | K18: Water Losses | N18: ='Water Balance'!E25 -> 860.75258
C19: System Input | D19: Water Supplied | G19: Unauthorized Consumption | H19: ='Reporting Worksheet'!G25+'Reporting Worksheet'!G26+'Reporting Worksheet'!G47+'Reporting Worksheet'!G52 -> 982.5243 | K19: Billed Auth. Cons. | O19: ='Water Balance'!F13 -> 4440.547
C20: =B17+B27 -> 5477.4063 | F20: Apparent Losses | G20: ='Reporting Worksheet'!G38 -> 13.557678 | K20: Unbilled Auth. Cons. | O20: ='Water Balance'!F17 -> 121.77172
D21: ='Reporting Worksheet'!G19 -> 5423.0713 | F21: ='Reporting Worksheet'!G47 -> 24.659046 | G21: Customer Metering Inaccuracies | K21: Apparent Losses | O21: ='Water Balance'!F21 -> 24.659046
G22: ='Reporting Worksheet'!G42 -> 0 | K22: Real Losses | O22: ='Water Balance'!F27 -> 836.09353
G23: Systematic Data Handling Errors | K23: Revenue Water | P23: ='Water Balance'!H13 -> 4440.547
E24: Water Losses | G24: ='Reporting Worksheet'!G43 -> 11.101367 | K24: Non Revenue Water | P24: ='Water Balance'!H19 -> 982.5243
B25: Water Imported | E25: ='Reporting Worksheet'!G54 -> 860.75258 | G25: Leakage on Transmission and/or Distribution Mains | L25: =L13+L14 -> 5477.4063 | M25: =SUM(M13:M24) -> 5477.4063 | N25: =SUM(N13:N24) -> 5477.4063 | O25: =SUM(O13:O24) -> 5477.4063 | P25: =SUM(P13:P24) -> 5477.4063
F26: Real Losses | G26: Not broken down
B27: =IF('Reporting Worksheet'!G16>0,IF('Reporting Worksheet'!R16=1,'Reporting Worksheet'!G16/(1+'Reporting Worksheet'!L16),'Reporting Worksheet'!G16-'Reporting Worksheet'!N16),0) -> 233.6473 | F27: ='Reporting Worksheet'!G52 -> 836.09353 | G27: Leakage and Overflows at Utility's Storage Tanks
G28: Not broken down
G29: Leakage on Service Connections
G30: Not broken down

Sheet GradingAssessment
G2: Score
C3: Grade | D3: Weight | E3: adjWeight | F3: adjFactor | G3: Grade*Weight | H3: droppedPts | I3: uniqueRank | K3: Needs grade | L3: Has grade | M3: Grade Problem
B4: Volume from own sources: | C4: =IF('Reporting Worksheet'!E15="n/a",0,'Reporting Worksheet'!E15) -> 7 | D4: ='Reporting Worksheet'!T15 -> 33.177901 | E4: =D4 -> 33.177901 | F4: =IF(D4<>0,E4/10,0) -> 3.3177901 | G4: =C4*F4 -> 23.224531 | H4: =IF(F4=0,0,E4-G4) -> 9.9533703 | I4: {=SUM(1*(H4<$H$4:$H$23))+1+IF(ROW(H4)-ROW($H$4)=0,0,SUM(1*(H4=OFFSET($H$4,0,0,INDEX(ROW(H4)-ROW($H$4)+1,1)-1,1))))} -> 1 | J4: Volume from own sources | K4: =IF(D4<>0,1,0) -> 1 | L4: =IF(C4>0,1,0) -> 1 | M4: =IF(AND(K4=1,L4=0),1,0) -> 0
B5: Volume from own sources master meter error adjustment: | C5: =IF('Reporting Worksheet'!J15="n/a",0,'Reporting Worksheet'!J15) -> 0 | D5: ='Reporting Worksheet'!U15 -> 0 | E5: =D5 -> 0 | F5: =IF(D5<>0,E5/10,0) -> 0 | G5: =C5*F5 -> 0 | H5: =IF(F5=0,0,E5-G5) -> 0 | I5: {=SUM(1*(H5<$H$4:$H$23))+1+IF(ROW(H5)-ROW($H$4)=0,0,SUM(1*(H5=OFFSET($H$4,0,0,INDEX(ROW(H5)-ROW($H$4)+1,1)-1,1))))} -> 16 | J5: Master meter error adjustment | K5: =IF(D5<>0,1,0) -> 0 | L5: =IF(C5>0,1,0) -> 0 | M5: =IF(AND(K5=1,L5=0),1,0) -> 0
B6: Water imported: | C6: =IF('Reporting Worksheet'!E16="n/a",0,'Reporting Worksheet'!E16) -> 9 | D6: ='Reporting Worksheet'!T16 -> 1.4783149 | E6: =D6 -> 1.4783149 | F6: =IF(D6<>0,E6/10,0) -> 0.14783149 | G6: =C6*F6 -> 1.3304834 | H6: =IF(F6=0,0,E6-G6) -> 0.14783149 | I6: {=SUM(1*(H6<$H$4:$H$23))+1+IF(ROW(H6)-ROW($H$4)=0,0,SUM(1*(H6=OFFSET($H$4,0,0,INDEX(ROW(H6)-ROW($H$4)+1,1)-1,1))))} -> 14 | J6: Water imported | K6: =IF(D6<>0,1,0) -> 1 | L6: =IF(C6>0,1,0) -> 1 | M6: =IF(AND(K6=1,L6=0),1,0) -> 0
B7: Water imported meter error adjustment: | C7: =IF('Reporting Worksheet'!J16="n/a",0,'Reporting Worksheet'!J16) -> 0 | D7: ='Reporting Worksheet'!U16 -> 0 | E7: =D7 -> 0 | F7: =IF(D7<>0,E7/10,0) -> 0 | G7: =C7*F7 -> 0 | H7: =IF(F7=0,0,E7-G7) -> 0 | I7: {=SUM(1*(H7<$H$4:$H$23))+1+IF(ROW(H7)-ROW($H$4)=0,0,SUM(1*(H7=OFFSET($H$4,0,0,INDEX(ROW(H7)-ROW($H$4)+1,1)-1,1))))} -> 17 | J7: Master meter error adjustment (Import) | K7: =IF(D7<>0,1,0) -> 0 | L7: =IF(C7>0,1,0) -> 0 | M7: =IF(AND(K7=1,L7=0),1,0) -> 0
B8: Water exported: | C8: =IF('Reporting Worksheet'!E17="n/a",0,'Reporting Worksheet'!E17) -> 2 | D8: ='Reporting Worksheet'!T17 -> 0.34378415 | E8: =D8 -> 0.34378415 | F8: =IF(D8<>0,E8/10,0) -> 0.034378415 | G8: =C8*F8 -> 0.068756831 | H8: =IF(F8=0,0,E8-G8) -> 0.27502732 | I8: {=SUM(1*(H8<$H$4:$H$23))+1+IF(ROW(H8)-ROW($H$4)=0,0,SUM(1*(H8=OFFSET($H$4,0,0,INDEX(ROW(H8)-ROW($H$4)+1,1)-1,1))))} -> 13 | J8: Water exported | K8: =IF(D8<>0,1,0) -> 1 | L8: =IF(C8>0,1,0) -> 1 | M8: =IF(AND(K8=1,L8=0),1,0) -> 0
B9: Water exported meter error adjustment: | C9: =IF('Reporting Worksheet'!J17="n/a",0,'Reporting Worksheet'!J17) -> 0 | D9: ='Reporting Worksheet'!U17 -> 0 | E9: =D9 -> 0 | F9: =IF(D9<>0,E9/10,0) -> 0 | G9: =C9*F9 -> 0 | H9: =IF(F9=0,0,E9-G9) -> 0 | I9: {=SUM(1*(H9<$H$4:$H$23))+1+IF(ROW(H9)-ROW($H$4)=0,0,SUM(1*(H9=OFFSET($H$4,0,0,INDEX(ROW(H9)-ROW($H$4)+1,1)-1,1))))} -> 18 | J9: Master meter error adjustment (Export) | K9: =IF(D9<>0,1,0) -> 0 | L9: =IF(C9>0,1,0) -> 0 | M9: =IF(AND(K9=1,L9=0),1,0) -> 0
B10: Billed metered: | C10: =IF('Reporting Worksheet'!E23="n/a",0,'Reporting Worksheet'!E23) -> 9 | D10: =IF(AND('Reporting Worksheet'!E23="n/a",'Reporting Worksheet'!G23=0),0,8) -> 8 | E10: =D10/$D$26 -> 10.196078 | F10: =IF(D10<>0,E10/10,0) -> 1.0196078 | G10: =C10*F10 -> 9.1764706 | H10: =IF(F10=0,0,E10-G10) -> 1.0196078 | I10: {=SUM(1*(H10<$H$4:$H$23))+1+IF(ROW(H10)-ROW($H$4)=0,0,SUM(1*(H10=OFFSET($H$4,0,0,INDEX(ROW(H10)-ROW($H$4)+1,1)-1,1))))} -> 8 | J10: Billed metered | K10: =IF(D10<>0,1,0) -> 1 | L10: =IF(C10>0,1,0) -> 1 | M10: =IF(AND(K10=1,L10=0),1,0) -> 0
B11: Billed unmetered: | C11: =IF('Reporting Worksheet'!E24="n/a",0,'Reporting Worksheet'!E24) -> 0 | D11: =IF('Reporting Worksheet'!G24=0,0,6) -> 0 | E11: =D11/$D$26 -> 0 | F11: =IF(D11<>0,E11/10,0) -> 0 | G11: =C11*F11 -> 0 | H11: =IF(F11=0,0,E11-G11) -> 0 | I11: {=SUM(1*(H11<$H$4:$H$23))+1+IF(ROW(H11)-ROW($H$4)=0,0,SUM(1*(H11=OFFSET($H$4,0,0,INDEX(ROW(H11)-ROW($H$4)+1,1)-1,1))))} -> 19 | J11: Billed unmetered | K11: =IF(D11<>0,1,0) -> 0 | L11: =IF(C11>0,1,0) -> 0 | M11: =IF(AND(K11=1,L11=0),1,0) -> 0
B12: Unbilled metered: | C12: =IF('Reporting Worksheet'!E25="n/a",0,'Reporting Worksheet'!E25) -> 8 | D12: =IF('Reporting Worksheet'!G25=0,0,6) -> 6 | E12: =D12/$D$26 -> 7.6470588 | F12: =IF(D12<>0,E12/10,0) -> 0.76470588 | G12: =C12*F12 -> 6.1176471 | H12: =IF(F12=0,0,E12-G12) -> 1.5294118 | I12: {=SUM(1*(H12<$H$4:$H$23))+1+IF(ROW(H12)-ROW($H$4)=0,0,SUM(1*(H12=OFFSET($H$4,0,0,INDEX(ROW(H12)-ROW($H$4)+1,1)-1,1))))} -> 6 | J12: Unbilled metered | K12: =IF(D12<>0,1,0) -> 1 | L12: =IF(C12>0,1,0) -> 1 | M12: =IF(AND(K12=1,L12=0),1,0) -> 0
A13: D | B13: Unbilled unmetered: | C13: =IF(OR('Reporting Worksheet'!R26=1,AND('Reporting Worksheet'!R26=2,'Reporting Worksheet'!N26=0)),5,'Reporting Worksheet'!E26) -> 5 | D13: 1 | E13: =D13/$D$26 -> 1.2745098 | F13: =IF(D13<>0,E13/10,0) -> 0.12745098 | G13: =C13*F13 -> 0.6372549 | H13: =IF(F13=0,0,E13-G13) -> 0.6372549 | I13: {=SUM(1*(H13<$H$4:$H$23))+1+IF(ROW(H13)-ROW($H$4)=0,0,SUM(1*(H13=OFFSET($H$4,0,0,INDEX(ROW(H13)-ROW($H$4)+1,1)-1,1))))} -> 11 | J13: Unbilled unmetered | K13: =IF(D13<>0,1,0) -> 1 | L13: =IF(C13>0,1,0) -> 1 | M13: =IF(AND(K13=1,L13=0),1,0) -> 0
A14: D | B14: Unauthorized consumption: | C14: =IF(OR('Reporting Worksheet'!R38=1,AND('Reporting Worksheet'!R38=2,'Reporting Worksheet'!N38=0)),5,'Reporting Worksheet'!E38) -> 5 | D14: 4 | E14: =D14/$D$26 -> 5.0980392 | F14: =IF(D14<>0,E14/10,0) -> 0.50980392 | G14: =C14*F14 -> 2.5490196 | H14: =IF(F14=0,0,E14-G14) -> 2.5490196 | I14: {=SUM(1*(H14<$H$4:$H$23))+1+IF(ROW(H14)-ROW($H$4)=0,0,SUM(1*(H14=OFFSET($H$4,0,0,INDEX(ROW(H14)-ROW($H$4)+1,1)-1,1))))} -> 4 | J14: Unauthorized consumption | K14: =IF(D14<>0,1,0) -> 1 | L14: =IF(C14>0,1,0) -> 1 | M14: =IF(AND(K14=1,L14=0),1,0) -> 0
B15: Customer metering inaccuracies: | C15: =IF('Reporting Worksheet'!E42="n/a",0,'Reporting Worksheet'!E42) -> 6 | D15: =IF(AND('Reporting Worksheet'!E42="n/a",'Reporting Worksheet'!G42=0),0,6) -> 6 | E15: =D15/$D$26 -> 7.6470588 | F15: =IF(D15<>0,E15/10,0) -> 0.76470588 | G15: =C15*F15 -> 4.5882353 | H15: =IF(F15=0,0,E15-G15) -> 3.0588235 | I15: {=SUM(1*(H15<$H$4:$H$23))+1+IF(ROW(H15)-ROW($H$4)=0,0,SUM(1*(H15=OFFSET($H$4,0,0,INDEX(ROW(H15)-ROW($H$4)+1,1)-1,1))))} -> 3 | J15: Customer metering inaccuracies | K15: =IF(D15<>0,1,0) -> 1 | L15: =IF(C15>0,1,0) -> 1 | M15: =IF(AND(K15=1,L15=0),1,0) -> 0
B16: Systematic data handling errors: | C16: =IF('Reporting Worksheet'!G43=0,1,IF('Reporting Worksheet'!R43=1,5,'Reporting Worksheet'!E43)) -> 5 | D16: 4 | E16: =D16/$D$26 -> 5.0980392 | F16: =IF(D16<>0,E16/10,0) -> 0.50980392 | G16: =C16*F16 -> 2.5490196 | H16: =IF(F16=0,0,E16-G16) -> 2.5490196 | I16: {=SUM(1*(H16<$H$4:$H$23))+1+IF(ROW(H16)-ROW($H$4)=0,0,SUM(1*(H16=OFFSET($H$4,0,0,INDEX(ROW(H16)-ROW($H$4)+1,1)-1,1))))} -> 5 | J16: Systematic data handling errors | K16: =IF(D16<>0,1,0) -> 1 | L16: =IF(C16>0,1,0) -> 1 | M16: =IF(AND(K16=1,L16=0),1,0) -> 0
B17: Length of mains: | C17: ='Reporting Worksheet'!E62 -> 9 | D17: 1 | E17: =D17/$D$26 -> 1.2745098 | F17: =IF(D17<>0,E17/10,0) -> 0.12745098 | G17: =C17*F17 -> 1.1470588 | H17: =IF(F17=0,0,E17-G17) -> 0.12745098 | I17: {=SUM(1*(H17<$H$4:$H$23))+1+IF(ROW(H17)-ROW($H$4)=0,0,SUM(1*(H17=OFFSET($H$4,0,0,INDEX(ROW(H17)-ROW($H$4)+1,1)-1,1))))} -> 15 | J17: Length of mains | K17: =IF(D17<>0,1,0) -> 1 | L17: =IF(C17>0,1,0) -> 1 | M17: =IF(AND(K17=1,L17=0),1,0) -> 0
B18: Number of active AND inactive service connections: | C18: ='Reporting Worksheet'!E63 -> 6 | D18: 1 | E18: =D18/$D$26 -> 1.2745098 | F18: =IF(D18<>0,E18/10,0) -> 0.12745098 | G18: =C18*F18 -> 0.76470588 | H18: =IF(F18=0,0,E18-G18) -> 0.50980392 | I18: {=SUM(1*(H18<$H$4:$H$23))+1+IF(ROW(H18)-ROW($H$4)=0,0,SUM(1*(H18=OFFSET($H$4,0,0,INDEX(ROW(H18)-ROW($H$4)+1,1)-1,1))))} -> 12 | J18: Number of active AND inactive service connections | K18: =IF(D18<>0,1,0) -> 1 | L18: =IF(C18>0,1,0) -> 1 | M18: =IF(AND(K18=1,L18=0),1,0) -> 0
B19: Average length of customer service line: | C19: ='Reporting Worksheet'!R67 -> 4 | D19: 1 | E19: =D19/$D$26 -> 1.2745098 | F19: =IF(D19<>0,E19/10,0) -> 0.12745098 | G19: =C19*F19 -> 0.50980392 | H19: =IF(F19=0,0,E19-G19) -> 0.76470588 | I19: {=SUM(1*(H19<$H$4:$H$23))+1+IF(ROW(H19)-ROW($H$4)=0,0,SUM(1*(H19=OFFSET($H$4,0,0,INDEX(ROW(H19)-ROW($H$4)+1,1)-1,1))))} -> 9 | J19: Average length of customer service line | K19: =IF(D19<>0,1,0) -> 1 | L19: =IF(C19>0,1,0) -> 1 | M19: =IF(AND(K19=1,L19=0),1,0) -> 0
B20: Average operating pressure: | C20: ='Reporting Worksheet'!E69 -> 4 | D20: 1 | E20: =D20/$D$26 -> 1.2745098 | F20: =IF(D20<>0,E20/10,0) -> 0.12745098 | G20: =C20*F20 -> 0.50980392 | H20: =IF(F20=0,0,E20-G20) -> 0.76470588 | I20: {=SUM(1*(H20<$H$4:$H$23))+1+IF(ROW(H20)-ROW($H$4)=0,0,SUM(1*(H20=OFFSET($H$4,0,0,INDEX(ROW(H20)-ROW($H$4)+1,1)-1,1))))} -> 10 | J20: Average operating pressure | K20: =IF(D20<>0,1,0) -> 1 | L20: =IF(C20>0,1,0) -> 1 | M20: =IF(AND(K20=1,L20=0),1,0) -> 0
B21: Total annual cost of operating water system: | C21: ='Reporting Worksheet'!E76 -> 10 | D21: 6 | E21: =D21/$D$26 -> 7.6470588 | F21: =IF(D21<>0,E21/10,0) -> 0.76470588 | G21: =C21*F21 -> 7.6470588 | H21: =IF(F21=0,0,E21-G21) -> 0 | I21: {=SUM(1*(H21<$H$4:$H$23))+1+IF(ROW(H21)-ROW($H$4)=0,0,SUM(1*(H21=OFFSET($H$4,0,0,INDEX(ROW(H21)-ROW($H$4)+1,1)-1,1))))} -> 20 | J21: Total annual cost of operating water system | K21: =IF(D21<>0,1,0) -> 1 | L21: =IF(C21>0,1,0) -> 1 | M21: =IF(AND(K21=1,L21=0),1,0) -> 0
B22: Customer retail unit cost (applied to Apparent Losses): | C22: ='Reporting Worksheet'!E77 -> 8 | D22: 6 | E22: =D22/$D$26 -> 7.6470588 | F22: =IF(D22<>0,E22/10,0) -> 0.76470588 | G22: =C22*F22 -> 6.1176471 | H22: =IF(F22=0,0,E22-G22) -> 1.5294118 | I22: {=SUM(1*(H22<$H$4:$H$23))+1+IF(ROW(H22)-ROW($H$4)=0,0,SUM(1*(H22=OFFSET($H$4,0,0,INDEX(ROW(H22)-ROW($H$4)+1,1)-1,1))))} -> 7 | J22: Customer retail unit cost (applied to Apparent Losses) | K22: =IF(D22<>0,1,0) -> 1 | L22: =IF(C22>0,1,0) -> 1 | M22: =IF(AND(K22=1,L22=0),1,0) -> 0
B23: Variable production cost (applied to Real Losses): | C23: =IF('Reporting Worksheet'!E78="n/a",0,'Reporting Worksheet'!E78) -> 4 | D23: 6 | E23: =D23/$D$26 -> 7.6470588 | F23: =IF(D23<>0,E23/10,0) -> 0.76470588 | G23: =C23*F23 -> 3.0588235 | H23: =IF(F23=0,0,E23-G23) -> 4.5882353 | I23: {=SUM(1*(H23<$H$4:$H$23))+1+IF(ROW(H23)-ROW($H$4)=0,0,SUM(1*(H23=OFFSET($H$4,0,0,INDEX(ROW(H23)-ROW($H$4)+1,1)-1,1))))} -> 2 | J23: Variable production cost (applied to Real Losses) | K23: =IF(D23<>0,1,0) -> 1 | L23: =IF(C23>0,1,0) -> 1 | M23: =IF(AND(K23=1,L23=0),1,0) -> 0
D24: =SUM(D4:D23) -> 86 | E24: =SUM(E4:E23) -> 100 | F24: =SUM(F4:F23) -> 10 | G24: =SUM(G4:G23) -> 69.99632 | M24: =SUM(M4:M23) -> 0
D25: =SUM(D10:D23) -> 51
D26: =D25/(100-D27) -> 0.78461538
C27: Total Pts for Water Supplied (top 6 items): | D27: 35 | L27: =IF(SUM('Reporting Worksheet'!R26,'Reporting Worksheet'!R38)=2,2,IF(SUM('Reporting Worksheet'!R26,'Reporting Worksheet'!R38)=3,1,0)) -> 2 | M27: default(s) being used

Sheet Dashboard
B2: AWWA Free Water Audit Software: Dashboard
F4: Water Audit Report for: | G4: =IF(ISBLANK(Instructions!D18),"<< Please enter system details and contact information on the Instructions tab >>",Instructions!D18&IF(ISBLANK(Instructions!D36),""," ("&Instructions!D36&")")) -> Suez Water DE
F5: Reporting Year: | G5: =IF(ISBLANK(Instructions!D26),"",Instructions!D26) -> 2020 | H5: =IF(ISBLANK(Instructions!D26),"",IF(Instructions!E26="Calendar Year","1/"&Instructions!D26&" - "&"12/"&Instructions!D26,IF(OR(ISBLANK(Instructions!D28),ISBLANK(Instructions!D30)),"",MONTH(Instructions!D28)&"/"&YEAR(Instructions!D28)&" - "&MONTH(Instructions!D30)&"/"&YEAR(Instructions!D30)))) -> 1/2020 - 12/2020 | N5: Show me the VOLUME of Non-Revenue Water
F6: Data Validity Score: | G6: =IF(ISBLANK(Instructions!$D$34),"N/A*",IF(GradingAssessment!M24>0,"N/A*",ROUND(GradingAssessment!G24,0))) -> 70 | H6: =IF(G6="N/A*","* Confirm Units and Data Grading are Complete","") | N6: Show me the COST of Non-Revenue Water | S6: 1

Sheet Grading Matrix
C2: AWWA Free Water Audit Software: Grading Matrix | R2: =VLOOKUP(1,GradingAssessment!$I$4:$J$23,2,FALSE)&":" -> Volume from own sources:
C4: The grading assigned to each audit component and the corresponding recommended improvements and actions are highlighted in yellow. Audit accuracy is likely to be improved by prioritizing those items shown in red | R4: =VLOOKUP(2,GradingAssessment!$I$4:$J$23,2,FALSE)&":" -> Variable production cost (applied to Real Losses):
C7: Grading >>> | D7: n/a | E7: 1 | F7: 2 | G7: 3 | H7: 4 | I7: 5 | J7: 6 | K7: 7 | L7: 8 | M7: 9 | N7: 10 | R7: =VLOOKUP(3,GradingAssessment!$I$4:$J$23,2,FALSE)&":" -> Customer metering inaccuracies:
D8: WATER SUPPLIED
C9: Volume from own sources: | D9: Select this grading only if the water utility purchases/imports all of its water resources (i.e. has no sources of its own) | E9: Less than 25% of water production sources are metered, remaining sources are estimated. No regular meter accuracy testing or electronic calibration conducted. | F9: 25% - 50% of treated water production sources are metered; other sources estimated. No regular meter accuracy testing or electronic calibration conducted. | G9: Conditions between 2 and 4 | H9: 50% - 75% of treated water production sources are metered, other sources estimated. Occasional meter accuracy testing or electronic calibration conducted. | I9: Conditions between 4 and 6 | J9: At least 75% of treated water production sources are metered, or at least 90% of the source flow is derived from metered sources. Meter accuracy testing and/or electronic calibration of related instrumentation is conducted annually. Less than 25% of tested meters are found outside of +/- 6% accuracy. | K9: Conditions between 6 and 8 | L9: 100% of treated water production sources are metered, meter accuracy testing and electronic calibration of related instrumentation is conducted annually, less than 10% of meters are found outside of +/- 6% accuracy | M9: Conditions between 8 and 10 | N9: 100% of treated water production sources are metered, meter accuracy testing and electronic calibration of related instrumentation is conducted semi-annually, with less than 10% found outside of +/- 3% accuracy. Procedures are reviewed by a third party knowledgeable in the M36 methodology. | Q9: ='Reporting Worksheet'!E15 -> 7 | R9: =IF(OR(C9=$R$2,C9=$R$4,C9=$R$7),1,0) -> 1
C10: Improvements to attain higher data grading for "Volume from own Sources" component: | E10: to qualify for 2: Organize and launch efforts to collect data for determining volume from own sources | F10: to qualify for 4: Locate all water production sources on maps and in the field, launch meter accuracy testing for existing meters, begin to install meters on unmetered water production sources and replace any obsolete/defective meters. | H10: to qualify for 6: Formalize annual meter accuracy testing for all source meters; specify the frequency of testing. Complete installation of meters on unmetered water production sources and complete replacement of all obsolete/defective meters. | J10: to qualify for 8: Conduct annual meter accuracy testing and calibration of related instrumentation on all meter installations on a regular basis. Complete project to install new, or replace defective existing, meters so that entire production meter population is metered. Repair or replace meters outside of +/- 6% accuracy. | L10: to qualify for 10: Maintain annual meter accuracy testing and calibration of related instrumentation for all meter installations. Repair or replace meters outside of +/- 3% accuracy. Investigate new meter technology; pilot one or more replacements with innovative meters in attempt to further improve meter accuracy. | N10: to maintain 10: Standardize meter accuracy test frequency to semi-annual, or more frequent, for all meters. Repair or replace meters outside of +/- 3% accuracy. Continually investigate/pilot improving metering technology. | Q10: =Q9 -> 7
C11: Volume from own sources master meter and supply error adjustment: | D11: Select n/a only if the water utility fails to have meters on its sources of supply | E11: Inventory information on meters and paper records of measured volumes exist but are incomplete and/or in a very crude condition; data error cannot be determined | F11: No automatic datalogging of production volumes; daily readings are scribed on paper records without any accountability controls. Flows are not balanced across the water distribution system: tank/storage elevation changes are not employed in calculating the "Volume from own sources" component and archived flow data is adjusted only when grossly evident data error occurs. | G11: Conditions between 2 and 4 | H11: Production meter data is logged automatically in electronic format and reviewed at least on a monthly basis with necessary corrections implemented. "Volume from own sources" tabulations include estimate of daily changes in tanks/storage facilities. Meter data is adjusted when gross data errors occur, or occasional meter testing deems this necessary. | I11: Conditions between 4 and 6 | J11: Hourly production meter data logged automatically & reviewed on at least a weekly basis. Data is adjusted to correct gross error when meter/instrumentation equipment malfunction is detected; and/or error is confirmed by meter accuracy testing. Tank/storage facility elevation changes are automatically used in calculating a balanced "Volume from own sources" component, and data gaps in the archived data are corrected on at least a weekly basis. | K11: Conditions between 6 and 8 | L11: Continuous production meter data is logged automatically & reviewed each business day. Data is adjusted to correct gross error from detected meter/instrumentation equipment malfunction and/or results of meter accuracy testing. Tank/storage facility elevation changes are automatically used in "Volume from own sources" tabulations and data gaps in the archived data are corrected on a daily basis. | M11: Conditions between 8 and 10 | N11: Computerized system (SCADA or similar) automatically balances flows from all sources and storages; results are reviewed each business day. Tight accountability controls ensure that all data gaps that occur in the archived flow data are quickly detected and corrected. Regular calibrations between SCADA and sources meters ensures minimal data transfer error. | Q11: ='Reporting Worksheet'!J15 -> 0 | R11: =IF(OR(C11=$R$2,C11=$R$4,C11=$R$7),1,0) -> 0
C12: Improvements to attain higher data grading for "Master meter and supply error adjustment" component: | E12: to qualify for 2: Develop a plan to restructure recordkeeping system to capture all flow data; set a procedure to review flow data on a daily basis to detect input errors. Obtain more reliable information about existing meters by conducting field inspections of meters and related instrumentation, and obtaining manufacturer literature. | F12: to qualify for 4: Install automatic datalogging equipment on production meters. Complete installation of level instrumentation at all tanks/storage facilities and include tank level data in automatic calculation routine in a computerized system. Construct a computerized listing or spreadsheet to archive input volumes, tank/storage volume changes and import/export flows in order to determine the composite "Water Supplied" volume for the distribution system. Set a procedure to review this data on a monthly basis to detect gross anomalies and data gaps. | H12: to qualify for 6: Refine computerized data collection and archive to include hourly production meter data that is reviewed at least on a weekly basis to detect specific data anomalies and gaps. Use daily net storage change to balance flows in calculating "Water Supplied" volume. Necessary corrections to data errors are implemented on a weekly basis. | J12: to qualify for 8: Ensure that all flow data is collected and archived on at least an hourly basis. All data is reviewed and detected errors corrected each business day. Tank/storage levels variations are employed in calculating balanced "Water Supplied" component. Adjust production meter data for gross error and inaccuracy confirmed by testing. | L12: to qualify for 10: Link all production and tank/storage facility elevation change data to a Supervisory Control & Data Acquisition (SCADA) System, or similar computerized monitoring/control system, and establish automatic flow balancing algorithm and regularly calibrate between SCADA and source meters. Data is reviewed and corrected each business day. | N12: to maintain 10: Monitor meter innovations for development of more accurate and less expensive flowmeters. Continue to replace or repair meters as they perform outside of desired accuracy limits. Stay abreast of new and more accurate water level instruments to better record tank/storage levels and archive the variations in storage volume. Keep current with SCADA and data management systems to ensure that archived data is well-managed and error free. | Q12: =Q11 -> 0
C13: Water Imported: | D13: Select n/a if the water utility's supply is exclusively from its own water resources (no bulk purchased/ imported water) | E13: Less than 25% of imported water sources are metered, remaining sources are estimated. No regular meter accuracy testing. | F13: 25% - 50% of imported water sources are metered; other sources estimated. No regular meter accuracy testing. | G13: Conditions between 2 and 4 | H13: 50% - 75% of imported water sources are metered, other sources estimated. Occasional meter accuracy testing conducted. | I13: Conditions between 4 and 6 | J13: At least 75% of imported water sources are metered, meter accuracy testing and/or electronic calibration of related instrumentation is conducted annually for all meter installations. Less than 25% of tested meters are found outside of +/- 6% accuracy. | K13: Conditions between 6 and 8 | L13: 100% of imported water sources are metered, meter accuracy testing and electronic calibration of related instrumentation is conducted annually, less than 10% of meters are found outside of +/- 6% accuracy | M13: Conditions between 8 and 10 | N13: 100% of imported water sources are metered, meter accuracy testing and electronic calibration of related instrumentation is conducted semi-annually for all meter installations, with less than 10% of accuracy tests found outside of +/- 3% accuracy. | Q13: ='Reporting Worksheet'!E16 -> 9 | R13: =IF(OR(C13=$R$2,C13=$R$4,C13=$R$7),1,0) -> 0
C14: Improvements to attain higher data grading for "Water Imported Volume" component: (Note: usually the water supplier selling the water - "the Exporter" - to the utility being audited is responsible to maintain the metering installation measuring the imported volume. The utility should coordinate carefully with the Exporter to ensure that adequate meter upkeep takes place and an accurate measure of the Water Imported volume is quantified.) | E14: to qualify for 2: Review bulk water purchase agreements with partner suppliers; confirm requirements for use and maintenance of accurate metering. Identify needs for new or replacement meters with goal to meter all imported water sources. | F14: To qualify for 4: Locate all imported water sources on maps and in the field, launch meter accuracy testing for existing meters, begin to install meters on unmetered imported water interconnections and replace obsolete/defective meters. | H14: to qualify for 6: Formalize annual meter accuracy testing for all imported water meters, planning for both regular meter accuracy testing and calibration of the related instrumentation. Continue installation of meters on unmetered imported water interconnections and replacement of obsolete/defective meters. | J14: to qualify for 8: Complete project to install new, or replace defective, meters on all imported water interconnections. Maintain annual meter accuracy testing for all imported water meters and conduct calibration of related instrumentation at least annually. Repair or replace meters outside of +/- 6% accuracy. | L14: to qualify for 10: Conduct meter accuracy testing for all meters on a semi-annual basis, along with calibration of all related instrumentation. Repair or replace meters outside of +/- 3% accuracy. Investigate new meter technology; pilot one or more replacements with innovative meters in attempt to improve meter accuracy. | N14: to maintain 10: Standardize meter accuracy test frequency to semi-annual, or more frequent, for all meters. Continue to conduct calibration of related instrumentation on a semi-annual basis. Repair or replace meters outside of +/- 3% accuracy. Continually investigate/pilot improving metering technology. | Q14: =Q13 -> 9
C15: Water imported master meter and supply error adjustment: | D15: Select n/a if the Imported water supply is unmetered, with Imported water quantities estimated on the billing invoices sent by the Exporter to the purchasing Utility. | E15: Inventory information on imported meters and paper records of measured volumes exist but are incomplete and/or in a very crude condition; data error cannot be determined Written agreement(s) with water Exporter(s) are missing or written in vague language concerning meter management and testing. | F15: No automatic datalogging of imported supply volumes; daily readings are scribed on paper records without any accountability controls to confirm data accuracy and the absence of errors and data gaps in recorded volumes. Written agreement requires meter accuracy testing but is vague on the details of how and who conducts the testing. | G15: Conditions between 2 and 4 | H15: Imported supply metered flow data is logged automatically in electronic format and reviewed at least on a monthly basis by the Exporter with necessary corrections implemented. Meter data is adjusted by the Exporter when gross data errors are detected. A coherent data trail exists for this process to protect both the selling and the purchasing Utility. Written agreement exists and clearly states requirements and roles for meter accuracy testing and data management. | I15: Conditions between 4 and 6 | J15: Hourly Imported supply metered data is logged automatically & reviewed on at least a weekly basis by the Exporter. Data is adjusted to correct gross error when meter/instrumentation equipment malfunction is detected; and to correct for error confirmed by meter accuracy testing. Any data gaps in the archived data are detected and corrected during the weekly review. A coherent data trail exists for this process to protect both the selling and the purchasing Utility. | K15: Conditions between 6 and 8 | L15: Continuous Imported supply metered flow data is logged automatically & reviewed each business day by the Exporter. Data is adjusted to correct gross error from detected meter/instrumentation equipment malfunction and/or results of meter accuracy testing. Any data errors/gaps are detected and corrected on a daily basis. A data trail exists for the process to protect both the selling and the purchasing Utility. | M15: Conditions between 8 and 10 | N15: Computerized system (SCADA or similar) automatically records data which is reviewed each business day by the Exporter. Tight accountability controls ensure that all error/data gaps that occur in the archived flow data are quickly detected and corrected. A reliable data trail exists and contract provisions for meter testing and data management are reviewed by the selling and purchasing Utility at least once every five years. | Q15: ='Reporting Worksheet'!J16 -> 0 | R15: =IF(OR(C15=$R$2,C15=$R$4,C15=$R$7),1,0) -> 0
C16: Improvements to attain higher data grading for "Water imported master meter and supply error adjustment" component: | E16: to qualify for 2: Develop a plan to restructure recordkeeping system to capture all flow data; set a procedure to review flow data on a daily basis to detect input errors. Obtain more reliable information about existing meters by conducting field inspections of meters and related instrumentation, and obtaining manufacturer literature. Review the written agreement between the selling and purchasing Utility. | F16: to qualify for 4: Install automatic datalogging equipment on Imported supply meters. Set a procedure to review this data on a monthly basis to detect gross anomalies and data gaps. Launch discussions with the Exporters to jointly review terms of the written agreements regarding meter accuracy testing and data management; revise the terms as necessary. | H16: to qualify for 6: Refine computerized data collection and archive to include hourly Imported supply metered flow data that is reviewed at least on a weekly basis to detect specific data anomalies and gaps. Make necessary corrections to errors/data errors on a weekly basis. | J16: to qualify for 8: Ensure that all Imported supply metered flow data is collected and archived on at least an hourly basis. All data is reviewed and errors/data gaps are corrected each business day. | L16: to qualify for 10: Conduct accountability checks to confirm that all Imported supply metered data is reviewed and corrected each business day by the Exporter. Results of all meter accuracy tests and data corrections should be available for sharing between the Exporter and the purchasing Utility. Establish a schedule for a regular review and updating of the contractual language in the written agreement between the selling and the purchasing Utility; at least every five years. | N16: to maintain 10: Monitor meter innovations for development of more accurate and less expensive flowmeters; work with the Exporter to help identify meter replacement needs. Keep communication lines with Exporters open and maintain productive relations. Keep the written agreement current with clear and explicit language that meets the ongoing needs of all parties. | Q16: =Q15 -> 0
C17: Water Exported: | D17: Select n/a if the water utility sells no bulk water to neighboring water utilities (no exported water sales) | E17: Less than 25% of exported water sources are metered, remaining sources are estimated. No regular meter accuracy testing. | F17: 25% - 50% of exported water sources are metered; other sources estimated. No regular meter accuracy testing. | G17: Conditions between 2 and 4 | H17: 50% - 75% of exported water sources are metered, other sources estimated. Occasional meter accuracy testing conducted. | I17: Conditions between 4 and 6 | J17: At least 75% of exported water sources are metered, meter accuracy testing and/or electronic calibration conducted annually. Less than 25% of tested meters are found outside of +/- 6% accuracy. | K17: Conditions between 6 and 8 | L17: 100% of exported water sources are metered, meter accuracy testing and electronic calibration of related instrumentation is conducted annually, less than 10% of meters are found outside of +/- 6% accuracy | M17: Conditions between 8 and 10 | N17: 100% of exported water sources are metered, meter accuracy testing and electronic calibration of related instrumentation is conducted semi-annually for all meter installations, with less than 10% of accuracy tests found outside of +/- 3% accuracy. | Q17: ='Reporting Worksheet'!E17 -> 2 | R17: =IF(OR(C17=$R$2,C17=$R$4,C17=$R$7),1,0) -> 0
C18: Improvements to attain higher data grading for "Water Exported Volume" component: (Note: usually, if the water utility being audited sells (Exports) water to a neighboring purchasing Utility, it is the responsibility of the utility exporting the water to maintain the metering installation measuring the Exported volume. The utility exporting the water should ensure that adequate meter upkeep takes place and an accurate measure of the Water Exported volume is quantified.) | E18: to qualify for 2: Review bulk water sales agreements with purchasing utilities; confirm requirements for use & upkeep of accurate metering. Identify needs to install new, or replace defective meters as needed. | F18: To qualify for 4: Locate all exported water sources on maps and in field, launch meter accuracy testing for existing meters, begin to install meters on unmetered exported water interconnections and replace obsolete/defective meters | H18: to qualify for 6: Formalize annual meter accuracy testing for all exported water meters. Continue installation of meters on unmetered exported water interconnections and replacement of obsolete/defective meters. | J18: to qualify for 8: Complete project to install new, or replace defective, meters on all exported water interconnections. Maintain annual meter accuracy testing for all exported water meters. Repair or replace meters outside of +/- 6% accuracy. | L18: to qualify for 10: Maintain annual meter accuracy testing for all meters. Repair or replace meters outside of +/- 3% accuracy. Investigate new meter technology; pilot one or more replacements with innovative meters in attempt to improve meter accuracy. | N18: to maintain 10: Standardize meter accuracy test frequency to semi-annual, or more frequent, for all meters. Repair or replace meters outside of +/- 3% accuracy. Continually investigate/pilot improving metering technology. | Q18: =Q17 -> 2
C19: Water exported master meter and supply error adjustment: | D19: Select n/a only if the water utility fails to have meters on its exported supply interconnections. | E19: Inventory information on exported meters and paper records of measured volumes exist but are incomplete and/or in a very crude condition; data error cannot be determined Written agreement(s) with the utility purchasing the water are missing or written in vague language concerning meter management and testing. | F19: No automatic datalogging of exported supply volumes; daily readings are scribed on paper records without any accountability controls to confirm data accuracy and the absence of errors and data gaps in recorded volumes. Written agreement requires meter accuracy testing but is vague on the details of how and who conducts the testing. | G19: Conditions between 2 and 4 | H19: Exported metered flow data is logged automatically in electronic format and reviewed at least on a monthly basis, with necessary corrections implemented. Meter data is adjusted by the utility selling (exporting) the water when gross data errors are detected. A coherent data trail exists for this process to protect both the utility exporting the water and the purchasing Utility. Written agreement exists and clearly states requirements and roles for meter accuracy testing and data management. | I19: Conditions between 4 and 6 | J19: Hourly exported supply metered data is logged automatically & reviewed on at least a weekly basis by the utility selling the water. Data is adjusted to correct gross error when meter/instrumentation equipment malfunction is detected; and to correct for error found by meter accuracy testing. Any data gaps in the archived data are detected and corrected during the weekly review. A coherent data trail exists for this process to protect both the selling (exporting) utility and the purchasing Utility. | K19: Conditions between 6 and 8 | L19: Continuous exported supply metered flow data is logged automatically & reviewed each business day by the utility selling (exporting) the water. Data is adjusted to correct gross error from detected meter/instrumentation equipment malfunction and any error confirmed by meter accuracy testing. Any data errors/gaps are detected and corrected on a daily basis. A data trail exists for the process to protect both the selling (exporting) Utility and the purchasing Utility. | M19: Conditions between 8 and 10 | N19: Computerized system (SCADA or similar) automatically records data which is reviewed each business day by the utility selling (exporting) the water. Tight accountability controls ensure that all error/data gaps that occur in the archived flow data are quickly detected and corrected. A reliable data trail exists and contract provisions for meter testing and data management are reviewed by the selling Utility and purchasing Utility at least once every five years. | Q19: ='Reporting Worksheet'!J17 -> 0 | R19: =IF(OR(C19=$R$2,C19=$R$4,C19=$R$7),1,0) -> 0
C20: Improvements to attain higher data grading for "Water exported master meter and supply error adjustment" component: | E20: to qualify for 2: Develop a plan to restructure recordkeeping system to capture all flow data; set a procedure to review flow data on a daily basis to detect input errors. Obtain more reliable information about existing meters by conducting field inspections of meters and related instrumentation, and obtaining manufacturer literature. Review the written agreement between the utility selling (exporting) the water and the purchasing Utility. | F20: to qualify for 4: Install automatic datalogging equipment on exported supply meters. Set a procedure to review this data on a monthly basis to detect gross anomalies and data gaps. Launch discussions with the purchasing utilities to jointly review terms of the written agreements regarding meter accuracy testing and data management; revise the terms as necessary. | H20: to qualify for 6: Refine computerized data collection and archive to include hourly exported supply metered flow data that is reviewed at least on a weekly basis to detect specific data anomalies and gaps. Make necessary corrections to errors/data errors on a weekly basis. | J20: to qualify for 8: Ensure that all exported metered flow data is collected and archived on at least an hourly basis. All data is reviewed and errors/data gaps are corrected each business day. | L20: to qualify for 10: Conduct accountability checks to confirm that all exported metered flow data is reviewed and corrected each business day by the utility selling the water. Results of all meter accuracy tests and data corrections should be available for sharing between the utility and the purchasing Utility. Establish a schedule for a regular review and updating of the contractual language in the written agreements with the purchasing utilities; at least every five years. | N20: to maintain 10: Monitor meter innovations for development of more accurate and less expensive flowmeters; work with the purchasing utilities to help identify meter replacement needs. Keep communication lines with the purchasing utilities open and maintain productive relations. Keep the written agreement current with clear and explicit language that meets the ongoing needs of all parties. | Q20: =Q19 -> 0
C21: AUTHORIZED CONSUMPTION
C22: Billed metered: | D22: n/a (not applicable). Select n/a only if the entire customer population is not metered and is billed for water service on a flat or fixed rate basis. In such a case the volume entered must be zero. | E22: Less than 50% of customers with volume-based billings from meter readings; flat or fixed rate billing exists for the majority of the customer population | F22: At least 50% of customers with volume-based billing from meter reads; flat rate billing for others. Manual meter reading is conducted, with less than 50% meter read success rate, remainding accounts' consumption is estimated. Limited meter records, no regular meter testing or replacement. Billing data maintained on paper records, with no auditing. | G22: Conditions between 2 and 4 | H22: At least 75% of customers with volume-based, billing from meter reads; flat or fixed rate billing for remaining accounts. Manual meter reading is conducted with at least 50% meter read success rate; consumption for accounts with failed reads is estimated. Purchase records verify age of customer meters; only very limited meter accuracy testing is conducted. Customer meters are replaced only upon complete failure. Computerized billing records exist, but only sporadic internal auditing conducted. | I22: Conditions between 4 and 6 | J22: At least 90% of customers with volume-based billing from meter reads; consumption for remaining accounts is estimated. Manual customer meter reading gives at least 80% customer meter reading success rate; consumption for accounts with failed reads is estimated. Good customer meter records eixst, but only limited meter accuracy testing is conducted. Regular replacement is conducted for the oldest meters. Computerized billing records exist with annual auditing of summary statistics conducting by utility personnel. | K22: Conditions between 6 and 8 | L22: At least 97% of customers exist with volume-based billing from meter reads. At least 90% customer meter reading success rate; or at least 80% read success rate with planning and budgeting for trials of Automatic Meter Reading (AMR) or Advanced Metering Infrastructure (AMI) in one or more pilot areas. Good customer meter records. Regular meter accuracy testing guides replacement of statistically significant number of meters each year. Routine auditing of computerized billing records for global and detailed statistics occurs annually by utility personnel, and is verified by third party at least once every five years. | M22: Conditions between 8 and 10 | N22: At least 99% of customers exist with volume-based billing from meter reads. At least 95% customer meter reading success rate; or minimum 80% meter reading success rate, with Automatic Meter Reading (AMR) or Advanced Metering Infrastructure (AMI) trials underway. Statistically significant customer meter testing and replacement program in place on a continuous basis. Computerized billing with routine, detailed auditing, including field investigation of representative sample of accounts undertaken annually by utility personnel. Audit is conducted by third party auditors at least once every three years. | Q22: ='Reporting Worksheet'!E23 -> 9 | R22: =IF(OR(C22=$R$2,C22=$R$4,C22=$R$7),1,0) -> 0
C23: Improvements to attain higher data grading for "Billed Metered Consumption" component: | D23: If n/a is selected because the customer meter population is unmetered, consider establishing a new policy to meter the customer population and employ water rates based upon metered volumes. | E23: to qualify for 2: Conduct investigations or trials of customer meters to select appropriate meter models. Budget funding for meter installations. Investigate volume based water rate structures. | F23: to qualify for 4: Purchase and install meters on unmetered accounts. Implement policies to improve meter reading success. Catalog meter information during meter read visits to identify age/model of existing meters. Test a minimal number of meters for accuracy. Install computerized billing system. | H23: to qualify for 6: Purchase and install meters on unmetered accounts. Eliminate flat fee billing and establish appropriate water rate structure based upon measured consumption. Continue to achieve verifiable success in removing manual meter reading barriers. Expand meter accuracy testing. Launch regular meter replacement program. Launch a program of annual auditing of global billing statistics by utility personnel. | J23: to qualify for 8: Purchase and install meters on unmetered accounts. If customer meter reading success rate is less than 97%, assess cost-effectiveness of Automatic Meter Reading (AMR) or Advanced Metering Infrastructure (AMI) system for portion or entire system; or otherwise achieve ongoing improvements in manual meter reading success rate to 97% or higher. Refine meter accuracy testing program. Set meter replacement goals based upon accuracy test results. Implement annual auditing of detailed billing records by utility personnel and implement third party auditing at least once every five years. | L23: to qualify for 10: Purchase and install meters on unmetered accounts. Launch Automatic Meter Reading (AMR) or Advanced Metering Infrastructure (AMI) system trials if manual meter reading success rate of at least 99% is not achieved within a five-year program. Continue meter accuracy testing program. Conduct planning and budgeting for large scale meter replacement based upon meter life cycle analysis using cumulative flow target. Continue annual detailed billing data auditing by utility personnel and conduct third party auditing at least once every three years. | N23: to maintain 10: Continue annual internal billing data auditing, and third party auditing at least every three years. Continue customer meter accuracy testing to ensure that accurate customer meter readings are obtained and entered as the basis for volume based billing. Stay abreast of improvements in Automatic Meter Reading (AMR) and Advanced Metering Infrastructure (AMI) and information management. Plan and budget for justified upgrades in metering, meter reading and billing data management to maintain very high accuracy in customer metering and billing. | Q23: =Q22 -> 9
C24: Billed unmetered: | D24: Select n/a if it is the policy of the water utility to meter all customer connections and it has been confirmed by detailed auditing that all customers do indeed have a water meter; i.e. no intentionally unmetered accounts exist | E24: Water utility policy does not require customer metering; flat or fixed fee billing is employed. No data is collected on customer consumption. The only estimates of customer population consumption available are derived from data estimation methods using average fixture count multiplied by number of connections, or similar approach. | F24: Water utility policy does not require customer metering; flat or fixed fee billing is employed. Some metered accounts exist in parts of the system (pilot areas or District Metered Areas) with consumption read periodically or recorded on portable dataloggers over one, three, or seven day periods. Data from these sample meters are used to infer consumption for the total customer population. Site specific estimation methods are used for unusual buildings/water uses. | G24: Conditions between 2 and 4 | H24: Water utility policy does require metering and volume based billing in general. However, a liberal amount of exemptions and a lack of clearly written and communicated procedures result in up to 20% of billed accounts believed to be unmetered by exemption; or the water utility is in transition to becoming fully metered, and a large number of customers remain unmetered. A rough estimate of the annual consumption for all unmetered accounts is included in the annual water audit, with no inspection of individual unmetered accounts. | I24: Conditions between 4 and 6 | J24: Water utility policy does require metering and volume based billing but established exemptions exist for a portion of accounts such as municipal buildings. As many as 15% of billed accounts are unmetered due to this exemption or meter installation difficulties. Only a group estimate of annual consumption for all unmetered accounts is included in the annual water audit, with no inspection of individual unmetered accounts. | K24: Conditions between 6 and 8 | L24: Water utility policy does require metering and volume based billing for all customer accounts. However, less than 5% of billed accounts remain unmetered because meter installation is hindered by unusual circumstances. The goal is to minimize the number of unmetered accounts. Reliable estimates of consumption are obtained for these unmetered accounts via site specific estimation methods. | M24: Conditions between 8 and 10 | N24: Water utility policy does require metering and volume based billing for all customer accounts. Less than 2% of billed accounts are unmetered and exist because meter installation is hindered by unusual circumstances. The goal exists to minimize the number of unmetered accounts to the extent that is economical. Reliable estimates of consumption are obtained at these accounts via site specific estimation methods. | Q24: ='Reporting Worksheet'!E24 -> n/a | R24: =IF(OR(C24=$R$2,C24=$R$4,C24=$R$7),1,0) -> 0
C25: Improvements to attain higher data grading for "Billed Unmetered Consumption" component: | E25: to qualify for 2: Conduct research and evaluate cost/benefit of a new water utility policy to require metering of the customer population; thereby greatly reducing or eliminating unmetered accounts. Conduct pilot metering project by installing water meters in small sample of customer accounts and periodically reading the meters or datalogging the water consumption over one, three, or seven day periods. | F25: to qualify for 4: Implement a new water utility policy requiring customer metering. Launch or expand pilot metering study to include several different meter types, which will provide data for economic assessment of full scale metering options. Assess sites with access difficulties to devise means to obtain water consumption volumes. Begin customer meter installation. | H25: to qualify for 6: Refine policy and procedures to improve customer metering participation for all but solidly exempt accounts. Assign staff resources to review billing records to identify errant unmetered properties. Specify metering needs and funding requirements to install sufficient meters to significant reduce the number of unmetered accounts | J25: to qualify for 8: Push to install customer meters on a full scale basis. Refine metering policy and procedures to ensure that all accounts, including municipal properties, are designated for meters. Plan special efforts to address "hard-to-access" accounts. Implement procedures to obtain a reliable consumption estimate for the remaining few unmetered accounts awaiting meter installation. | L25: to qualify for 10: Continue customer meter installation throughout the service area, with a goal to minimize unmetered accounts. Sustain the effort to investigate accounts with access difficulties, and devise means to install water meters or otherwise measure water consumption. | N25: to maintain 10: Continue to refine estimation methods for unmetered consumption and explore means to establish metering, for as many billed remaining unmetered accounts as is economically feasible. | Q25: =Q24 -> n/a
C26: Unbilled metered: | D26: select n/a if all billing-exempt consumption is unmetered. | E26: Billing practices exempt certain accounts, such as municipal buildings, but written policies do not exist; and a reliable count of unbilled metered accounts is unavailable. Meter upkeep and meter reading on these accounts is rare and not considered a priority. Due to poor recordkeeping and lack of auditing, water consumption for all such accounts is purely guesstimated. | F26: Billing practices exempt certain accounts, such as municipal buildings, but only scattered, dated written directives exist to justify this practice. A reliable count of unbilled metered accounts is unavailable. Sporadic meter replacement and meter reading occurs on an as-needed basis. The total annual water consumption for all unbilled, metered accounts is estimated based upon approximating the number of accounts and assigning consumption from actively billed accounts of same meter size. | G26: Conditions between 2 and 4 | H26: Dated written procedures permit billing exemption for specific accounts, such as municipal properties, but are unclear regarding certain other types of accounts. Meter reading is given low priority and is sporadic. Consumption is quantified from meter readings where available. The total number of unbilled, unmetered accounts must be estimated along with consumption volumes. | I26: Conditions between 4 and 6 | J26: Written policies regarding billing exemptions exist but adherence in practice is questionable. Metering and meter reading for municipal buildings is reliable but sporadic for other unbilled metered accounts. Periodic auditing of such accounts is conducted. Water consumption is quantified directly from meter readings where available, but the majority of the consumption is estimated. | K26: Conditions between 6 and 8 | L26: Written policy identifies the types of accounts granted a billing exemption. Customer meter management and meter reading are considered secondary priorities, but meter reading is conducted at least annually to obtain consumption volumes for the annual water audit. High level auditing of billing records ensures that a reliable census of such accounts exists. | M26: Conditions between 8 and 10 | N26: Clearly written policy identifies the types of accounts given a billing exemption, with emphasis on keeping such accounts to a minimum. Customer meter management and meter reading for these accounts is given proper priority and is reliably conducted. Regular auditing confirms this. Total water consumption for these accounts is taken from reliable readings from accurate meters. | Q26: ='Reporting Worksheet'!E25 -> 8 | R26: =IF(OR(C26=$R$2,C26=$R$4,C26=$R$7),1,0) -> 0
C27: Improvements to attain higher data grading for "Unbilled Metered Consumption" component: | E27: to qualify for 2: Reassess the water utility's policy allowing certain accounts to be granted a billing exemption. Draft an outline of a new written policy for billing exemptions, with clear justification as to why any accounts should be exempt from billing, and with the intention to keep the number of such accounts to a minimum. | F27: to qualify for 4: Review historic written directives and policy documents allowing certain accounts to be billing-exempt. Draft an outline of a written policy for billing exemptions, identify criteria that grants an exemption, with a goal of keeping this number of accounts to a minimum. Consider increasing the priority of reading meters on unbilled accounts at least annually. | H27: to qualify for 6: Draft a new written policy regarding billing exemptions based upon consensus criteria allowing this occurrence. Assign resources to audit meter records and billing records to obtain census of unbilled metered accounts. Gradually include a greater number of these metered accounts to the routes for regular meter reading. | J27: to qualify for 8: Communicate billing exemption policy throughout the organization and implement procedures that ensure proper account management. Conduct inspections of accounts confirmed in unbilled metered status and verify that accurate meters exist and are scheduled for routine meter readings. Gradually increase the number of unbilled metered accounts that are included in regular meter reading routes. | L27: to qualify for 10: Ensure that meter management (meter accuracy testing, meter replacement) and meter reading activities for unbilled accounts are accorded the same priority as billed accounts. Establish ongoing annual auditing process to ensure that water consumption is reliably collected and provided to the annual water audit process. | N27: to maintain 10: Reassess the utility's philosophy in allowing any water uses to go "unbilled". It is possible to meter and bill all accounts, even if the fee charged for water consumption is discounted or waived. Metering and billing all accounts ensures that water consumption is tracked and water waste from plumbing leaks is detected and minimized. | Q27: =Q26 -> 8
C28: Unbilled unmetered: | E28: Extent of unbilled, unmetered consumption is unknown due to unclear policies and poor recordkeeping. Total consumption is quantified based upon a purely subjective estimate. | F28: Clear extent of unbilled, unmetered consumption is unknown, but a number of events are randomly documented each year, confirming existence of such consumption, but without sufficient documentation to quantify an accurate estimate of the annual volume consumed. | G28: Conditions between 2 and 4 | H28: Extent of unbilled, unmetered consumption is partially known, and procedures exist to document certain events such as miscellaneous fire hydrant uses. Formulae is used to quantify the consumption from such events (time running multiplied by typical flowrate, multiplied by number of events). | I28: Default value of 1.25% of system input volume is employed | J28: Coherent policies exist for some forms of unbilled, unmetered consumption but others await closer evaluation. Reasonable recordkeeping for the managed uses exists and allows for annual volumes to be quantified by inference, but unsupervised uses are guesstimated. | K28: Conditions between 6 and 8 | L28: Clear policies and good recordkeeping exist for some uses (ex: water used in periodic testing of unmetered fire connections), but other uses (ex: miscellaneous uses of fire hydrants) have limited oversight. Total consumption is a mix of well quantified use such as from formulae (time running multiplied by typical flow, multiplied by number of events) or temporary meters, and relatively subjective estimates of less regulated use. | M28: Conditions between 8 and 10 | N28: Clear policies exist to identify permitted use of water in unbilled, unmetered fashion, with the intention of minimizing this type of consumption. Good records document each occurrence and consumption is quantified via formulae (time running multiplied by typical flow, multiplied by number of events) or use of temporary meters. | Q28: ='Reporting Worksheet'!E26 -> 0 | R28: =IF(OR(C28=$R$2,C28=$R$4,C28=$R$7),1,0) -> 0
C29: Improvements to attain higher data grading for "Unbilled Unmetered Consumption" component: | E29: to qualify for 5: Utilize the accepted default value of 1.25% of the volume of water supplied as an expedient means to gain a reasonable quantification of this use. to qualify for 2: Establish a policy regarding what water uses should be allowed to remain as unbilled and unmetered. Consider tracking a small sample of one such use (ex: fire hydrant flushings). | F29: to qualify for 5: Utilize accepted default value of 1.25% of the volume of water supplied as an expedient means to gain a reasonable quantification of this use. to qualify for 4: Evaluate the documentation of events that have been observed. Meet with user groups (ex: for fire hydrants - fire departments, contractors to ascertain their need and/or volume requirements for water from fire hydrants). | H29: to qualify for 5: Utilize accepted default value of 1.25% of the volume of water supplied as an expedient means to gain a reasonable quantification of all such use. This is particularly appropriate for water utilities who are in the early stages of the water auditing process, and should focus on other components since the volume of unbilled, umetered consumption is usually a relatively small quatity component, and other larger-quantity components should take priority. | I29: to qualify for 6 or greater: Finalize policy and begin to conduct field checks to better establish and quantify such usage. Proceed if top-down audit exists and/or a great volume of such use is suspected. | J29: to qualify for 8: Assess water utility policy and procedures for various unmetered usages. For example, ensure that a policy exists and permits are issued for use of fire hydrants by persons outside of the utility. Create written procedures for use and documentation of fire hydrants by water utility personnel. Use same approach for other types of unbilled, unmetered water usage. | L29: to qualify for 10: Refine written procedures to ensure that all uses of unbilled, unmetered water are overseen by a structured permitting process managed by water utility personnel. Reassess policy to determine if some of these uses have value in being converted to billed and/or metered status. | N29: to maintain 10: Continue to refine policy and procedures with intention of reducing the number of allowable uses of water in unbilled and unmetered fashion. Any uses that can feasibly become billed and metered should be converted eventually. | Q29: =Q28 -> 0
C30: APPARENT LOSSES
C31: Unauthorized consumption: | E31: Extent of unauthorized consumption is unknown due to unclear policies and poor recordkeeping. Total unauthorized consumption is guesstimated. | F31: Unauthorized consumption is a known occurrence, but its extent is a mystery. There are no requirements to document observed events, but periodic field reports capture some of these occurrences. Total unauthorized consumption is approximated from this limited data. | G31: conditions between 2 and 4 | H31: Procedures exist to document some unauthorized consumption such as observed unauthorized fire hydrant openings. Use formulae to quantify this consumption (time running multiplied typical flowrate, multiplied by number of events). | I31: Default value of 0.25% of volume of water supplied is employed | J31: Coherent policies exist for some forms of unauthorized consumption (more than simply fire hydrant misuse) but others await closer evaluation. Reasonable surveillance and recordkeeping exist for occurrences that fall under the policy. Volumes quantified by inference from these records. | K31: Conditions between 6 and 8 | L31: Clear policies and good auditable recordkeeping exist for certain events (ex: tampering with water meters, illegal bypasses of customer meters); but other occurrences have limited oversight. Total consumption is a combination of volumes from formulae (time x typical flow) and subjective estimates of unconfirmed consumption. | M31: Conditions between 8 and 10 | N31: Clear policies exist to identify all known unauthorized uses of water. Staff and procedures exist to provide enforcement of policies and detect violations. Each occurrence is recorded and quantified via formulae (estimated time running multiplied by typical flow) or similar methods. All records and calculations should exist in a form that can be audited by a third party. | Q31: ='Reporting Worksheet'!E38 -> 0 | R31: =IF(OR(C31=$R$2,C31=$R$4,C31=$R$7),1,0) -> 0
C32: Improvements to attain higher data grading for "Unauthorized Consumption" component: | E32: to qualify for 5: Use accepted default of 0.25% of volume of water supplied. to qualify for 2: Review utility policy regarding what water uses are considered unauthorized, and consider tracking a small sample of one such occurrence (ex: unauthorized fire hydrant openings) | F32: to qualify for 5: Use accepted default of 0.25% of system input volume to qualify for 4: Review utility policy regarding what water uses are considered unauthorized, and consider tracking a small sample of one such occurrence (ex: unauthorized fire hydrant openings) | H32: to qualify for 5: Utilize accepted default value of 0.25% of volume of water supplied as an expedient means to gain a reasonable quantification of all such use. This is particularly appropriate for water utilities who are in the early stages of the water auditing process. | I32: to qualify for 6 or greater: Finalize policy updates to clearly identify the types of water consumption that are authorized from those usages that fall outside of this policy and are, therefore, unauthorized. Begin to conduct regular field checks. Proceed if the top-down audit already exists and/or a great volume of such use is suspected. | J32: to quality for 8: Assess water utility policies to ensure that all known occurrences of unauthorized consumption are outlawed, and that appropriate penalties are prescribed. Create written procedures for detection and documentation of various occurrences of unauthorized consumption as they are uncovered. | L32: to qualify for 10: Refine written procedures and assign staff to seek out likely occurrences of unauthorized consumption. Explore new locking devices, monitors and other technologies designed to detect and thwart unauthorized consumption. | N32: to maintain 10: Continue to refine policy and procedures to eliminate any loopholes that allow or tacitly encourage unauthorized consumption. Continue to be vigilant in detection, documentation and enforcement efforts. | Q32: =Q31 -> 0
C33: Customer metering inaccuracies: | D33: select n/a only if the entire customer population is unmetered. In such a case the volume entered must be zero. | E33: Customer meters exist, but with unorganized paper records on meters; no meter accuracy testing or meter replacement program for any size of retail meter. Metering workflow is driven chaotically with no proactive management. Loss volume due to aggregate meter inaccuracy is guesstimated. | F33: Poor recordkeeping and meter oversight is recognized by water utility management who has allotted staff and funding resources to organize improved recordkeeping and start meter accuracy testing. Existing paper records gathered and organized to provide cursory disposition of meter population. Customer meters are tested for accuracy only upon customer request. | G33: Conditions between 2 and 4 | H33: Reliable recordkeeping exists; meter information is improving as meters are replaced. Meter accuracy testing is conducted annually for a small number of meters (more than just customer requests, but less than 1% of inventory). A limited number of the oldest meters are replaced each year. Inaccuracy volume is largely an estimate, but refined based upon limited testing data. | I33: Conditions between 4 and 6 | J33: A reliable electronic recordkeeping system for meters exists. The meter population includes a mix of new high performing meters and dated meters with suspect accuracy. Routine, but limited, meter accuracy testing and meter replacement occur. Inaccuracy volume is quantified using a mix of reliable and less certain data. | K33: Conditions between 6 and 8 | L33: Ongoing meter replacement and accuracy testing result in highly accurate customer meter population. Testing is conducted on samples of meters of varying age and accumulated volume of throughput to determine optimum replacement time for various types of meters. | M33: Ongoing meter replacement and accuracy testing result in highly accurate customer meter population. Statistically significant number of meters are tested in audit year. This testing is conducted on samples of meters of varying age and accumulated volume of throughput to determine optimum replacement time for these meters. | N33: Good records of all active customer meters exist and include as a minimum: meter number, account number/location, type, size and manufacturer. Ongoing meter replacement occurs according to a targeted and justified basis. Regular meter accuracy testing gives a reliable measure of composite inaccuracy volume for the customer meter population. New metering technology is embraced to keep overall accuracy improving. Procedures are reviewed by a third party knowledgeable in the M36 methodology. | Q33: ='Reporting Worksheet'!E42 -> 6 | R33: =IF(OR(C33=$R$2,C33=$R$4,C33=$R$7),1,0) -> 1
C34: Improvements to attain higher data grading for "Customer meter inaccuracy volume" component: | D34: If n/a is selected because the customer meter population is unmetered, consider establishing a new policy to meter the customer population and employ water rates based upon metered volumes. | E34: to qualify for 2: Gather available meter purchase records. Conduct testing on a small number of meters believed to be the most inaccurate. Review staffing needs of the metering group and budget for necessary resources to better organize meter management. | F34: to qualify for 4: Implement a reliable record keeping system for customer meter histories, preferably using electronic methods typically linked to, or part of, the Customer Billing System or Customer Information System. Expand meter accuracy testing to a larger group of meters. | H34: to qualify for 6: Standardize the procedures for meter recordkeeping within an electronic information system. Accelerate meter accuracy testing and meter replacements guided by testing results. | J34: to qualify for 8: Expand annual meter accuracy testing to evaluate a statistically significant number of meter makes/models. Expand meter replacement program to replace statistically significant number of poor performing meters each year. | L34: to qualify for 9: Continue efforts to manage meter population with reliable recordkeeping. Test a statistically significant number of meters each year and analyze test results in an ongoing manner to serve as a basis for a target meter replacement strategy based upon accumulated volume throughput. | M34: to qualify for 10: Continue efforts to manage meter population with reliable recordkeeping, meter testing and replacement. Evaluate new meter types and install one or more types in 5-10 customer accounts each year in order to pilot improving metering technology. | N34: to maintain 10: Increase the number of meters tested and replaced as justified by meter accuracy test data. Continually monitor development of new metering technology and Advanced Metering Infrastructure (AMI) to grasp opportunities for greater accuracy in metering of water flow and management of customer consumption data. | Q34: =Q33 -> 6
C35: Systematic Data Handling Errors: | D35: Note: all water utilities incur some amount of this error. Even in water utilities with unmetered customer populations and fixed rate billing, errors occur in annual billing tabulations. Enter a positive value for the volume and select a grading. | E35: Policies and procedures for activation of new customer water billing accounts are vague and lack accountability. Billing data is maintained on paper records which are not well organized. No auditing is conducted to confirm billing data handling efficiency. An unknown number of customers escape routine billing due to lack of billing process oversight. | F35: Policy and procedures for activation of new customer accounts and oversight of billing records exist but need refinement. Billing data is maintained on paper records or insufficiently capable electronic database. Only periodic unstructured auditing work is conducted to confirm billing data handling efficiency. The volume of unbilled water due to billing lapses is a guess. | G35: Conditions between 2 and 4 | H35: Policy and procedures for new account activation and oversight of billing operations exist but needs refinement. Computerized billing system exists, but is dated or lacks needed functionality. Periodic, limited internal audits conducted and confirm with approximate accuracy the consumption volumes lost to billing lapses. | I35: Conditions between 4 and 6 | J35: Policy and procedures for new account activation and oversight of billing operations is adequate and reviewed periodically. Computerized billing system is in use with basic reporting available. Any effect of billing adjustments on measured consumption volumes is well understood. Internal checks of billing data error conducted annually. Reasonably accurate quantification of consumption volume lost to billing lapses is obtained. | K35: Conditions between 6 and 8 | L35: New account activation and billing operations policy and procedures are reviewed at least biannually. Computerized billing system includes an array of reports to confirm billing data and system functionality. Checks are conducted routinely to flag and explain zero consumption accounts. Annual internal checks conducted with third party audit conducted at least once every five years. Accountability checks flag billing lapses. Consumption lost to billing lapses is well quantified and reducing year-by-year. | M35: Conditions between 8 and 10 | N35: Sound written policy and procedures exist for new account activation and oversight of customer billing operations. Robust computerized billing system gives high functionality and reporting capabilities which are utilized, analyzed and the results reported each billing cycle. Assessment of policy and data handling errors are conducted internally and audited by third party at least once every three years, ensuring consumption lost to billing lapses is minimized and detected as it occurs. | Q35: ='Reporting Worksheet'!E43 -> 0 | R35: =IF(OR(C35=$R$2,C35=$R$4,C35=$R$7),1,0) -> 0
C36: Improvements to attain higher data grading for "Systematic Data Handling Error volume" component: | E36: to qualify for 2: Draft written policy and procedures for activating new water billing accounts and oversight of billing operations. Investigate and budget for computerized customer billing system. Conduct initial audit of billing records by flow-charting the basic business processes of the customer account/billing function. | F36: to qualify for 4: Finalize written policy and procedures for activation of new billing acocunts and overall billing operations management. Implement a computerized customer billing system. Conduct initial audit of billing records as part of this process. | H36: to qualify for 6: Refine new account activation and billing operations procedures and ensure consistency with the utility policy regarding billing, and minimize opportunity for missed billings. Upgrade or replace customer billing system for needed functionality - ensure that billing adjustments don't corrupt the value of consumption volumes. Procedurize internal annual audit process. | J36: to qualify for 8: Formalize regular review of new account activation process and general billing practices. Enhance reporting capability of computerized billing system. Formalize regular auditing process to reveal scope of data handling error. Plan for periodic third party audit to occur at least once every five years. | L36: to qualify for 10: Close policy/procedure loopholes that allow some customer accounts to go unbilled, or data handling errors to exist. Ensure that billing system reports are utilized, analyzed and reported every billing cycle. Ensure that internal and third party audits are conducted at least once every three years. | N36: to maintain 10: Stay abreast of customer information management developments and innovations. Monitor developments of Advanced Metering Infrastructure (AMI) and integrate technology to ensure that customer endpoint information is well-monitored and errors/lapses are at an economic minimum. | Q36: =Q35 -> 0
C37: SYSTEM DATA
C38: Length of mains: | E38: Poorly assembled and maintained paper as-built records of existing water main installations makes accurate determination of system pipe length impossible. Length of mains is guesstimated. | F38: Paper records in poor or uncertain condition (no annual tracking of installations & abandonments). Poor procedures to ensure that new water mains installed by developers are accurately documented. | G38: Conditions between 2 and 4 | H38: Sound written policy and procedures exist for documenting new water main installations, but gaps in management result in a uncertain degree of error in tabulation of mains length. | I38: Conditions between 4 and 6 | J38: Sound written policy and procedures exist for permitting and commissioning new water mains. Highly accurate paper records with regular field validation; or electronic records and asset management system in good condition. Includes system backup. | K38: Conditions between 6 and 8 | L38: Sound written policy and procedures exist for permitting and commissioning new water mains. Electronic recordkeeping such as a Geographical Information System (GIS) and asset management system are used to store and manage data. | M38: Conditions between 8 and 10 | N38: Sound written policy exists for managing water mains extensions and replacements. Geographic Information System (GIS) data and asset management database agree and random field validation proves truth of databases. Records of annual field validation should be available for review. | Q38: ='Reporting Worksheet'!E62 -> 9 | R38: =IF(OR(C38=$R$2,C38=$R$4,C38=$R$7),1,0) -> 0
C39: Improvements to attain higher data grading for "Length of Water Mains" component: | E39: to qualify for 2: Assign personnel to inventory current as-built records and compare with customer billing system records and highway plans in order to verify poorly documented pipelines. Assemble policy documents regarding permitting and documentation of water main installations by the utility and building developers; identify gaps in procedures that result in poor documentation of new water main installations. | F39: to qualify for 4: Complete inventory of paper records of water main installations for several years prior to audit year. Review policy and procedures for commissioning and documenting new water main installation. | H39: to qualify for 6: Finalize updates/improvements to written policy and procedures for permitting/commissioning new main installations. Confirm inventory of records for five years prior to audit year; correct any errors or omissions. | J39: to qualify for 8: Launch random field checks of limited number of locations. Convert to electronic database such as a Geographic Information System (GIS) with backup as justified. Develop written policy and procedures. | L39: to qualify for 10: Link Geographic Information System (GIS) and asset management databases, conduct field verification of data. Record field verification information at least annually. | N39: to maintain 10: Continue with standardization and random field validation to improve the completeness and accuracy of the system. | Q39: =Q38 -> 9
C40: Number of active AND inactive service connections: | E40: Vague permitting (of new service connections) policy and poor paper recordkeeping of customer connections/billings result in suspect determination of the number of service connections, which may be 10-15% in error from actual count. | F40: General permitting policy exists but paper records, procedural gaps, and weak oversight result in questionable total for number of connections, which may vary 5-10% of actual count. | G40: Conditions between 2 and 4 | H40: Written account activation policy and procedures exist, but with some gaps in performance and oversight. Computerized information management system is being brought online to replace dated paper recordkeeping system. Reasonably accurate tracking of service connection installations & abandonments; but count can be up to 5% in error from actual total. | I40: Conditions between 4 and 6 | J40: Written new account activation and overall billing policies and procedures are adequate and reviewed periodically. Computerized information management system is in use with annual installations & abandonments totaled. Very limited field verifications and audits. Error in count of number of service connections is believed to be no more than 3%. | K40: Conditions between 6 and 8 | L40: Policies and procedures for new account activation and overall billing operations are written, well-structured and reviewed at least biannually. Well-managed computerized information management system exists and routine, periodic field checks and internal system audits are conducted. Counts of connections are no more than 2% in error. | M40: Conditions between 8 and 10 | N40: Sound written policy and well managed and audited procedures ensure reliable management of service connection population. Computerized information management system, Customer Billing System, and Geographic Information System (GIS) information agree; field validation proves truth of databases. Count of connections recorded as being in error is less than 1% of the entire population. | Q40: ='Reporting Worksheet'!E63 -> 6 | R40: =IF(OR(C40=$R$2,C40=$R$4,C40=$R$7),1,0) -> 0
C41: Improvements to attain higher data grading for "Number of Active and Inactive Service Connections" component: | D41: Note: The number of Service Connections does not include fire hydrant leads/lines connecting the hydrant to the water main | E41: to qualify for 2: Draft new policy and procedures for new account activation and overall billing operations. Research and collect paper records of installations & abandonments for several years prior to audit year. | F41: to qualify for 4: Refine policy and procedures for new account activation and overall billing operations. Research computerized recordkeeping system (Customer Information System or Customer Billing System) to improve documentation format for service connections. | H41: to qualify for 6: Refine procedures to ensure consistency with new account activation and overall billing policy to establish new service connections or decommission existing connections. Improve process to include all totals for at least five years prior to audit year. | J41: to qualify for 8: Formalize regular review of new account activation and overall billing operations policies and procedures. Launch random field checks of limited number of locations. Develop reports and auditing mechanisms for computerized information management system. | L41: to qualify for 10: Close any procedural loopholes that allow installations to go undocumented. Link computerized information management system with Geographic Information System (GIS) and formalize field inspection and information system auditing processes. Documentation of new or decommissioned service connections encounters several levels of checks and balances. | N41: to maintain 10: Continue with standardization and random field validation to improve knowledge of system. | Q41: =Q40 -> 6
C42: Average length of customer service line: | D42: Note: if customer water meters are located outside of the customer building next to the curb stop or boundary separating utility/customer responsibility, then the auditor should answer "Yes" to the question on the Reporting Worksheet asking about this. If the answer is Yes, the grading description listed under the Grading of 10(a) will be followed, with a value of zero automatically entered at a Grading of 10. See the Service Connection Diagram worksheet for a visual presentation of this distance. | E42: Gradings 1-9 apply if customer properties are unmetered, if customer meters exist and are located inside the customer building premises, or if the water utility owns and is responsible for the entire service connection piping from the water main to the customer building. In any of these cases the average distance between the curb stop or boundary separating utility/customer responsibility for service connection piping, and the typical first point of use (ex: faucet) or the customer meter must be quantified. Gradings of 1-9 are used to grade the validity of the means to quantify this value. (See the "Service Connection Diagram" worksheet) | N42: Either of two conditions can be met for a grading of 10: a) Customer water meters exist outside of customer buildings next to the curb stop or boundary separating utility/customer responsibility for service connection piping. If so, answer "Yes" to the question on the Reporting Working asking about this condition. A value of zero and a Grading of 10 are automatically entered in the Reporting Worksheet . b). Meters exist inside customer buildings, or properties are unmetered. In either case, answer "No" to the Reporting Worksheet question on meter location, and enter a distance determined by the auditor. For a Grading of 10 this value must be a very reliable number from a Geographic Information System (GIS) and confirmed by a statistically valid number of field checks. | Q42: =Q43 -> 4 | R42: =IF(OR(C42=$R$2,C42=$R$4,C42=$R$7),1,0) -> 0
E43: Vague policy exists to define the delineation of water utility ownership and customer ownership of the service connection piping. Curb stops are perceived as the breakpoint but these have not been well-maintained or documented. Most are buried or obscured. Their location varies widely from site-to-site, and estimating this distance is arbitrary due to the unknown location of many curb stops. | F43: Policy requires that the curb stop serves as the delineation point between water utility ownership and customer ownership of the service connection piping. The piping from the water main to the curb stop is the property of the water utility; and the piping from the curb stop to the customer building is owned by the customer. Curb stop locations are not well documented and the average distance is based upon a limited number of locations measured in the field. | G43: Conditions between 2 and 4 | H43: Good policy requires that the curb stop serves as the delineation point between water utility ownership and customer ownership of the service connection piping. Curb stops are generally installed as needed and are reasonably documented. Their location varies widely from site-to-site, and an estimate of this distance is hindered by the availability of paper records of limited accuracy. | I43: Conditions between 4 and 6 | J43: Clear written policy exists to define utility/customer responsibility for service connection piping. Accurate, well-maintained paper or basic electronic recordkeeping system exists. Periodic field checks confirm piping lengths for a sample of customer properties. | K43: Conditions between 6 and 8 | L43: Clearly worded policy standardizes the location of curb stops and meters, which are inspected upon installation. Accurate and well maintained electronic records exist with periodic field checks to confirm locations of service lines, curb stops and customer meter pits. An accurate number of customer properties from the customer billing system allows for reliable averaging of this length. | M43: Conditions between 8 and 10 | Q43: ='Reporting Worksheet'!R67 -> 4 | R43: =IF(OR(C43=$R$2,C43=$R$4,C43=$R$7),1,0) -> 0
C44: Improvements to attain higher data grading for "Average Length of Customer Service Line" component: | E44: to qualify for 2: Research and collect paper records of service line installations. Inspect several sites in the field using pipe locators to locate curb stops. Obtain the length of this small sample of connections in this manner. | F44: to qualify for 4: Formalize and communicate policy delineating utility/customer responsibilities for service connection piping. Assess accuracy of paper records by field inspection of a small sample of service connections using pipe locators as needed. Research the potential migration to a computerized information management system to store service connection data. | H44: to qualify for 6: Establish coherent procedures to ensure that policy for curb stop, meter installation and documentation is followed. Gain consensus within the water utility for the establishment of a computerized information management system. | J44: to qualify for 8: Implement an electronic means of recordkeeping, typically via a customer information system, customer billing system, or Geographic Information System (GIS). Standardize the process to conduct field checks of a limited number of locations. | L44: to qualify for 10: Link customer information management system and Geographic Information System (GIS), standardize process for field verification of data. | N44: to maintain 10: Continue with standardization and random field validation to improve knowledge of service connection configurations and customer meter locations. | Q44: =Q43 -> 4
C45: Average operating pressure: | E45: Available records are poorly assembled and maintained paper records of supply pump characteristics and water distribution system operating conditions. Average pressure is guesstimated based upon this information and ground elevations from crude topographical maps. Widely varying distribution system pressures due to undulating terrain, high system head loss and weak/erratic pressure controls further compromise the validity of the average pressure calculation. | F45: Limited telemetry monitoring of scattered pumping station and water storage tank sites provides some static pressure data, which is recorded in handwritten logbooks. Pressure data is gathered at individual sites only when low pressure complaints arise. Average pressure is determined by averaging relatively crude data, and is affected by significant variation in ground elevations, system head loss and gaps in pressure controls in the distribution system. | G45: Conditions between 2 and 4 | H45: Effective pressure controls separate different pressure zones; moderate pressure variation across the system, occasional open boundary valves are discovered that breech pressure zones. Basic telemetry monitoring of the distribution system logs pressure data electronically. Pressure data gathered by gauges or dataloggers at fire hydrants or buildings when low pressure complaints arise, and during fire flow tests and system flushing. Reliable topographical data exists. Average pressure is calculated using this mix of data. | I45: Conditions between 4 and 6 | J45: Reliable pressure controls separate distinct pressure zones; only very occasional open boundary valves are encountered that breech pressure zones. Well-covered telemetry monitoring of the distribution system (not just pumping at source treatment plants or wells) logs extensive pressure data electronically. Pressure gathered by gauges/dataloggers at fire hydrants and buildings when low pressure complaints arise, and during fire flow tests and system flushing. Average pressure is determined by using this mix of reliable data. | K45: Conditions between 6 and 8 | L45: Well-managed, discrete pressure zones exist with generally predictable pressure fluctuations. A current full-scale SCADA System or similar realtime monitoring system exists to monitor the water distribution system and collect data, including real time pressure readings at representative sites across the system. The average system pressure is determined from reliable monitoring system data. | M45: Conditions between 8 and 10 | N45: Well-managed pressure districts/zones, SCADA System and hydraulic model exist to give very precise pressure data across the water distribution system. Average system pressure is reliably calculated from extensive, reliable, and cross-checked data. Calculations are reported on an annual basis as a minimum. | Q45: ='Reporting Worksheet'!E69 -> 4 | R45: =IF(OR(C45=$R$2,C45=$R$4,C45=$R$7),1,0) -> 0
C46: Improvements to attain higher data grading for "Average Operating Pressure" component: | E46: to qualify for 2: Employ pressure gauging and/or datalogging equipment to obtain pressure measurements from fire hydrants. Locate accurate topographical maps of service area in order to confirm ground elevations. Research pump data sheets to find pump pressure/flow characteristics | F46: to qualify for 4: Formalize a procedure to use pressure gauging/datalogging equipment to gather pressure data during various system events such as low pressure complaints, or operational testing. Gather pump pressure and flow data at different flow regimes. Identify faulty pressure controls (pressure reducing valves, altitude valves, partially open boundary valves) and plan to properly configure pressure zones. Make all pressure data from these efforts available to generate system-wide average pressure. | H46: to qualify for 6: Expand the use of pressure gauging/datalogging equipment to gather scattered pressure data at a representative set of sites, based upon pressure zones or areas. Utilize pump pressure and flow data to determine supply head entering each pressure zone or district. Correct any faulty pressure controls (pressure reducing valves, altitude valves, partially open boundary valves) to ensure properly configured pressure zones. Use expanded pressure dataset from these activities to generate system-wide average pressure. | J46: to qualify for 8: Install a Supervisory Control and Data Acquisition (SCADA) System, or similar realtime monitoring system, to monitor system parameters and control operations. Set regular calibration schedule for instrumentation to insure data accuracy. Obtain accurate topographical data and utilize pressure data gathered from field surveys to provide extensive, reliable data for pressure averaging. | L46: to qualify for 10: Annually, obtain a system-wide average pressure value from the hydraulic model of the distribution system that has been calibrated via field measurements in the water distribution system and confirmed in comparisons with SCADA System data. | N46: to maintain 10: Continue to refine the hydraulic model of the distribution system and consider linking it with SCADA System for real-time pressure data calibration, and averaging. | Q46: =Q45 -> 4
C47: COST DATA
C48: Total annual cost of operating water system: | E48: Incomplete paper records and lack of financial accounting documentation on many operating functions makes calculation of water system operating costs a pure guesstimate | F48: Reasonably maintained, but incomplete, paper or electronic accounting provides data to estimate the major portion of water system operating costs. | G48: Conditions between 2 and 4 | H48: Electronic, industry-standard cost accounting system in place. However, gaps in data are known to exist, periodic internal reviews are conducted but not a structured financial audit. | I48: Conditions between 4 and 6 | J48: Reliable electronic, industry-standard cost accounting system in place, with all pertinent water system operating costs tracked. Data audited periodically by utility personnel, but not a Certified Public Accountant (CPA). | K48: Conditions between 6 and 8 | L48: Reliable electronic, industry-standard cost accounting system in place, with all pertinent water system operating costs tracked. Data audited at least annually by utility personnel, and at least once every three years by third-party CPA. | M48: Conditions between 8 and 10 | N48: Reliable electronic, industry-standard cost accounting system in place, with all pertinent water system operating costs tracked. Data audited annually by utility personnel and annually also by third-party CPA. | Q48: ='Reporting Worksheet'!E76 -> 10 | R48: =IF(OR(C48=$R$2,C48=$R$4,C48=$R$7),1,0) -> 0
C49: Improvements to attain higher data grading for "Total Annual Cost of Operating the Water System" component: | E49: to qualify for 2: Gather available records, institute new financial accounting procedures to regularly collect and audit basic cost data of most important operations functions. | F49: to qualify for 4: Implement an electronic cost accounting system, structured according to accounting standards for water utilities | H49: to qualify for 6: Establish process for periodic internal audit of water system operating costs; identify cost data gaps and institute procedures for tracking these outstanding costs. | J49: to qualify for 8: Standardize the process to conduct routine financial audit on an annual basis. Arrange for CPA audit of financial records at least once every three years. | L49: to qualify for 10: Standardize the process to conduct a third-party financial audit by a CPA on an annual basis. | N49: to maintain 10: Maintain program, stay abreast of expenses subject to erratic cost changes and long-term cost trend, and budget/track costs proactively | Q49: =Q48 -> 10
C50: Customer retail unit cost (applied to Apparent Losses): | D50: Customer population unmetered, and/or only a fixed fee is charged for consumption. | E50: Antiquated, cumbersome water rate structure is used, with periodic historic amendments that were poorly documented and implemented; resulting in classes of customers being billed inconsistent charges. The actual composite billing rate likely differs significantly from the published water rate structure, but a lack of auditing leaves the degree of error indeterminate. | F50: Dated, cumbersome water rate structure, not always employed consistently in actual billing operations. The actual composite billing rate is known to differ from the published water rate structure, and a reasonably accurate estimate of the degree of error is determined, allowing a composite billing rate to be quantified. | G50: Conditions between 2 and 4 | H50: Straight-forward water rate structure in use, but not updated in several years. Billing operations reliably employ the rate structure. The composite billing rate is derived from a single customer class such as residential customer accounts, neglecting the effect of different rates from varying customer classes. | I50: Conditions between 4 and 6 | J50: Clearly written, up-to-date water rate structure is in force and is applied reliably in billing operations. Composite customer rate is determined using a weighted average residential rate using volumes of water in each rate block. | K50: Conditions between 6 and 8 | L50: Effective water rate structure is in force and is applied reliably in billing operations. Composite customer rate is determined using a weighted average composite consumption rate, which includes residential, commercial, industrial, institutional (CII), and any other distinct customer classes within the water rate structure. | M50: Conditions between 8 and 10 | N50: Current, effective water rate structure is in force and applied reliably in billing operations. The rate structure and calculations of composite rate - which includes residential, commercial, industrial, institutional (CII), and other distinct customer classes - are reviewed by a third party knowledgeable in the M36 methodology at least once every five years. | Q50: ='Reporting Worksheet'!E77 -> 8 | R50: =IF(OR(C50=$R$2,C50=$R$4,C50=$R$7),1,0) -> 0
C51: Improvements to attain higher data grading for "Customer Retail Unit Cost" component: | E51: to qualify for 2: Formalize the process to implement water rates, including a secure documentation procedure. Create a current, formal water rate document and gain approval from all stakeholders. | F51: to qualify for 4: Review the water rate structure and update/formalize as needed. Assess billing operations to ensure that actual billing operations incorporate the established water rate structure. | H51: to qualify for 6: Evaluate volume of water used in each usage block by residential users. Multiply volumes by full rate structure. | I51: Launch effort to fully meter the customer population and charge rates based upon water volumes | J51: to qualify for 8: Evaluate volume of water used in each usage block by all classifications of users. Multiply volumes by full rate structure. | L51: to qualify for 10: Conduct a periodic third-party audit of water used in each usage block by all classifications of users. Multiply volumes by full rate structure. | N51: to maintain 10: Keep water rate structure current in addressing the water utility's revenue needs. Update the calculation of the customer unit rate as new rate components, customer classes, or other components are modified. | Q51: =Q50 -> 8
C52: Variable production cost (applied to Real Losses): | D52: Note: if the water utility purchases/imports its entire water supply, then enter the unit purchase cost of the bulk water supply in the Reporting Worksheet with a grading of 10 | E52: Incomplete paper records and lack of documentation on primary operating functions (electric power and treatment costs most importantly) makes calculation of variable production costs a pure guesstimate | F52: Reasonably maintained, but incomplete, paper or electronic accounting provides data to roughly estimate the basic operations costs (pumping power costs and treatment costs) and calculate a unit variable production cost. | G52: Conditions between 2 and 4 | H52: Electronic, industry-standard cost accounting system in place. Electric power and treatment costs are reliably tracked and allow accurate weighted calculation of unit variable production costs based on these two inputs and water imported purchase costs (if applicable). All costs are audited internally on a periodic basis. | I52: Conditions between 4 and 6 | J52: Reliable electronic, industry-standard cost accounting system in place, with all pertinent water system operating costs tracked. Pertinent additional costs beyond power, treatment and water imported purchase costs (if applicable) such as liability, residuals management, wear and tear on equipment, impending expansion of supply, are included in the unit variable production cost, as applicable. The data is audited at least annually by utility personnel. | K52: Conditions between 6 and 8 | L52: Reliable electronic, industry-standard cost accounting system in place, with all pertinent primary and secondary variable production and water imported purchase (if applicable) costs tracked. The data is audited at least annually by utility personnel, and at least once every three years by a third-party knowledgeable in the M36 methodology. | M52: Conditions between 8 and 10 | N52: Either of two conditions can be met to obtain a grading of 10: 1) Third party CPA audit of all pertinent primary and secondary variable production and water imported purchase (if applicable) costs on an annual basis. or: 2) Water supply is entirely purchased as bulk water imported, and the unit purchase cost - including all applicable marginal supply costs - serves as the variable production cost. If all applicable marginal supply costs are not included in this figure, a grade of 10 should not be selected. | Q52: ='Reporting Worksheet'!E78 -> 4 | R52: =IF(OR(C52=$R$2,C52=$R$4,C52=$R$7),1,0) -> 1
C53: Improvements to attain higher data grading for "Variable Production Cost" component: | E53: to qualify for 2: Gather available records, institute new procedures to regularly collect and audit basic cost data and most important operations functions. | F53: to qualify for 4: Implement an electronic cost accounting system, structured according to accounting standards for water utilities | H53: to qualify for 6: Formalize process for regular internal audits of production costs. Assess whether additional costs (liability, residuals management, equipment wear, impending infrastructure expansion) should be included to calculate a more representative variable production cost. | J53: to qualify for 8: Formalize the accounting process to include direct cost components (power, treatment) as well as indirect cost components (liability, residuals management, etc.) Arrange to conduct audits by a knowledgable third-party at least once every three years. | L53: to qualify for 10: Standardize the process to conduct a third-party financial audit by a CPA on an annual basis. | N53: to maintain 10: Maintain program, stay abreast of expenses subject to erratic cost changes and budget/track costs proactively | Q53: =Q52 -> 4

Sheet Service Connection Diagram
B2: AWWA Free Water Audit Software: Customer Service Line Diagrams
E4: =IF(ISBLANK(Instructions!H34),"","All Units in "&Instructions!H34)

Sheet Definitions
B2: AWWA Free Water Audit Software: Definitions
C4: Item Name | D4: Description
C6: Apparent Losses | D6: = unauthorized consumption + customer metering inaccuracies + systematic data handling errors Apparent Losses include all types of inaccuracies associated with customer metering (worn meters as well as improperly sized meters or wrong type of meter for the water usage profile) as well as systematic data handling errors (meter reading, billing, archiving and reporting), plus unauthorized consumption (theft or illegal use). NOTE: Over-estimation of Apparent Losses results in under-estimation of Real Losses. Under-estimation of Apparent Losses results in over-estimation of Real Losses.
C8: AUTHORIZED CONSUMPTION | D8: = billed water exported + billed metered + billed unmetered + unbilled metered + unbilled unmetered consumption The volume of metered and/or unmetered water taken by registered customers, the water utility's own uses, and uses of others who are implicitly or explicitly authorized to do so by the water utility; for residential, commercial, industrial and public-minded purposes. Typical retail customers' consumption is tabulated usually from established customer accounts as billed metered consumption, or - for unmetered customers - billed unmetered consumption. These types of consumption, along with billed water exported, provide revenue potential for the water utility. Be certain to tabulate the water exported volume as a separate component and do not "double-count" it by including in the billed metered consumption component as well as the water exported component. Unbilled authorized consumption occurs typically in non-account uses, including water for fire fighting and training, flushing of water mains and sewers, street cleaning, watering of municipal gardens, public fountains, or similar public-minded uses. Occasionally these uses may be metered and billed (or charged a flat fee), but usually they are unmetered and unbilled. In the latter case, the water auditor may use a default value to estimate this quantity, or implement procedures for the reliable quantification of these uses. This starts with documenting usage events as they occur and estimating the amount of water used in each event. (See Unbilled unmetered consumption)
C10: Average length of customer service line | D10: This is the average length of customer service line, Lp, that is owned and maintained by the customer; from the point of ownership transfer to the customer water meter, or building line (if unmetered). The quantity is one of the data inputs for the calculation of Unavoidable Annual Real Losses (UARL), which serves as the denominator of the performance indicator: Infrastructure Leakage Index (ILI). The value of Lp is multiplied by the number of customer service connections to obtain a total length of customer owned piping in the system. The purpose of this parameter is to account for the unmetered service line infrastructure that is the responsibility of the customer for arranging repairs of leaks that occur on their lines. In many cases leak repairs arranged by customers take longer to be executed than leak repairs arranged by the water utility on utility-maintained piping. Leaks run longer - and lose more water - on customer-owned service piping, than utility owned piping. If the customer water meter exists near the ownership transfer point (usually the curb stop located between the water main and the customer premises) this distance is zero because the meter and transfer point are the same. This is the often encountered configuration of customer water meters located in an underground meter box or "pit" outside of the customer's building. The Free Water Audit Software asks a "Yes/No" question about the meter at this location. If the auditor selects "Yes" then this distance is set to zero and the data grading score for this component is set to 10. If water meters are typically located inside the customer premise/building, or properties are unmetered, it is up to the water auditor to estimate a system-wide average Lp length based upon the various customer land parcel sizes and building locations in the service area. Lp will be a shorter length in areas of high density housing, and a longer length in areas of low density housing and varied commercial and industrial buildings. General parcel demographics should be employed to obtain a composite average Lp length for the entire system. Refer to the "Service Connection Diagram" worksheet for a depiction of the service line/metering configurations that typically exist in water utilities. This worksheet gives guidance on the determination of the Average Length, Lp, for each configuration.
C12: Average operating pressure | D12: This is the average pressure in the distribution system that is the subject of the water audit. Many water utilities have a calibrated hydraulic model of their water distribution system. For these utilities, the hydraulic model can be utilized to obtain a very accurate quantity of average pressure. In the absence of a hydraulic model, the average pressure may be approximated by obtaining readings of static water pressure from a representative sample of fire hydrants or other system access points evenly located across the system. A weighted average of the pressure can be assembled; but be sure to take into account the elevation of the fire hydrants, which typically exist several feet higher than the level of buried water pipelines. If the water utility is compiling the water audit for the first time, the average pressure can be approximated, but with a low data grading. In subsequent years of auditing, effort should be made to improve the accuracy of the average pressure quantity. This will then qualify the value for a higher data grading.
C14: Billed Authorized Consumption | D14: All consumption that is billed and authorized by the utility. This may include both metered and unmetered consumption. See "Authorized Consumption" for more information.
C16: Billed metered consumption | D16: All metered consumption which is billed to retail customers, including all groups of customers such as domestic, commercial, industrial or institutional. It does NOT include water supplied to neighboring utilities (water exported) which is metered and billed. Be sure to subtract any consumption for exported water sales that may be included in these billing roles. Water supplied as exports to neighboring water utilities should be included only in the Water Exported component. The metered consumption data can be taken directly from billing records for the water audit period. The accuracy of yearly metered consumption data can be refined by including an adjustment to account for customer meter reading lag time since not all customer meters are read on the same day of the meter reading period. However additional analysis is necessary to determine the lag time adjustment value, which may or may not be significant.
C18: Billed unmetered consumption | D18: All billed consumption which is calculated based on estimates or norms from water usage sites that have been determined by utility policy to be left unmetered. This is typically a very small component in systems that maintain a policy to meter their customer population. However, this quantity can be the key consumption component in utilities that have not adopted a universal metering policy. This component should NOT include any water that is supplied to neighboring utilities (water exported) which is unmetered but billed. Water supplied as exports to neighboring water utilities should be included only in the Water Exported component.
C20: Customer metering inaccuracies | D20: Apparent water losses caused by the collective under-registration of customer water meters. Many customer water meters gradually wear as large cumulative volumes of water are passed through them over time. This causes the meters to under-register the flow of water. This occurrence is common with smaller residential meters of sizes 5/8-inch and 3/4 inch after they have registered very large cumulative volumes of water, which generally occurs only after periods of years. For meters sized 1-inch and larger - typical of multi-unit residential, commercial and industrial accounts - meter under-registration can occur from wear or from the improper application of the meter; i.e. installing the wrong type of meter or the wrong size of meter, for the flow pattern (profile) of the consumer. For instance, many larger meters have reduced accuracy at low flows. If an oversized meter is installed, most of the time the routine flow will occur in the low flow range of the meter, and a significant portion of it may not be registered. It is important to properly select and install all meters, but particularly large customer meters, size 1-inch and larger. The auditor has two options for entering data for this component of the audit. The auditor can enter a percentage under-registration (typically an estimated value), this will apply the selected percentage to the two categories of metered consumption to determine the volume of water not recorded due to customer meter inaccuracy. Note that this percentage is a composite average inaccuracy for all customer meters in the entire meter population. The percentage will be multiplied by the sum of the volumes in the Billed Metered and Unbilled Metered components. Alternatively, if the auditor has substantial data from meter testing activities, he or she can calculate their own loss volumes, and this volume may be entered directly. Note that a value of zero will be accepted but an alert will appear asking if the customer population is unmetered. Since all metered systems have some degree of inaccuracy, a positive value should be entered. A value of zero in this component is valid only if the water utility does not meter its customer population.
C22: Customer retail unit cost | D22: The Customer Retail Unit Cost represents the charge that customers pay for water service. This unit cost is applied routinely to the components of Apparent Loss, since these losses represent water reaching customers but not (fully) paid for. Since most water utilities have a rate structure that includes a variety of different costs based upon class of customer, a weighted average of individual costs and number of customer accounts in each class can be calculated to determine a single composite cost that should be entered into this cell. Finally, the weighted average cost should also include additional charges for sewer, storm water or biosolids processing, but only if these charges are based upon the volume of potable water consumed. For water utilities in regions with limited water resources and a questionable ability to meet the drinking water demands in the future, the Customer Retail Unit Cost might also be applied to value the Real Losses; instead of applying the Variable Production Cost to Real Losses. In this way, it is assumed that every unit volume of leakage reduced by leakage management activities will be sold to a customer. Note: the Free Water Audit Software allows the user to select the units that are charged to customers (either $/1,000 gallons, $/hundred cubic feet, or $/1,000 litres) and automatically converts these units to the units that appear in the "WATER SUPPLIED" box. The monetary units are United States dollars, $.
C24: Infrastructure Leakage Index (ILI) | D24: The ratio of the Current Annual Real Losses (Real Losses) to the Unavoidable Annual Real Losses (UARL). The ILI is a highly effective performance indicator for comparing (benchmarking) the performance of utilities in operational management of real losses.
C26: Length of mains | D26: Length of all pipelines (except service connections) in the system starting from the point of system input metering (for example at the outlet of the treatment plant). It is also recommended to include in this measure the total length of fire hydrant lead pipe. Hydrant lead pipe is the pipe branching from the water main to the fire hydrant. Fire hydrant leads are typically of a sufficiently large size that is more representative of a pipeline than a service connection. The average length of hydrant leads across the entire system can be assumed if not known, and multiplied by the number of fire hydrants in the system, which can also be assumed if not known. This value can then be added to the total pipeline length. Total length of mains can therefore be calculated as: Length of Mains, miles = (total pipeline length, miles) + [ {(average fire hydrant lead length, ft) x (number of fire hydrants)} / 5,280 ft/mile ] or Length of Mains, kilometres = (total pipeline length, kilometres) + [ {(average fire hydrant lead length, metres) x (number of fire hydrants)} / 1,000 metres/kilometre ]
... C53: Units and Conversions | D53: The user may develop an audit based on one of three unit selections: 1) Million Gallons (US) 2) Megalitres (Thousand Cubic Metres) 3) Acre-feet Once this selection has been made in the instructions sheet, all calculations are made on the basis of the chosen units. Should the user wish to make additional conversions, a unit converter is provided below (use drop down menus to select units from the yellow unit boxes):
E54: Enter Units: | G54: Convert From… | I54: Converts to…..
E55: 1 | G55: Million Gallons (US) | H55: = | I55: =E55*INDEX(Sheet1!N2:P4,MATCH(G55,Sheet1!M2:M4,0),MATCH(J55,Sheet1!N1:P1,0)) -> 3.0688833 | J55: Acre-feet
G56: ="(conversion factor = "&INDEX(Sheet1!N2:P4,MATCH(G55,Sheet1!M2:M4,0),MATCH(J55,Sheet1!N1:P1,0))&")" -> (conversion factor = 3.06888328973723)
C59: Use of Option Buttons
C61: Variable production cost (applied to Real Losses) | D61: The cost to produce and supply the next unit of water (e.g., $/million gallons). This cost is determined by calculating the summed unit costs for ground and surface water treatment and all power used for pumping from the source to the customer. It may also include other miscellaneous unit costs that apply to the production of drinking water. It should also include the unit cost of bulk water purchased as an import if applicable. It is common to apply this unit cost to the volume of Real Losses. However, if water resources are strained and the ability to meet future drinking water demands is in question, then the water auditor can be justified in applying the Customer Retail Rate to the Real Loss volume, rather than applying the Variable Production Cost. The Free Water Audit Software applies the Variable Production costs to Real Losses by default. However, the auditor has the option on the Reporting Worksheet to select the Customer Retail Cost as the basis for the Real Loss cost evaluation if the auditor determines that this is warranted.
C63: Volume from own sources | D63: The volume of water withdrawn (abstracted) from water resources (rivers, lakes, streams, wells, etc) controlled by the water utility, and then treated for potable water distribution. Most water audits are compiled for utility retail water distribution systems, so this volume should reflect the amount of treated drinking water that entered the distribution system. Often the volume of water measured at the effluent of the treatment works is slightly less than the volume measured at the raw water source, since some of the water is used in the treatment process. Thus, it is useful if flows are metered at the effluent of the treatment works. If metering exists only at the raw water source, an adjustment for water used in the treatment process should be included to account for water consumed in treatment operations such as filter backwashing, basin flushing and cleaning, etc. If the audit is conducted for a wholesale water agency that sells untreated water, then this quantity reflects the measure of the raw water, typically metered at the source.
C65: Volume from own sources: Master meter and supply error adjustment | D65: An estimate or measure of the degree of inaccuracy that exists in the master (production) meters measuring the annual Volume from own Sources, and any error in the data trail that exists to collect, store and report the summary production data. This adjustment is a weighted average number that represents the collective error for all master meters for all days of the audit year and any errors identified in the data trail. Meter error can occur in different ways. A meter or meters may be inaccurate by under-registering flow (did not capture all the flow), or by over-registering flow (overstated the actual flow). Data error can occur due to data gaps caused by temporary outages of the meter or related instrumentation. All water utilities encounter some degree of inaccuracy in master meters and data errors in archival systems are common; thus a value of zero should not be entered. Enter a negative percentage or value for metered data under-registration; or, enter a positive percentage or value for metered data over-registration.
C67: Water exported | D67: The Water Exported volume is the bulk water conveyed and sold by the water utility to neighboring water systems that exists outside of their service area. Typically this water is metered at the custody transfer point of interconnection between the two water utilities. Usually the meter(s) are owned by the water utility that is selling the water: i.e. the exporter. If the water utility who is compiling the annual water audit sells bulk water in this manner, they are an exporter of water. Note: The Water Exported volume is sold to wholesale customers who are typically charged a wholesale rate that is different than retail rates charged to the retail customers existing within the service area. Many state regulatory agencies require that the Water Exported volume be reported to them as a quantity separate and distinct from the retail customer billed consumption. For these reasons - and others - the Water Exported volume is always quantified separately from Billed Authorized Consumption in the standard water audit. Be certain not to "double-count" this quantity by including it in both the Water Exported box and the Billed Metered Consumption box of the water audit Reporting Worksheet. This volume should be included only in the Water Exported box.
C69: Water exported: Master meter and supply error adjustment | D69: An estimate or measure of the volume in which the Water Exported volume is incorrect. This adjustment is a weighted average that represents the collective error for all of the metered and archived exported flow for all days of the audit year. Meter error can occur in different ways. A meter may be inaccurate by under-registering flow (did not capture all the flow), or by over-registering flow (overstated the actual flow). Error in the metered, archived data can also occur due to data gaps caused by temporary outages of the meter or related instrumentation. All water utilities encounter some degree of error in their metered data, particularly if meters are aged and infrequently tested. Occasional errors also occur in the archived data. Thus, a value of zero should not be entered. Enter a negative percentage or value for metered data under-registration; or enter a positive percentage or value for metered data over-registration. If regular meter accuracy testing is conducted on the meter(s) - which is usually conducted by the water utility selling the water - then the results of this testing can be used to help quantify the meter error adjustment. Corrections to data gaps or other errors found in the archived data should also be included as a portion of this meter error adjustment.
C71: Water imported | D71: The Water Imported volume is the bulk water purchased to become part of the Water Supplied volume. Typically this is water purchased from a neighboring water utility or regional water authority, and is metered at the custody transfer point of interconnection between the two water utilities. Usually the meter(s) are owned by the water supplier selling the water to the utility conducting the water audit. The water supplier selling the bulk water usually charges the receiving utility based upon a wholesale water rate.
C73: Water imported: Master meter and supply error adjustment | D73: An estimate or measure of the volume in which the Water Imported volume is incorrect. This adjustment is a weighted average that represents the collective error for all of the metered and archived imported flow for all days of the audit year. Meter error can occur in different ways. A meter may be inaccurate by under-registering flow (did not capture all the flow), or by over-registering flow (overstated the actual flow). Error in the metered, archived data can also occur due to data gaps caused by temporary outages of the meter or related instrumentation. All water utilities encounter some level of meter inaccuracy, particularly if meters are aged and infrequently tested. Occasional errors also occur in the archived metered data. Thus, a value of zero should not be entered. Enter a negative percentage or value for metered data under-registration; or, enter a positive percentage or value for metered data over-registration. If regular meter accuracy testing is conducted on the meter(s) - which is usually conducted by the water utility selling the water - then the results of this testing can be used to help quantify the meter error adjustment.
C75: WATER LOSSES | D75: = apparent losses + real losses Water Losses are the difference between Water Supplied and Authorized Consumption. Water losses can be considered as a total volume for the whole system, or for partial systems such as transmission systems, pressure zones or district metered areas (DMA); if one of these configurations are the basis of the water audit.

Sheet Loss Control Planning
B2: AWWA Free Water Audit Software: Determining Water Loss Standing
F4: Water Audit Report for: | G4: =IF(ISBLANK(Instructions!D18),"<< Please enter system details and contact information on the Instructions tab >>",Instructions!D18&IF(ISBLANK(Instructions!D36),""," ("&Instructions!D36&")")) -> Suez Water DE
F5: Reporting Year: | G5: =IF(ISBLANK(Instructions!D26),"",Instructions!D26) -> 2020 | H5: =IF(ISBLANK(Instructions!D26),"",IF(Instructions!E26="Calendar Year","1/"&Instructions!D26&" - "&"12/"&Instructions!D26,IF(OR(ISBLANK(Instructions!D28),ISBLANK(Instructions!D30)),"",MONTH(Instructions!D28)&"/"&YEAR(Instructions!D28)&" - "&MONTH(Instructions!D30)&"/"&YEAR(Instructions!D30)))) -> 1/2020 - 12/2020
F6: Data Validity Score: | G6: =IF(ISBLANK(Instructions!$D$34),"N/A*",IF(GradingAssessment!M24>0,"N/A*",ROUND(GradingAssessment!G24,0))) -> 70 | H6: =IF(G6="N/A*","* Confirm Units and Data Grading are Complete","")
C8: Water Loss Control Planning Guide
D9: Water Audit Data Validity Level / Score
C10: Functional Focus Area | D10: Level I (0-25) | G10: Level II (26-50) | J10: Level III (51-70) | M10: Level IV (71-90) | P10: Level V (91-100)
C11: Audit Data Collection | D11: Launch auditing and loss control team; address production metering deficiencies | G11: Analyze business process for customer metering and billing functions and water supply operations. Identify data gaps. | J11: Establish/revise policies and procedures for data collection | M11: Refine data collection practices and establish as routine business process | P11: Annual water audit is a reliable gauge of year-to-year water efficiency standing
C12: Short-term loss control | D12: Research information on leak detection programs. Begin flowcharting analysis of customer billing system | G12: Conduct loss assessment investigations on a sample portion of the system: customer meter testing, leak survey, unauthorized consumption, etc. | J12: Establish ongoing mechanisms for customer meter accuracy testing, active leakage control and infrastructure monitoring | M12: Refine, enhance or expand ongoing programs based upon economic justification | P12: Stay abreast of improvements in metering, meter reading, billing, leakage management and infrastructure rehabilitation
C13: Long-term loss control | G13: Begin to assess long-term needs requiring large expenditure: customer meter replacement, water main replacement program, new customer billing system or Automatic Meter Reading (AMR) system. | J13: Begin to assemble economic business case for long-term needs based upon improved data becoming available through the water audit process. | M13: Conduct detailed planning, budgeting and launch of comprehensive improvements for metering, billing or infrastructure management | P13: Continue incremental improvements in short-term and long-term loss control interventions
C14: Target-setting | J14: Establish long-term apparent and real loss reduction goals (+10 year horizon) | M14: Establish mid-range (5 year horizon) apparent and real loss reduction goals | P14: Evaluate and refine loss control goals on a yearly basis
C15: Benchmarking | J15: Preliminary Comparisons - can begin to rely upon the Infrastructure Leakage Index (ILI) for performance comparisons for real losses (see below table) | M15: Performance Benchmarking - ILI is meaningful in comparing real loss standing | P15: Identify Best Practices/ Best in class - the ILI is very reliable as a real loss performance indicator for best in class service
C16: For validity scores of 50 or below, the shaded blocks should not be focus areas until better data validity is achieved.
E18: 0 | H18: 26 | K18: 51 | N18: 71 | Q18: 91
E19: 25 | H19: 51 | K19: 71 | N19: 91 | Q19: 100
E20: =IF(AND(GradingAssessment!$G$24>=E18,GradingAssessment!$G$24<='Loss Control Planning'!E19),1,0) -> 0 | H20: =IF(AND(GradingAssessment!$G$24>=H18,GradingAssessment!$G$24<'Loss Control Planning'!H19),1,0) -> 0 | K20: =IF(AND(GradingAssessment!$G$24>=K18,GradingAssessment!$G$24<'Loss Control Planning'!K19),1,0) -> 1 | N20: =IF(AND(GradingAssessment!$G$24>=N18,GradingAssessment!$G$24<'Loss Control Planning'!N19),1,0) -> 0 | Q20: =IF(AND(GradingAssessment!$G$24>=Q18,GradingAssessment!$G$24<='Loss Control Planning'!Q19),1,0) -> 0
C21: Once data have been entered into the Reporting Worksheet, the performance indicators are automatically calculated. How does a water utility operator know how well his or her system is performing? The AWWA Water Loss Control Committee provided the following table to assist water utilities is gauging an approximate Infrastructure Leakage Index (ILI) that is appropriate for their water system and local conditions. The lower the amount of leakage and real losses that exist in the system, then the lower the ILI value will be. Note: this table offers an approximate guideline for leakage reduction target-setting. The best means of setting such targets include performing an economic assessment of various loss control methods. However, this table is useful if such an assessment is not possible.
C23: General Guidelines for Setting a Target ILI (without doing a full economic analysis of leakage control options)
C24: Target ILI Range | D24: Financial Considerations | I24: Operational Considerations | N24: Water Resources Considerations
B25: 1 | C25: 1.0 - 3.0 | D25: Water resources are costly to develop or purchase; ability to increase revenues via water rates is greatly limited because of regulation or low ratepayer affordability. | I25: Operating with system leakage above this level would require expansion of existing infrastructure and/or additional water resources to meet the demand. | N25: Available resources are greatly limited and are very difficult and/or environmentally unsound to develop. | S25: =IF(AND('Reporting Worksheet'!#REF!>='Loss Control Planning'!U25,'Reporting Worksheet'!#REF!<='Loss Control Planning'!V25),1,0) -> #REF! | U25: 1 | V25: 3
B26: 2 | C26: >3.0 -5.0 | D26: Water resources can be developed or purchased at reasonable expense; periodic water rate increases can be feasibly imposed and are tolerated by the customer population. | I26: Existing water supply infrastructure capability is sufficient to meet long-term demand as long as reasonable leakage management controls are in place. | N26: Water resources are believed to be sufficient to meet long-term needs, but demand management interventions (leakage management, water conservation) are included in the long-term planning. | S26: =IF(AND('Reporting Worksheet'!#REF!>='Loss Control Planning'!U26,'Reporting Worksheet'!#REF!<='Loss Control Planning'!V26),1,0) -> #REF! | U26: 3 | V26: 5
B27: 3 | C27: >5.0 - 8.0 | D27: Cost to purchase or obtain/treat water is low, as are rates charged to customers. | I27: Superior reliability, capacity and integrity of the water supply infrastructure make it relatively immune to supply shortages. | N27: Water resources are plentiful, reliable, and easily extracted. | S27: =IF(AND('Reporting Worksheet'!#REF!>='Loss Control Planning'!U27,'Reporting Worksheet'!#REF!<='Loss Control Planning'!V27),1,0) -> #REF! | U27: 5 | V27: 8
C28: Greater than 8.0 | D28: Although operational and financial considerations may allow a long-term ILI greater than 8.0, such a level of leakage is not an effective utilization of water as a resource. Setting a target level greater than 8.0 - other than as an incremental goal to a smaller long-term target - is discouraged. | S28: =IF('Reporting Worksheet'!#REF!>'Loss Control Planning'!U28,1,0) -> #REF! | U28: 8
B29: 4 | C29: Less than 1.0 | D29: If the calculated Infrastructure Leakage Index (ILI) value for your system is 1.0 or less, two possibilities exist. a) you are maintaining your leakage at low levels in a class with the top worldwide performers in leakage control. b) A portion of your data may be flawed, causing your losses to be greatly understated. This is likely if you calculate a low ILI value but do not employ extensive leakage control practices in your operations. In such cases it is beneficial to validate the data by performing field measurements to confirm the accuracy of production and customer meters, or to identify any other potential sources of error in the data. | S29: =IF('Reporting Worksheet'!#REF!<1,1,0) -> #REF! | U29: 1

Sheet Example Audits
A1: AWWA Free Water Audit Software: Examples of Completed and Validated Audits

Sheet Acknowledgements
B2: AWWA Free Water Audit Software: Acknowledgements
C4: AWWA Water Audit Software Version 5.0 Developed by the Water Loss Control Committee of the American Water Works Association August, 2014
C6: This software is intended to serve as a basic tool to compile a preliminary, or “top-down”, water audit. It is recommended that users also refer to the current edition of the AWWA M36 Publication, Water Audits and Loss Control Programs, for detailed guidance on compiling a comprehensive, or “bottom-up”, water audit using the same water audit methodology.
C8: DEVELOPED BY: | D8: Andrew Chastain-Howley, PG*, MCSM. Black & Veatch
D9: Will J. Jernigan, P.E. Cavanaugh & Associates, P.A.
D10: George Kunkel, P.E. Philadelphia Water Department
D11: Alain Lalonde, P.Eng. Master Meter Canada Inc.
D12: Ralph Y. McCord, P.E. Louisville Water Company
D13: David A. Sayers Delaware River Basin Commission
D14: Brian M. Skeens, P.E. CH2M HILL
D15: Reinhard Sturm Water Systems Optimization, Inc.
D16: Isabel Szendrey Ramos, P.E. Autoridad de Acueductos y Alcantarillados
D17: John H. Van Arsdel M.E. Simpson Company, Inc.
C19: REFERENCES: | D19: - Alegre, H., Hirner, W., Baptista, J. and Parena, R. Performance Indicators for Water Supply Services. IWA Publishing ‘Manual of Best Practice’ Series, 2000. ISBN 1 900222 272
D20: - Kunkel, G. et al, 2003. Water Loss Control Committee Report: Applying Worldwide Best Management Practices in Water Loss Control. Journal AWWA, 95:8:65 - AWWA Water Audits and Loss Control Programs, M36 Publication, 3rd Edition, 2009 - Service Connection Diagrams courtesy of Ronnie McKenzie, WRP Pty Ltd.
C22: VERSION HISTORY:
C23: Version: | D23: Release Date: | E23: Number of Worksheets: | F23: Key Features and Developments
C24: v1 | D24: 2005/ 2006 | E24: 5 | F24: The AWWA Water Audit Software was piloted in 2005 (v1.0 beta). The early versions (1.x) of the software restricted data entry to units of Million Gallons per year. For each entry into the audit, users identified whether the input was measured or estimated.
C25: v2 | D25: 2006 | E25: 5 | F25: The most significant enhancement in v2 of the software was to allow the user to choose the volumetric units to be used in the audit, Million Gallons or Thousand Cubic Metres (megalitres) per year. Two financial performance indicators were added to provide feedback to the user on the cost of Real and Apparent losses.
C26: v3 | D26: 2007 | E26: 7 | F26: In v3, the option to report volumetric units in acre-feet was added. Another new feature in v3 was the inclusion of default values for two water audit components (unbilled unmetered and unauthorized consumption). v3 also included two examples of completed audits in units of million gallons and Megalitres. Several checks were added into v3 to provide instant feedback to the user on common data entry problems, in order to help the user complete an accurate water audit.
C27: v4 - v4.2 | D27: 2010 | E27: 10 | F27: v4 (and versions 4.x) of the software included a new approach to data grading. The simple "estimated" or "measured" approach was replaced with a more granular scale (typically 1-10) that reflected descriptions of utility practices and served to describe the confidence and accuracy of the input data. Each input value had a corresponding scale fully described in the Grading Matrix tab. The Grading Matrix also showed the actions required to move to a higher grading score. Grading descriptions were available on the Reporting Worksheet via a pop-up box next to each water audit input. A water audit data validity score is generated (max = 100) and priority areas for attention (to improve audit accuracy) are identified, once a user completes the requied data grading. A service connection diagram was also added to help users understand the impact of customer service line configurations on water losses and how this information should be entered into the water audit software. An acknoweldgements section was also added. Minor bug fixes resulted in the release of versions 4.1 and 4.2. A French language version was also made available for v4.2.
C28: v5 | D28: 2014 | E28: 12 | F28: In v5, changes were made to the way Water Supplied information is entered into software, with each major component having a corresponding Master Meter Error Adjustment entry (and data grading requirement). This required changes to the data validity score calculation; v5 of the software uses a weighting system that is, in part, proportional to the volume of input components. The Grading Matrix was updated to reflect the new audit inputs and also to include clarifications and additions to the scale descriptions. The appearance of the software was updated in v5 to make the software more user-friendly and several new features were added to provide more feedback to the user. Notably, a dashboard tab has been added to provide more visual feedback on the water audit results and associated costs of Non-Revenue Water. A comments sheet was added to allow the user to track notes, comments and to cite sources used.

Sheet Sheet1
B1: $/100 cubic feet (ccf) | C1: $/1000 gallons (US) | D1: $/1000 litres | F1: Conversion table | M1: FROM: TO: | N1: Million gallons (US) | O1: Megalitres (thousand cubic metres) | P1: Acre-feet
A2: Million gallons (US) | B2: =1000000/(F2*100) -> 1336.8056 | C2: 1000 | D2: =1000/F5 -> 3785.4118 | F2: 7.4805195 | G2: gallons / cubic foot | H2: converting FROM volume unit TO pricing UNITS | M2: Million gallons (US) | N2: 1 | O2: =F4 -> 3.7854118 | P2: 3.0688833
A3: Megalitres (thousand cubic metres) | B3: =1000000/F4/(F2*100) -> 353.14667 | C3: =1000/F4 -> 264.17205 | D3: 1000 | F3: 43560 | G3: sq feet / acre | M3: Megalitres (thousand cubic metres) | N3: =1/O2 -> 0.26417205 | O3: 1 | P3: 0.81071319
A4: Acre-feet | B4: =F3/100 -> 435.6 | C4: =F3*F2/1000 -> 325.85143 | D4: =F3*F2*F4/1000 -> 1233.4818 | F4: 3.7854118 | G4: litres / gallon | M4: Acre-feet | N4: =325851.427242/1000000 -> 0.32585143 | O4: 1.2334818 | P4: 1
F5: =1/F4 -> 0.26417205 | G5: gallons / litre
A7: losses | B7: 1 | C7: million gallons (US) | D7: =MATCH(C7,A2:A4,0) -> 1
E8: =INDEX($B$2:$D$4,MATCH(C7,A2:A4,0),MATCH(C9,B1:D1,0)) -> 1336.8056
A9: cost | B9: 10 | C9: $/100 cubic feet (ccf) | D9: =MATCH(C9,B1:D1,0) -> 1
B11: cost = | C11: =B7*B9*E8 -> 13368.056 | I11: Multiply By…
G12: million | I12: From | L12: To
G13: m3 | H13: 547500 | I13: Million Gallons (US) | J13: = | K13: =H13*INDEX(N2:P4,MATCH(I13,M2:M4,0),MATCH(L13,N1:P1,0)) -> 2072513 | L13: Megalitres (thousand cubic metres)
B15: customer cost
B16: $/100 cubic feet (ccf) | C16: $/1000 gallons (US) | D16: $/1000 litres | H16: =1500000000/1000000*365 -> 547500 | I16: 1.5 BGD
A17: million gallons (US) | B17: =1000000/(7.48*100) -> 1336.8984 | C17: 1000 | D17: =1000000/CONVERT(1000,"l","gal") -> 3785.4118
A18: thousand cubic metres | B18: =1000000/CONVERT((7.48*100),"gal","l") -> 353.17119 | C18: =1000000/CONVERT(1000,"gal","l") -> 264.17205 | D18: 1000
A19: acre-feet | B19: =43560/100 -> 435.6 | C19: =43560/(1000/7.48) -> 325.8288 | D19: =F3/(CONVERT(1000,"l","gal")/F2) -> 1233.4818
A22: customer cost | B22: 5 | C22: $/1000 gallons (US) | D22: =MATCH(C22,B16:D16,0) -> 2
E23: =INDEX($B$2:$D$4,MATCH(C24,A2:A4,0),MATCH(C22,B1:D1,0)) -> 1000
A24: marginal production | B24: 5000 | C24: million gallons (US) | D24: =MATCH(C24,A17:A19,0) -> 1
B26: cost = | C26: =(B22*E23)/B24 -> 1
C27: >1 = higher customer cost
C28: <1 = lower customer cost
A31: =IF(ISERROR(1/G60),"",(((G24+G25+G40)*G62)+(G37*G61)*INDEX(Sheet1!B2:D4,MATCH(Instructions!G24,Sheet1!A2:A4,0),MATCH('Reporting Worksheet'!I61:J61,Sheet1!B1:D1,0)))/G60)
B33: (reallosses * real loss cost per unit) + (apparent losses * apparent loss cost per unit * unit conversion factor)
A37: =IF(ISBLANK(Instructions!$G$26),"",IF(Instructions!$G$26="Megalitres (thousand cubic metres)",IF(AND(G55>25,G50*20+G51>3000),(((18*G50)+(0.8*G51)+(25*(G51*G53/1000)))*G55/1000000)*365,"Not valid"),IF(AND(G55>40,G50*32+G51>3000),(((5.41*G50)+(0.15*G51)+(7.5*(G51*G53/5280)))*G55)/1000000*365,"Not Valid")))
A38: IF(AND(G55>40,G50*32+G51>3000),(((5.41*G50)+(0.15*G51)+(7.5*(G51*G53/5280)))*G55)/1000000,"Not Valid")))
A39: Logic:
A40: If volume unit is blank show nothing
A42: If instructions is tcm Then
A43: If pressure > 25 AND length of mains * 20 + # connections > 3000 Then
A44: (((18 * length of mains) + (0.8 * # connections) + (25 * (# service connections * avg len of pipe / 1000))) * pressure) /1000
A45: Otherwise not valid
A47: If instructions is gallons Then
A48: If pressure > 40 AND length of mains * 32 + # connections > 3000 Then
A49: (((5.41 * length of mains) + (0.15 * # connections) + (7.5 * (# service connections * avg len of pipe / 5280))) * pressure) /1000000
A50: Otherwise not valid
... A75: Use this abbreviation for labelling the Dashboard NRW chart:
A76: =IF('Performance Indicators'!R21=FALSE,"Var. Prod. Cost","Cust.Ret.Unit Cost") -> Cust.Ret.Unit Cost
A77: ----------------------
A78: Data for plotting the Cost/Volume Bar Chart on the Dashboard
E79: =IF(Dashboard!S6=1,"Total Volume of NRW = ","Total Cost of NRW =$")&IF(Dashboard!S6=1,TEXT(SUM(C90,C91,C94,C95,C96,C98),"#,###")&" "&'Reporting Worksheet'!I15,TEXT(SUM(D90,D91,D94,D95,D96,D98),"#,###")) -> Total Volume of NRW = 983 MG/Yr
C80: ="Volume ("&'Reporting Worksheet'!I15&")" -> Volume (MG/Yr) | D80: Cost $ | E80: =OFFSET(B80,0,Dashboard!$S$6) -> Volume (MG/Yr)
A81: Vol. from own sources: | C81: ='Reporting Worksheet'!G15 -> 5243.759 | D81: =C81*('Reporting Worksheet'!$G$78) -> 1818011.2 | E81: =OFFSET(B81,0,Dashboard!$S$6) -> 5243.759
A82: =A81&" MA" -> Vol. from own sources: MA | C82: ='Reporting Worksheet'!S15 -> 0 | D82: =C82*('Reporting Worksheet'!$G$78) -> 0 | E82: =OFFSET(B82,0,Dashboard!$S$6) -> 0
A83: Water imported: | C83: ='Reporting Worksheet'!G16 -> 233.6473 | D83: =C83*('Reporting Worksheet'!$G$78) -> 81005.519 | E83: =OFFSET(B83,0,Dashboard!$S$6) -> 233.6473
A84: =A83&" MA" -> Water imported: MA | C84: ='Reporting Worksheet'!S16 -> 0 | D84: =C84*('Reporting Worksheet'!$G$78) -> 0 | E84: =OFFSET(B84,0,Dashboard!$S$6) -> 0
A85: Water exported: | C85: ='Reporting Worksheet'!G17 -> 54.335 | D85: =C85*('Reporting Worksheet'!$G$78) -> 18837.945 | E85: =OFFSET(B85,0,Dashboard!$S$6) -> 54.335
A86: =A85&" MA" -> Water exported: MA | C86: ='Reporting Worksheet'!S17 -> 0 | D86: =C86*('Reporting Worksheet'!$G$78) -> 0 | E86: =OFFSET(B86,0,Dashboard!$S$6) -> 0
A87: WATER SUPPLIED: | C87: ='Reporting Worksheet'!G19 -> 5423.0713 | D87: =C87*('Reporting Worksheet'!$G$78) -> 1880178.8 | E87: =OFFSET(B87,0,Dashboard!$S$6) -> 5423.0713
A88: Billed metered: | C88: ='Reporting Worksheet'!G23 -> 4440.547 | D88: =C88*('Reporting Worksheet'!$G$77*1000) -> 24645036 | E88: =OFFSET(B88,0,Dashboard!$S$6) -> 4440.547
A89: Billed unmetered: | C89: ='Reporting Worksheet'!G24 -> 0 | D89: =C89*('Reporting Worksheet'!$G$77*1000) -> 0 | E89: =OFFSET(B89,0,Dashboard!$S$6) -> 0
A90: ="Unbilled metered (valued at "&A76&")" -> Unbilled metered (valued at Cust.Ret.Unit Cost) | C90: ='Reporting Worksheet'!G25 -> 53.98333 | D90: =IF(ISBLANK(Instructions!D34),"",IF(ISBLANK('Reporting Worksheet'!G78),"",'Reporting Worksheet'!G25*(IF('Performance Indicators'!R21=FALSE,'Reporting Worksheet'!G78,IF('Performance Indicators'!R21=TRUE,'Reporting Worksheet'!G77*INDEX(Sheet1!B2:D4,MATCH(Instructions!D34,Sheet1!A2:A4,0),MATCH('Reporting Worksheet'!I77,Sheet1!B1:D1,0)),""))))) -> 299607.48 | E90: =OFFSET(B90,0,Dashboard!$S$6) -> 53.98333
A91: ="Unbilled unmetered (valued at "&A76&")" -> Unbilled unmetered (valued at Cust.Ret.Unit Cost) | C91: ='Reporting Worksheet'!G26 -> 67.788391 | D91: =IF(ISBLANK(Instructions!D34),"",IF(ISBLANK('Reporting Worksheet'!G78),"",'Reporting Worksheet'!G26*(IF('Performance Indicators'!R21=FALSE,'Reporting Worksheet'!G78,IF('Performance Indicators'!R21=TRUE,'Reporting Worksheet'!G77*INDEX(Sheet1!B2:D4,MATCH(Instructions!D34,Sheet1!A2:A4,0),MATCH('Reporting Worksheet'!I77,Sheet1!B1:D1,0)),""))))) -> 376225.57 | E91: =OFFSET(B91,0,Dashboard!$S$6) -> 67.788391
A92: Auth. Consumption | B92: ----------- | C92: ='Reporting Worksheet'!G30 -> 4562.3187 | D92: =C92*('Reporting Worksheet'!$G$77*1000) -> 25320869 | E92: =OFFSET(B92,0,Dashboard!$S$6) -> 4562.3187
A93: Water Losses | C93: ='Reporting Worksheet'!G35 -> 860.75258 | D93: =C93*('Reporting Worksheet'!$G$77*1000) -> 4777176.8 | E93: =OFFSET(B93,0,Dashboard!$S$6) -> 860.75258
A94: Unauth. consumption | C94: ='Reporting Worksheet'!G38 -> 13.557678 | D94: =C94*('Reporting Worksheet'!$G$77*1000) -> 75245.114 | E94: =OFFSET(B94,0,Dashboard!$S$6) -> 13.557678
A95: Cust. metering inaccuracies | C95: ='Reporting Worksheet'!G42 -> 0 | D95: =C95*('Reporting Worksheet'!$G$77*1000) -> 0 | E95: =OFFSET(B95,0,Dashboard!$S$6) -> 0
A96: Syst. data handling errors | C96: ='Reporting Worksheet'!G43 -> 11.101367 | D96: =C96*('Reporting Worksheet'!$G$77*1000) -> 61612.59 | E96: =OFFSET(B96,0,Dashboard!$S$6) -> 11.101367
A97: Apparent Losses: | C97: ='Reporting Worksheet'!G47 -> 24.659046 | D97: =C97*('Reporting Worksheet'!$G$77*1000) -> 136857.7 | E97: =OFFSET(B97,0,Dashboard!$S$6) -> 24.659046
A98: ="Real Losses (valued at "&A76&")" -> Real Losses (valued at Cust.Ret.Unit Cost) | C98: ='Reporting Worksheet'!G52 -> 836.09353 | D98: ='Performance Indicators'!I21 -> 4640319.1 | E98: =OFFSET(B98,0,Dashboard!$S$6) -> 836.09353
A99: NON-REVENUE WATER: | C99: ='Reporting Worksheet'!G58 -> 982.5243 | D99: =D97+D98+D90+D91 -> 5453009.9 | E99: =OFFSET(B99,0,Dashboard!$S$6) -> 982.5243
